Workbook

Sheet RawData
B1: REV | C1: REV Grow | D1: Rev 5YR CAGR | E1: EPS | F1: EPS Grow | G1: NI 5YR CAGR | H1: GM | I1: SG&A 2 REV | J1: EBITDA % | K1: OPMargin | L1: DEG OF OP LEV | M1: FCF | N1: FCF Grow | O1: INVEN TURN | P1: CAPEX 2 REV | Q1: R&D | R1: R&D / REV | S1: CASH | T1: CASH / ASSET | U1: NET DEBT | V1: N DEBT/EQUITY | W1: ROA | X1: ROE | Y1: CROCI | Z1: PE | AA1: Forward PE | AB1: P/S | AC1: P/B | AD1: EV/EBITDA | AE1: EV/FCF | AF1: DIVIDEND | AG1: MKT CAP | AH1: EV | AI1: SHARE $ | AJ1: Shares Out | AK1: EBITDA | AL1: EBITDA Growth | AM1: EBTIDA 5yr CAGR
A2: EUSP | B2: No data | C2: -0.56 | D2: 0.045778085 | E2: -0.091298684 | F2: -20.9459 | G2: No data | H2: 0.2963 | I2: 0 | J2: -2.1912167 | K2: No data | L2: No data | M2: 3.96015 | N2: 2.8110893 | O2: No data | P2: 0.0017576141 | Q2: 0.72726 | R2: No data | S2: No data | T2: 0.9741707 | U2: No data | V2: -0.9794 | W2: -0.8302 | X2: No data | Y2: No data | AA2: No data | AB2: 1.2801472 | AC2: No data | AD2: 0.30796728 | AE2: -0.558441 | AF2: No data | AG2: 4.19544 | AH2: -2.21151 | AI2: 0.051 | AJ2: 82.26 | AK2: -7.18099 | AL2: No data | AM2: 0.32108018
A3: GNE | C3: 0.1312 | D3: 0.06155537 | E3: 0.18308796 | F3: 0.41564506 | H3: 0.2572 | I3: 0.18829301 | J3: 0.0038859139 | M3: 34.961 | N3: 0.6393161 | P3: 0.017451437 | Q3: No data | S3: No data | T3: 0.27727455 | V3: -0.506248 | W3: 0.0127 | Z3: 79.08767 | AA3: 24.905401 | AB3: 0.7936849 | AD3: 150.76901 | AE3: 8.098859 | AG3: 377.5485 | AH3: 283.1442 | AI3: 14.48 | AJ3: 26.49 | AK3: 1.878 | AM3: -0.4143127
A4: ENG | C4: -0.3871 | D4: -0.13786851 | E4: -1.3306202 | F4: -0.6921076 | H4: 0.0676 | I4: 0.33289343 | J4: -0.22335532 | M4: -1.679 | N4: 0.16113244 | P4: 0.004239152 | Q4: No data | S4: No data | T4: 0.09304611 | V4: -0.32514092 | W4: -0.4368 | AA4: 1.0699426 | AB4: 0.09278145 | AD4: -0.67358994 | AE4: -2.2406194 | AG4: 2.32 | AH4: 3.762 | AI4: No data | AJ4: 5.16 | AK4: -5.585 | AM4: 0.019537123
A5: WAVE | C5: 0.2645 | D5: No data | E5: -0.3556507 | F5: No data | H5: 0.75 | I5: 12.327381 | J5: -12.755953 | M5: 0 | N5: No data | P5: No data | Q5: 0.359 | S5: No data | T5: 0.614155 | V5: -0.7908 | W5: -0.2247 | AB5: 205.09525 | AD5: -13.758749 | AG5: 34.82723 | AH5: 29.485 | AI5: 5.9 | AJ5: 5.84 | AK5: -2.143 | AM5: No data
A6: GAME | C6: -0.4248 | D6: -0.12822299 | E6: -0.31139722 | F6: -0.46814975 | H6: 0.1917 | I6: 0.38631046 | J6: -0.48854575 | M6: -22.84184 | N6: 0.720281 | P6: 0.00525471 | Q6: 2.7225 | S6: 6.01222 | T6: 0.049638845 | V6: -0.0764 | W6: -0.3931 | AB6: 0.633634 | AD6: -1.1254569 | AE6: -1.7270608 | AG6: 46.263557 | AH6: 39.449177 | AI6: 0.4621 | AJ6: 98.38 | AK6: -35.05172 | AM6: -0.15716498
A7: PI | C7: 0.0424 | D7: 0.20215866 | E7: -0.4117569 | F7: -1.2009693 | H7: 0.5221 | I7: 0.23744632 | J7: 0.020047527 | M7: 40.267 | N7: 0.3955268 | P7: 0.042643726 | Q7: 101.58 | S7: No data | T7: 0.10015509 | V7: 1.1727 | W7: -0.0249 | AA7: 86.15877 | AB7: 15.177392 | AD7: 788.76843 | AE7: 141.29155 | AG7: 6404.815 | AH7: 5689.3867 | AI7: 181.36 | AJ7: 30.11 | AK7: 7.213 | AM7: -0.030969055
A8: IDT | C8: 0.0252 | D8: -0.015953567 | E8: 3.2392502 | F8: 0.096753284 | H8: 0.367 | I8: 0.2334118 | J8: 0.10358164 | M8: 92.905 | N8: 2.1266053 | P8: 0.017123276 | Q8: 51.836 | S8: No data | T8: 0.2890048 | V8: -0.5902 | W8: 0.1322 | Z8: 16.068533 | AA8: 15.501221 | AB8: 1.0483767 | AD8: 8.653185 | AE8: 12.008185 | AG8: 1272.4558 | AH8: 1115.6205 | AI8: 52.05 | AJ8: 25.07 | AK8: 128.926 | AM8: 0.19638498
A9: BKTI | C9: 0.0463 | D9: 0.1438503 | E9: 3.1868632 | F9: 3.362202 | H9: 0.4366 | I9: 0.25739858 | J9: 0.1696627 | M9: 12.283 | N9: 8.8942795 | P9: 0.029134642 | Q9: 2.306 | S9: No data | T9: 0.19615728 | V9: -0.3224 | W9: 0.2218 | Z9: 27.447052 | AA9: 21.765203 | AB9: 4.1654506 | AD9: 23.659426 | AE9: 25.597176 | AG9: 288.68884 | AH9: 314.4101 | AI9: 87.47 | AJ9: 3.73 | AK9: 13.289 | AM9: 0.74884135
A10: RDVT | C10: 0.2227 | D10: 0.2003615 | E10: 0.79503196 | F10: 1.2094674 | H10: 0.835 | I10: 0.5771015 | J10: 0.2579462 | M10: 18.936 | N10: 1.5683286 | P10: 0.12050911 | Q10: No data | S10: No data | T10: 0.40467203 | V10: -0.4458 | W10: 0.1081 | Z10: 63.98485 | AA10: 43.60722 | AB10: 8.293414 | AD10: 30.11736 | AE10: 35.456608 | AG10: 745.3378 | AH10: 671.4063 | AI10: 50.87 | AJ10: 14.09 | AK10: 22.293 | AM10: No data
A11: INOD | C11: 0.7357 | D11: 0.3285289 | E11: 1.055995 | F11: 0.68085533 | H11: 0.4132 | I11: 0.24464601 | J11: 0.19577551 | M11: 40.697 | N11: 3.68933 | P11: 0.044052217 | Q11: No data | S11: No data | T11: 0.48300374 | V11: -0.6696978 | W11: 0.2567 | Z11: 59.81089 | AA11: 70.241 | AB11: 8.43839 | AD11: 41.706306 | AE11: 47.843838 | AG11: 2107.9204 | AH11: 1947.1006 | AI11: 63.16 | AJ11: 31.86 | AK11: 46.686 | AM11: 0.7872666
A12: EACO | C12: 0.1631 | D12: 0.12024409 | E12: 6.1020575 | F12: 1.0429871 | H12: 0.3011 | I12: 0.20105627 | J12: 0.10431313 | M12: 18.429 | N12: -0.7756313 | P12: 0.0016393769 | Q12: No data | S12: No data | T12: 0.01653093 | V12: 0.0077 | W12: 0.1472 | Z12: 13.929728 | AB12: 1.027658 | AD12: 9.878493 | AE12: 22.476803 | AG12: 413.23517 | AH12: 414.225 | AI12: 85 | AJ12: 4.86 | AK12: 41.932 | AM12: 0.25658518
A13: IIIV | C13: -0.2369 | D13: 0.0904248 | E13: 0.5524884 | F13: -0.8439366 | H13: 0.6647 | I13: 0.5156077 | J13: 0.17667738 | M13: -4.441 | N13: -0.13457575 | P13: 0.043769866 | Q13: No data | S13: No data | T13: 0.10443429 | V13: -0.1711 | W13: 0.0271 | Z13: 48.906002 | AA13: 23.408056 | AB13: 3.774949 | AD13: 19.736616 | AE13: -181.81152 | AG13: 884.8759 | AH13: 807.425 | AI13: 27.02 | AJ13: 32.35 | AK13: 40.91 | AM13: 0.11801729
A14: GLAE | C14: 1 | D14: 0.14869836 | E14: -133.33333 | F14: -1.2 | H14: 1 | I14: 20 | J14: No data | M14: -3.4 | N14: 0.8292683 | P14: No data | Q14: No data | S14: No data | T14: 0.13304721 | V14: 2.069 | W14: -0.2439 | AB14: 4.2 | AE14: -3.7764707 | AG14: 0.7 | AH14: 12.84 | AI14: 28 | AJ14: 0.03 | AK14: No data | AM14: No data
A15: FC | C15: -0.0899 | D15: 0.061245136 | E15: 0.25230262 | F15: -0.8689001 | H15: 0.7604 | I15: 0.68404186 | J15: 0.05302789 | M15: 13.163 | N15: 0.26486507 | P15: 0.059213605 | Q15: No data | S15: No data | T15: 0.1304917 | V15: -0.46143386 | W15: -0.0062 | Z15: 78.952805 | AA15: 58.008152 | AB15: 0.9069904 | AD15: 14.923895 | AE15: 16.056538 | AG15: 225.53098 | AH15: 211.3522 | AI15: 19.92 | AJ15: 12.16 | AK15: 14.162 | AM15: -0.0015182684
A16: AVNW | C16: 0.1089 | D16: 0.12976143 | E16: 1.0422119 | F16: -3.6116316 | H16: 0.3425 | I16: 0.19384913 | J16: 0.08916928 | M16: 11.868 | N16: -0.17378317 | P16: 0.02045438 | Q16: 32.458 | S16: No data | T16: 0.10077629 | V16: 0.15799814 | W16: 0.0214 | Z16: 20.792318 | AA16: 8.618701 | AB16: 0.61354935 | AD16: 7.9107966 | AE16: 26.954567 | AG16: 274.66278 | AH16: 319.8968 | AI16: 21.67 | AJ16: 12.84 | AK16: 40.438 | AM16: 0.25286326
A17: CCRD | C17: 0.2361 | D17: 0.1262796 | E17: 1.028498 | F17: 4.0326633 | H17: 0.4541 | I17: 0.12169794 | J17: 0.21816751 | M17: 8.916 | N17: 207.34883 | P17: 0.08116282 | Q17: 11.213 | S17: 26.621 | T17: 0.37532428 | V17: -0.47270757 | W17: 0.123 | Z17: 24.297565 | AA17: 22.272728 | AB17: 3.0038283 | AD17: 11.885643 | AE17: 18.84826 | AG17: 183.9 | AH17: 168.0511 | AI17: 23.6 | AJ17: 7.79 | AK17: 14.139 | AM17: 0.008844381
A18: ACFN | C18: 0.363 | D18: 0.1484058 | E18: 2.5176 | F18: 54.210526 | H18: 0.7281 | I18: 0.45967594 | J18: 0.18732932 | M18: 0.849 | N18: -141.5 | P18: 0.0050973967 | Q18: 1.012 | S18: No data | T18: 0.2195168 | V18: -0.4199 | W18: 0.5661 | Z18: 7.9996824 | AB18: 4.5831056 | AD18: 23.335278 | AE18: 56.565372 | AG18: 51.26969 | AH18: 48.024 | AI18: 20.14 | AJ18: 2.5 | AK18: 2.058 | AM18: -0.4104765
A19: TSAT | C19: -0.2579 | D19: -0.12115695 | E19: -3.055823 | F19: -4.2065806 | H19: 0.9429 | I19: 0.42947268 | J19: 0.04726162 | M19: -1009.604 | N19: 1.9206115 | P19: 2.4447832 | Q19: No data | S19: 467.09 | T19: 0.06744001 | V19: 4.2608 | W19: -0.0225 | AB19: 1.4564012 | AD19: 163.88249 | AE19: -3.46692 | AG19: 474.00955 | AH19: 2520.8516 | AI19: 33.78 | AJ19: 51.09 | AK19: 21.358 | AM19: -0.5451669
A20: CSPI | C20: -0.2162 | D20: -0.07033556 | E20: -0.009229209 | F20: -0.7283582 | H20: 0.3248 | I20: 0.42442587 | J20: -0.06792662 | M20: 1.894 | N20: 0.4735 | P20: 0.0086410055 | Q20: 3.25 | S20: No data | T20: 0.38528448 | V20: -0.5951606 | W20: -0.0013 | AA20: No data | AB20: 2.6744697 | AD20: -30.354218 | AE20: 47.11795 | AG20: 114.54882 | AH20: 89.2414 | AI20: 11.74 | AJ20: 9.86 | AK20: -2.94 | AM20: 0.26239598
A21: SPOK | C21: 0.0147 | D21: -0.014334536 | E21: 0.8055825 | F21: 0.12998775 | H21: 0.6274 | I21: 0.37097016 | J21: 0.17679387 | M21: 22.623 | N21: 0.7818829 | P21: 0.022964241 | Q21: 11.662 | S21: No data | T21: 0.10197326 | V21: -0.1437756 | W21: 0.079 | Z21: 16.435312 | AA21: 16.22549 | AB21: 1.9518101 | AD21: 10.174661 | AE21: 11.111037 | AG21: 268.31177 | AH21: 251.365 | AI21: 13.24 | AJ21: 20.6 | AK21: 24.705 | AM21: 0.3226834
A22: SILC | C22: -0.4262 | D22: -0.022336941 | E22: 0 | F22: -1.1495436 | H22: 0.2896 | I22: 0.18201664 | J22: -0.19371673 | M22: 0 | N22: 17.513794 | P22: 0.043460462 | Q22: 19.513 | S22: No data | T22: 0 | V22: 0 | W22: -0.0984 | AB22: 1.4409026 | AG22: 88.98035 | AH22: 84.483 | AI22: 14.9 | AJ22: 5.67 | AK22: 0 | AM22: -0.22127618
A23: SODI | C23: -0.1594 | D23: 0.05985148 | E23: -0.17272727 | F23: -1.0566008 | H23: 0.2126 | I23: 0.2515356 | J23: 0.03632365 | M23: 1.472 | N23: 3.0413222 | P23: 0.011678168 | Q23: No data | S23: No data | T23: 0.11592434 | V23: 0.0564 | W23: -0.0148 | AA23: No data | AB23: 3.1935618 | AD23: 89.98852 | AE23: 29.282948 | AG23: 39.761353 | AH23: 43.1045 | AI23: 21 | AJ23: 2.09 | AK23: 0.479 | AM23: -0.14264044
A24: THRY | C24: -0.1073 | D24: -0.019909434 | E24: 0.40959156 | F24: -1.0525557 | H24: 0.6736 | I24: 0.62315637 | J24: 0.1411758 | M24: 36.166 | N24: 0.49513978 | P24: 0.04012605 | Q24: No data | S24: No data | T24: 0.016459128 | V24: 1.1608 | W24: 0.0255 | Z24: 13.403597 | AA24: 10.574368 | AB24: 0.3067393 | AD24: 4.503289 | AE24: 13.711337 | AG24: 241.41597 | AH24: 495.8842 | AI24: 5.49 | AJ24: 43.58 | AK24: 110.116 | AM24: -0.18989244
A25: GAMB | C25: 0.2421 | D25: 0.38248485 | E25: 0.053852715 | F25: -0.9479942 | H25: 0.9317 | I25: 0.5895909 | J25: 0.0870249 | M25: 41.879 | N25: 26.966516 | P25: 0.0056562624 | Q25: No data | S25: No data | T25: 0.024105664 | V25: 0.6047 | W25: 0.0069 | Z25: 93.21721 | AB25: 1.1425999 | AD25: 19.141623 | AE25: 6.1462164 | AG25: 185.49243 | AH25: 257.3974 | AI25: 5.02 | AJ25: 35.17 | AK25: 13.447 | AM25: -0.056652006
A26: INLX | C26: -0.0263 | D26: 0.24878028 | E26: -0.38877454 | F26: -11.167007 | H26: 0.655 | I26: 0.67242086 | J26: -0.011173609 | M26: 1.35092 | N26: 0.6290957 | P26: 0.052598514 | Q26: No data | S26: 2.07148 | T26: 0.12072694 | V26: -0.1602 | W26: -0.0958 | AB26: 2.1353362 | AD26: -181.42876 | AE26: 25.702362 | AG26: 36.056942 | AH26: 34.721832 | AI26: 8.1638 | AJ26: 4.48 | AK26: -0.19138 | AM26: -0.3473945
A27: QXO | C27: 81.0375 | D27: 32.85121 | E27: -0.2637287 | F27: -11.401957 | H27: 0.2249 | I27: 0.1856629 | J27: 0.045423165 | M27: 78.922 | N27: 2.5809157 | P27: 0.010688081 | Q27: No data | S27: 2306.9 | T27: 0.13861166 | V27: 0.0992 | W27: -0.0162 | AA27: 82.51473 | AB27: 3.6908894 | AD27: 85.85466 | AE27: 230.41145 | AG27: 16647.37 | AH27: 18184.533 | AI27: 25.52 | AJ27: 674.39 | AK27: 211.806 | AM27: No data
A28: OOMA | C28: 0.0422 | D28: 0.09820402 | E28: 0.08137681 | F28: -1.2314509 | H28: 0.61 | I28: 0.41501996 | J28: 0.06529731 | M28: 18.885 | N28: 1.0217497 | P28: 0.021611799 | Q28: 49.658 | S28: No data | T28: 0.1422341 | V28: -0.2414 | W28: 0.015 | Z28: 147.46216 | AA28: 19.392475 | AB28: 1.2539992 | AD28: 17.94503 | AE28: 16.38761 | AG28: 317.12402 | AH28: 309.48 | AI28: 12 | AJ28: 27.6 | AK28: 17.246 | AM28: 1.3713306
A29: MGNI | C29: 0.0627 | D29: 0.30154607 | E29: 0.4035503 | F29: 2.3522234 | H29: 0.623 | I29: 0.37787536 | J29: 0.20196138 | M29: 160.728 | N29: 1.0249268 | P29: 0.08779259 | Q29: 86.335 | S29: No data | T29: 0.16507281 | V29: 0.0918 | W29: 0.0204 | Z29: 37.91349 | AA29: 17.821783 | AB29: 3.1283154 | AD29: 16.01217 | AE29: 14.135577 | AG29: 2339.3057 | AH29: 2271.983 | AI29: 15.3 | AJ29: 143.65 | AK29: 141.891 | AM29: 0.8258396
A30: NEON | C30: -0.4854 | D30: -0.15698351 | E30: 0.5353397 | F30: -1.832453 | H30: 0.9654 | I30: 2.6968594 | J30: 3.9795175 | M30: -5.89 | N30: 0.8742764 | P30: 0.040964954 | Q30: 3.595 | S30: 11.585 | T30: 0.35299674 | V30: -0.43110844 | W30: 0.4317 | Z30: 3.5117888 | AB30: 14.358853 | AD30: 2.2865608 | AE30: -3.3941257 | AG30: 31.384066 | AH30: 19.9914 | AI30: 1.88 | AJ30: 16.78 | AK30: 8.743 | AM30: 0.012710306
A31: AEYE | C31: 0.1857 | D31: 0.16468386 | E31: -0.28285024 | F31: 0.064868145 | H31: 0.7861 | I31: 0.75500757 | J31: 0.024911482 | M31: 0.829 | N31: 0.81434184 | P31: 0.049468894 | Q31: 4.854 | S31: 4.55 | T31: 0.14928801 | V31: 1.4877 | W31: -0.1104 | AB31: 3.0029135 | AD31: 129.07837 | AE31: 153.36815 | AG31: 118.03896 | AH31: 127.1422 | AI31: 9.56 | AJ31: 12.42 | AK31: 0.985 | AM31: -0.28026178
A32: AGS | C32: 0.066 | D32: 0.066023216 | E32: 1.3215129 | F32: 9.751862 | H32: 0.8747 | I32: 0.24533103 | J32: 0.418717 | M32: 24.917 | N32: 0.5554515 | P32: 0.19445185 | Q32: 59.913 | S32: No data | T32: 0.0556264 | V32: 4.2302 | W32: 0.0798 | Z32: 9.451289 | AA32: 16.172123 | AB32: 1.316834 | AD32: 6.1567907 | AE32: 40.734596 | AG32: 518.4 | AH32: 1014.9839 | AI32: 12.49 | AJ32: 41.51 | AK32: 164.856 | AM32: 0.10334572
A33: RDCM | C33: 0.1204 | D33: 0.13718125 | E33: 0.58515286 | F33: 0.9627537 | H33: 0.7332 | I33: 0.3735821 | J33: 0.14835821 | M33: -3.45 | N33: 0.8603491 | P33: 0.0014925373 | Q33: 19.574 | S33: No data | T33: 0 | V33: 0 | W33: 0.0713 | Z33: 21.908806 | AA33: 12.085218 | AB33: 3.0672328 | AD33: 20.674507 | AE33: -59.56655 | AG33: 208.06052 | AH33: 205.5046 | AI33: 12.82 | AJ33: 16.03 | AK33: 9.94 | AM33: -0.45185173
A34: BNED | C34: 0.0138 | D34: -0.04034894 | E34: -2.055683 | F34: -0.14804222 | H34: 0.2239 | I34: 0.17853361 | J34: 0.0063043754 | M34: -68.689 | N34: -3.8654473 | P34: 0.00759727 | Q34: No data | S34: No data | T34: 0.008445348 | V34: 0.466 | W34: -0.0691 | AB34: 0.19220723 | AD34: 43.844345 | AE34: -6.3089795 | AG34: 283.29736 | AH34: 433.3575 | AI34: 8.85 | AJ34: 34.05 | AK34: 9.884 | AM34: -0.099583894
A35: ASUR | C35: 0.1454 | D35: 0.14631532 | E35: -0.61552596 | F35: 0.40622172 | H35: 0.671 | I35: 0.58313006 | J35: 0.097945794 | M35: -8.562 | N35: 0.37021664 | P35: 0.22169033 | Q35: 6.579 | S35: No data | T35: 0.048134994 | V35: 0.25299478 | W35: -0.0362 | AA35: 14.319161 | AB35: 2.0858583 | AD35: 25.073792 | AE35: -37.868397 | AG35: 261.81335 | AH35: 324.2292 | AI35: 9.92 | AJ35: 27.76 | AK35: 12.931 | AM35: 0.31969485
A36: RELL | C36: 0.0617 | D36: 0.063783444 | E36: 0.012146308 | F36: -1.3055556 | H36: 0.3113 | I36: 0.2956371 | J36: 0.014628845 | M36: 8.597 | N36: 4.115366 | P36: 0.013870948 | Q36: No data | S36: No data | T36: 0.1782103 | V36: -0.22372119 | W36: 0.0009 | Z36: 883.396 | AA36: 43.406147 | AB36: 0.7411076 | AD36: 39.04324 | AE36: 13.93785 | AG36: 151.12935 | AH36: 119.8237 | AI36: 10.73 | AJ36: 14.49 | AK36: 3.069 | AM36: 0.22119126
A37: EXPI | C37: -0.1637 | D37: 0.20546083 | E37: -0.1216822 | F37: -0.42658794 | H37: 0.0692 | I37: 0.075601004 | J37: -0.0012465938 | M37: 108.388 | N37: 0.533395 | P37: 0.0028006737 | Q37: 66.979 | S37: No data | T37: 0.2458043 | V37: -0.4793 | W37: -0.0438 | AB37: 0.3903017 | AD37: -288.8033 | AE37: 12.368758 | AG37: 1531.1859 | AH37: 1340.625 | AI37: 9.15 | AJ37: 158.84 | AK37: -4.642 | AM37: 0.6583921
A38: ACCS | C38: -0.3445 | D38: 0.029354563 | E38: -1.4855297 | F38: 8.827351 | H38: 0.7708 | I38: 0.8104076 | J38: -0.76118946 | M38: 3.011 | N38: 2.7077339 | P38: 0.012048192 | Q38: No data | S38: No data | T38: 0.09024653 | V38: -0.036789626 | W38: -0.1121 | AA38: 18.600954 | AB38: 2.0892644 | AD38: -2.668694 | AE38: 13.159117 | AG38: 37.52722 | AH38: 39.6221 | AI38: 10.53 | AJ38: 3.87 | AK38: -14.847 | AM38: No data
A39: MITK | C39: 0.0442 | D39: 0.1214368 | E39: 0.19268346 | F39: 1.6833435 | H39: 0.8509 | I39: 0.46717978 | J39: 0.28375936 | M39: 54.185 | N39: 1.7912396 | P39: 0.006427701 | Q39: 35.284 | S39: No data | T39: 0.33576557 | V39: 0.00983526 | W39: 0.0204 | Z39: 53.196056 | AA39: 9.1855755 | AB39: 2.603984 | AD39: 9.223078 | AE39: 8.679071 | AG39: 487.61346 | AH39: 470.2755 | AI39: 10.25 | AJ39: 45.65 | AK39: 50.989 | AM39: 0.16470626
A40: CTLP | C40: 0.1294 | D40: 0.1481149 | E40: 0.8146811 | F40: 3.4285293 | H40: 0.4111 | I40: 0.21004911 | J40: -0.021895595 | M40: 22.685 | N40: -3.3463638 | P40: 0.053256124 | Q40: 17.963 | S40: No data | T40: 0.1411631 | V40: -0.0656 | W40: 0.1662 | Z40: 13.318094 | AA40: 23.725182 | AB40: 2.558332 | AD40: -157.21867 | AE40: 34.51395 | AG40: 788.92883 | AH40: 782.949 | AI40: 10.85 | AJ40: 73.7 | AK40: -4.98 | AM40: 0.15815394
A41: AEHR | C41: -0.0323 | D41: 0.24810356 | E41: -0.22172609 | F41: -1.2283303 | H41: 0.3621 | I41: 0.32458025 | J41: -0.10792354 | M41: -16.248 | N41: 37.786045 | P41: 0.10887395 | Q41: 10.951 | S41: No data | T41: 0.15759376 | V41: -0.18553197 | W41: -0.0459 | AA41: 168.09062 | AB41: 13.716775 | AD41: -123.39395 | AE41: -46.568913 | AG41: 773.5699 | AH41: 756.6517 | AI41: 25.97 | AJ41: 30.01 | AK41: -6.132 | AM41: 0.24019842
A42: MHH | C42: 0.0516 | D42: 0.002102193 | E42: 0.07418803 | F42: -1.2172172 | H42: 0.281 | I42: 0.263355 | J42: 0.020225 | M42: 7.28 | N42: 4.1576242 | P42: 0.00179 | Q42: No data | S42: No data | T42: 0.25303465 | V42: -0.3181 | W42: 0.0078 | Z42: 96.241936 | AA42: 9.887142 | AB42: 0.41769 | AD42: 13.746601 | AE42: 7.6380496 | AG42: 84.80566 | AH42: 55.605 | AI42: 7.14 | AJ42: 11.7 | AK42: 4.045 | AM42: -0.24195422
A43: AATC | C43: -0.116 | D43: -0.041387446 | E43: 0.5878182 | F43: -0.54174346 | H43: 0.9646 | I43: 0.5307771 | J43: 0.4511988 | M43: 6.281 | N43: 1.5167834 | P43: 0.041149464 | Q43: 2.565 | S43: No data | T43: 0.18344763 | V43: -0.0755 | W43: 0.2014 | Z43: 10.122177 | AB43: 2.782265 | AD43: 6.010175 | AE43: 5.078172 | AG43: 31.364702 | AH43: 31.896 | AI43: 6 | AJ43: 5.5 | AK43: 5.307 | AM43: 0.145564
A44: TSSI | C44: 0.9166 | D44: 0.3217636 | E44: 0.16908145 | F44: 0.10838446 | H44: 0.123 | I44: 0.08136282 | J44: 0.04514195 | M44: -42.079 | N44: -2.2913854 | P44: 0.16572772 | Q44: No data | S44: No data | T44: 0.4273934 | V44: -0.7381 | W44: 0.0379 | Z44: 62.514248 | AA44: 86.35621 | AB44: 1.2985369 | AD44: 24.350863 | AE44: -6.1347346 | AG44: 249.22112 | AH44: 258.1435 | AI44: 10.57 | AJ44: 28.85 | AK44: 10.601 | AM44: 0.7171874
A45: CODA | C45: 0.2934 | D45: 0.02787626 | E45: 0.30497244 | F45: 0.14409667 | H45: 0.6592 | I45: 0.41517782 | J45: 0.21431349 | M45: 5.42756 | N45: -7.840009 | P45: 0.035896488 | Q45: 2.52321 | S45: 26.19644 | T45: 0.42311653 | V45: -0.4574 | W45: 0.0579 | Z45: 38.183777 | AA45: 30.722351 | AB45: 5.380752 | AD45: 20.086443 | AE45: 19.310675 | AG45: 115.30089 | AH45: 104.80985 | AI45: 11.645 | AJ45: 11.25 | AK45: 5.21794 | AM45: 0.062692635
A46: AXIL | C46: 0.0007 | D46: 0.881705 | E46: 0.1921716 | F46: -0.2529343 | H46: 0.7014 | I46: 0.6385724 | J46: 0.07050315 | M46: -0.15481 | N46: -0.44051448 | P46: 0.016394699 | Q46: No data | S46: 4.08662 | T46: 0.2661272 | V46: -0.3873 | W46: 0.0947 | Z46: 41.62946 | AA46: No data | AB46: 1.9836773 | AD46: 26.082327 | AE46: -323.83295 | AG46: 49.39891 | AH46: 50.13258 | AI46: 8 | AJ46: 6.76 | AK46: 1.92209 | AM46: No data
A47: DUOT | C47: 1.59 | D47: 0.1372892 | E47: -0.49188295 | F47: -0.045136247 | H47: 0.2638 | I47: 0.69596523 | J47: -0.35969716 | M47: -16.47932 | N47: 1.4899052 | P47: 0.42881882 | Q47: 1.20949 | S47: 33.2015 | T47: 0.47570518 | V47: -0.6698 | W47: -0.2364 | AB47: 11.054488 | AD47: -25.887815 | AE47: -10.750984 | AG47: 207.21518 | AH47: 177.1687 | AI47: 10.3 | AJ47: 20.42 | AK47: -6.84371 | AM47: 0.05008719
A48: ALAR | C48: 0.4297 | D48: No data | E48: No data | F48: No data | H48: 0.7092 | I48: No data | J48: No data | M48: No data | N48: No data | P48: No data | Q48: 3.557 | S48: No data | T48: No data | V48: -0.6742 | W48: 0.0322 | AG48: 212.56042 | AH48: 23.69217 | AI48: 9.63 | AJ48: No data | AK48: No data | AM48: No data
A49: SEAC | C49: 0.1305 | D49: -0.16045333 | E49: -3.5356588 | F49: 0.4347279 | H49: 0.655 | I49: 0.39704534 | J49: -0.28810817 | M49: -0.753 | N49: 0.17414431 | P49: 0.0016787741 | Q49: 8.077 | S49: No data | T49: 0.33875406 | V49: -0.44867414 | W49: -0.2198 | AB49: 0.25987425 | AD49: 0.5589575 | AE49: 7.00664 | AG49: 9.070868 | AH49: -5.276 | AI49: 3.51 | AJ49: 2.58 | AK49: -9.439 | AM49: 0.2931744
A50: INTT | C50: -0.0081 | D50: 0.18187235 | E50: -0.06674679 | F50: -1.180147 | H50: 0.424 | I50: 0.3418967 | J50: 0.046160042 | M50: 10.324 | N50: 1.5623487 | P50: 0.011172128 | Q50: 9.041 | S50: No data | T50: 0.12861754 | V50: -0.0892 | W50: -0.0055 | AA50: 314.11765 | AB50: 0.8217951 | AD50: 16.172716 | AE50: 8.79599 | AG50: 100.7413 | AH50: 90.8098 | AI50: 8.01 | AJ50: 12.48 | AK50: 5.615 | AM50: 0.1048253
A51: MRAM | C51: -0.0041 | D51: 0.051605757 | E51: -0.024846895 | F51: -1.3700325 | H51: 0.5131 | I51: 0.38354275 | J51: 0.021233361 | M51: 4.678 | N51: 1.271887 | P51: 0.12100593 | Q51: 13.946 | S51: No data | T51: 0.56379557 | V51: -0.6876 | W51: -0.0072 | AA51: 50.165016 | AB51: 4.858208 | AD51: 189.06673 | AE51: 46.03399 | AG51: 271.5354 | AH51: 215.347 | AI51: 11.4 | AJ51: 22.86 | AK51: 1.139 | AM51: -0.307943
A52: CXDO | C52: 0.1291 | D52: 0.33239052 | E52: 0.1418809 | F52: 2.541836 | H52: 0.744 | I52: 0.448648 | J52: 0.11045127 | M52: 9.082 | N52: 1.3526958 | P52: 0.00067826244 | Q52: 5.876 | S52: No data | T52: 0.37617335 | V52: -0.4619 | W52: 0.0624 | Z52: 50.535343 | AA52: 20.360254 | AB52: 3.3209856 | AD52: 26.200888 | AE52: 21.140728 | AG52: 206.51265 | AH52: 192.0001 | AI52: 7.17 | AJ52: 30.73 | AK52: 7.328 | AM52: 0.45597357
A53: AIOT | C53: 0.9297 | D53: 0.28976965 | E53: -0.30869824 | F53: 0.13153282 | H53: 0.5462 | I53: 0.5167294 | J53: 0.11717039 | M53: -24.913 | N53: 0.9907341 | P53: 0.10003827 | Q53: 18.576 | S53: No data | T53: 0.029777147 | V53: 0.5273 | W53: -0.0448 | AB53: 1.7596855 | AD53: 19.972464 | AE53: -40.003452 | AG53: 743.3958 | AH53: 996.606 | AI53: 5.6 | AJ53: 133.82 | AK53: 49.899 | AM53: 0.96575135
A54: HHS | C54: -0.1107 | D54: -0.017350659 | E54: -0.7354926 | F54: -0.8173715 | H54: 0.1847 | I54: 0.13342044 | J54: 0.01407328 | M54: -0.39 | N54: 0.055045873 | P54: 0.011747712 | Q54: No data | S54: No data | T54: 0.07 | V54: -0.292 | W54: -0.0558 | AA54: 2.7854133 | AB54: 0.13501717 | AD54: 7.106644 | AE54: -42.78564 | AG54: 21.799496 | AH54: 16.6864 | AI54: 3.04 | AJ54: 7.41 | AK54: 2.348 | AM54: 0.23539628
A55: WYY | C55: 0.1625 | D55: -0.010384806 | E55: -0.21477655 | F55: -0.3760732 | H55: 0.1339 | I55: 0.14322154 | J55: 0.018516755 | M55: 4.04287 | N55: -1.1820498 | P55: 0.0015290645 | Q55: No data | S55: No data | T55: 0.08907429 | V55: -0.5429607 | W55: -0.0307 | AB55: 0.46566314 | AD55: 22.597631 | AE55: 14.947559 | AG55: 62.214397 | AH55: 60.43104 | AI55: 6.8 | AJ55: 9.89 | AK55: 2.67422 | AM55: -0.09479094
A56: BLZE | C56: 0.1573 | D56: 0.22504596 | E56: -0.59923744 | F56: -0.25421682 | H56: 0.5912 | I56: 0.46859205 | J56: -0.045030627 | M56: 3.083 | N56: -1.8178066 | P56: 0.09432606 | Q56: 45.719 | S56: No data | T56: 0.15181434 | V56: 0.1067 | W56: -0.1931 | AB56: 1.9889679 | AD56: -45.552597 | AE56: 94.38534 | AG56: 289.654 | AH56: 290.99 | AI56: 4.89 | AJ56: 57.7 | AK56: -6.388 | AM56: -6.887837
A57: EVLV | C57: 0.4161 | D57: 0.77653176 | E57: -0.34371778 | F57: 0.0890155 | H57: 0.5635 | I57: 0.6786104 | J57: -0.27825436 | M57: -96.201 | N57: 0.38169792 | P57: 0.26453286 | Q57: 20.597 | S57: No data | T57: 0.10353316 | V57: -0.0291 | W57: -0.2165 | AB57: 8.417518 | AD57: -24.982876 | AE57: -9.863719 | AG57: 1258.9929 | AH57: 948.8996 | AI57: 6.58 | AJ57: 174.62 | AK57: -37.982 | AM57: -0.03718961
A58: SBET | C58: 0.6821 | D58: 0.22400485 | E58: -0.005237023 | F58: -0.6823536 | H58: 0.8332 | I58: 2.5322955 | J58: -8.929912 | M58: 13.58128 | N58: -0.4818018 | P58: 0.0006867068 | Q58: 0.277 | S58: No data | T58: 0.0036213226 | V58: -0.0036267187 | W58: -0.0012 | AA58: No data | AB58: 163.28302 | AD58: -18.18978 | AE58: 156.74928 | AG58: 1967.1678 | AH58: 2128.859 | AI58: 10.88 | AJ58: 196.69 | AK58: -117.03569 | AM58: 4.517231
A59: TACT | C59: 0.0827 | D59: 0.08129764 | E59: -0.79782397 | F59: 3.0985773 | H59: 0.4793 | I59: 0.37424886 | J59: -0.011898603 | M59: 8 | N59: -250 | P59: 0.028890923 | Q59: 6.588 | S59: No data | T59: 0.44552386 | V59: -0.5363 | W59: -0.1815 | AB59: 0.85091525 | AD59: -43.017223 | AE59: 3.2155375 | AG59: 41.461597 | AH59: 25.7243 | AI59: 4.23 | AJ59: 10.11 | AK59: -0.598 | AM59: -0.34812024
A60: GSIT | C60: 0.22 | D60: -0.054954648 | E60: -0.3309024 | F60: -0.23794276 | H60: 0.558 | I60: 0.46986347 | J60: -0.46116385 | M60: -7.877 | N60: 0.41772285 | P60: 0.001956377 | Q60: 13.868 | S60: No data | T60: 0.48714152 | V60: -0.6569309 | W60: -0.2456 | AB60: 10.86948 | AD60: -21.283726 | AE60: -29.935558 | AG60: 279.1143 | AH60: 235.8024 | AI60: 7.41 | AJ60: 35.24 | AK60: -11.079 | AM60: -0.09450546
A61: SOBR | C61: 0.9807 | D61: No data | E61: -5.4248686 | F61: -0.08034516 | H61: 0.2787 | I61: 21.399319 | J61: -21.786858 | M61: -6.97925 | N61: 1.1387053 | P61: 0.10481369 | Q61: 0.4123 | S61: 4.71166 | T61: 0.65528095 | V61: -0.7455 | W61: -0.7871 | AB61: 7.596452 | AD61: 0.21713687 | AE61: 0.24684457 | AG61: 2.6534462 | AH61: -1.72279 | AI61: 1.82 | AJ61: 1.52 | AK61: -7.93412 | AM61: -0.23108828
A62: INVE | C62: -0.66 | D62: -0.22948265 | E62: -0.61629474 | F62: -1.1989506 | H62: -0.0365 | I62: 0.8271633 | J62: -0.99277765 | M62: -17.177 | N62: 2.5409763 | P62: 0.06927095 | Q62: 3.427 | S62: No data | T62: 0.83606577 | V62: -0.8788919 | W62: -0.0934 | AB62: 3.7434704 | AD62: 2.0064743 | AE62: 2.553036 | AG62: 83.28526 | AH62: -43.8535 | AI62: 3.47 | AJ62: 23.75 | AK62: -21.856 | AM62: 0.7088183
A63: CURI | C63: 0.2862 | D63: No data | E63: -0.0935506 | F63: -0.6311625 | H63: 0.545 | I63: 0.65913355 | J63: 0.3481943 | M63: 12.046 | N63: 4.688984 | P63: 0.0011562429 | Q63: No data | S63: 14.108 | T63: 0.18884948 | V63: -0.2989 | W63: -0.0672 | AB63: 3.212869 | AD63: 8.618812 | AE63: 16.590818 | AG63: 210.16612 | AH63: 199.853 | AI63: 3.67 | AJ63: 58.3 | AK63: 23.188 | AM63: 1.8478525
A64: APPS | C64: 0.0682 | D64: 0.20661658 | E64: -0.6865805 | F64: -0.7439504 | H64: 0.4577 | I64: 0.26471552 | J64: 0.08796363 | M64: 16 | N64: -0.48335448 | P64: 0.055228416 | Q64: 40.338 | S64: 39.284 | T64: 0.047965813 | V64: 2.4102433 | W64: -0.0936 | AA64: 16.05392 | AB64: 1.1191677 | AD64: 20.446037 | AE64: 59.023876 | AG64: 547.2866 | AH64: 944.382 | AI64: 5.24 | AJ64: 112.15 | AK64: 46.189 | AM64: 0.14666492
A65: CMPD | C65: 0.2957 | D65: 0.0037851895 | E65: -0.18181819 | F65: 3.2105262 | H65: 0.5062 | I65: 0.5577362 | J65: -0.045184847 | M65: -0.014 | N65: -0.1627907 | P65: 0.0018256503 | Q65: No data | S65: No data | T65: 0.055555556 | V65: 2.982 | W65: -0.3032 | AB65: 2.6267457 | AD65: -61.47677 | AE65: -434.72858 | AG65: 5.50877 | AH65: 6.0862 | AI65: 4.07 | AJ65: 1.32 | AK65: -0.099 | AM65: -0.4461702
A66: SOPH | C66: 0.1366 | D66: 0.18350428 | E66: -1.1050552 | F66: 0.050170876 | H66: 0.6752 | I66: 1.1391598 | J66: -0.75918525 | M66: -46.454 | N66: 0.8933805 | P66: 0.11045472 | Q66: 34.821 | S66: 68.528 | T66: 0.46706972 | V66: -1.2489 | W66: -0.4006 | AB66: 4.7672825 | AD66: -6.279472 | AE66: -7.522011 | AG66: 354.16162 | AH66: 349.4275 | AI66: 5.15 | AJ66: 67.85 | AK66: -55.646 | AM66: -0.009278263
A67: RSSS | C67: 0.0583 | D67: 0.09579182 | E67: 0.04094737 | F67: -1.6320273 | H67: 0.4998 | I67: 0.30484438 | J67: 0.051444795 | M67: 7.25037 | N67: 1.4079373 | P67: 0.00074606156 | Q67: 5.66874 | S67: No data | T67: 0.26270843 | V67: -0.7667 | W67: 0.03 | Z67: 69.60154 | AA67: 20.155586 | AB67: 1.8992027 | AD67: 32.20575 | AE67: 11.271659 | AG67: 95.23599 | AH67: 81.7237 | AI67: 2.85 | AJ67: 32.87 | AK67: 2.53755 | AM67: 0.24963982
A68: ELVA | C68: 0.4306 | D68: 0.34445542 | E68: 0.07389585 | F68: -3.2769127 | H68: 0.309 | I68: 0.1310281 | J68: 0.10957917 | M68: -2.894 | N68: -3.18022 | P68: 0.07224329 | Q68: 4.379 | S68: No data | T68: 0.09945097 | V68: 0.5311 | W68: 0.0646 | Z68: 115.00483 | AA68: 48.428684 | AB68: 6.059619 | AD68: 57.66289 | AE68: -139.3553 | AG68: 571.59247 | AH68: 559.97406 | AI68: 8.69 | AJ68: No data | AK68: 6.994 | AM68: 0.087883994
A69: OSS | C69: 0.1433 | D69: 0.013377401 | E69: -0.28160155 | F69: -0.35932902 | H69: 0.2901 | I69: 0.30216432 | J69: -0.08706587 | M69: -7.7035 | N69: -10.720598 | P69: 0.008759454 | Q69: 5.58109 | S69: No data | T69: 0.15114558 | V69: -0.1646 | W69: -0.1764 | AB69: 3.3250332 | AD69: -37.363663 | AE69: -25.448809 | AG69: 200.3798 | AH69: 196.0449 | AI69: 11.69 | AJ69: 24.52 | AK69: -5.24694 | AM69: 0.41211525
A70: IDN | C70: 0.142 | D70: 0.15777807 | E70: 0.010346535 | F70: -1.3220339 | H70: 0.9033 | I70: 0.66947377 | J70: 0.033321194 | M70: 0.347 | N70: -0.10776398 | P70: 0.021804443 | Q70: 5.068 | S70: 7.223 | T70: 0.28598014 | V70: -0.382 | W70: 0.0089 | Z70: 582.80383 | AA70: 895.097 | AB70: 5.5447016 | AD70: 156.53415 | AE70: 330.2104 | AG70: 129.7155 | AH70: 114.583 | AI70: 6.03 | AJ70: 20.2 | AK70: 0.732 | AM70: -0.14377438
A71: RDNW | C71: -0.1244 | D71: 0.18299134 | E71: -2.679275 | F71: -0.46464 | H71: 0.269 | I71: 0.2342951 | J71: -0.03204894 | M71: 40 | N71: 0.97205347 | P71: 0.005021914 | Q71: No data | S71: 35.4 | T71: 0.05061481 | V71: 15.4387 | W71: -0.1404 | AB71: 0.20543617 | AD71: -18.016914 | AE71: 15.809842 | AG71: 224.2176 | AH71: 632.3937 | AI71: 5.91 | AJ71: 38.07 | AK71: -35.1 | AM71: 0.06251342
A72: ZDGE | C72: -0.0129 | D72: 0.21632099 | E72: -0.09730769 | F72: -0.866772 | H72: 0.9351 | I72: 0.88223654 | J72: -0.014389213 | M72: 2.5 | N72: 0.51503915 | P72: 0.019353325 | Q72: No data | S72: No data | T72: 0.5143636 | V72: -0.7143 | W72: -0.0345 | AA72: 34.653465 | AB72: 1.6787416 | AD72: -73.552444 | AE72: 12.6216 | AG72: 48.78874 | AH72: 31.554 | AI72: 3.85 | AJ72: 13 | AK72: -0.429 | AM72: 0.5115977
A73: PAYS | C73: 0.3261 | D73: 0.22969745 | E73: 0.13738863 | F73: -0.06324505 | H73: 0.5982 | I73: 0.41409996 | J73: 0.08079836 | M73: 9.84225 | N73: 0.42919394 | P73: 0.11799022 | Q73: No data | S73: 7.52905 | T73: 0.035936628 | V73: -0.1268 | W73: 0.0384 | Z73: 34.93739 | AA73: 37.274315 | AB73: 3.5282333 | AD73: 88.3841 | AE73: 26.253326 | AG73: 270.811 | AH73: 258.3918 | AI73: 4.8 | AJ73: 55.04 | AK73: 2.92351 | AM73: 0.019071344
A74: NTWK | C74: 0.077 | D74: 0.03701771 | E74: 0.041961864 | F74: -0.31589273 | H74: 0.48 | I74: 0.42659047 | J74: 0.05945687 | M74: -1.53423 | N74: -0.23527527 | P74: 0.026575431 | Q74: 1.13027 | S74: No data | T74: 0.36232233 | V74: -0.39510003 | W74: 0.0082 | Z74: 74.59154 | AB74: 0.5553851 | AD74: 5.764268 | AE74: -14.85553 | AG74: 37.39578 | AH74: 22.7918 | AI74: 3.13 | AJ74: 11.8 | AK74: 3.95398 | AM74: -0.09657143
A75: DAIO | C75: -0.2858 | D75: -0.04661085 | E75: -0.39062834 | F75: 1.06881 | H75: 0.515 | I75: 0.5313358 | J75: -0.20401098 | M75: -2.67 | N75: -4.917127 | P75: 0.03217142 | Q75: 6.587 | S75: No data | T75: 0.42583942 | V75: -0.60362273 | W75: -0.1524 | AB75: 1.7934822 | AD75: -5.9637213 | AE75: -7.634457 | AG75: 29.565647 | AH75: 20.384 | AI75: 3.2 | AJ75: 9.39 | AK75: -3.418 | AM75: 0.25224647
A76: SPRS | C76: 0.1601 | D76: 0.035382215 | E76: 0.1581296 | F76: 0.8438228 | H76: 0.2822 | I76: 0.25017256 | J76: 0.03198645 | M76: 0.93553 | N76: 0.5041196 | P76: 0.0033376229 | Q76: No data | S76: 4.2758 | T76: 0.15735206 | V76: -0.2048 | W76: 0.0347 | Z76: 21.121916 | AA76: No data | AB76: 0.5408086 | AD76: 13.116783 | AE76: 15.815207 | AG76: 18.889282 | AH76: 14.7956 | AI76: 3.35 | AJ76: 5.71 | AK76: 1.12799 | AM76: 0.031818487
A77: LTRX | C77: -0.2685 | D77: 0.1297019 | E77: -0.2609756 | F77: 1.0015589 | H77: 0.4275 | I77: 0.29605898 | J77: -0.014362521 | M77: 7.805 | N77: 0.61748415 | P77: 0.003567383 | Q77: 18.239 | S77: No data | T77: 0.18559313 | V77: -0.15485561 | W77: -0.0819 | AA77: 33.281734 | AB77: 2.1461105 | AD77: -142.63861 | AE77: 31.049711 | AG77: 247.17206 | AH77: 242.343 | AI77: 6.45 | AJ77: 39.36 | AK77: -1.699 | AM77: -0.0047577
A78: POLA | C78: -0.4432 | D78: 0.024693035 | E78: -3.2593985 | F78: 0.8126699 | H78: -0.3063 | I78: 0.5201778 | J78: -0.97561854 | M78: -0.726 | N78: 0.9404145 | P78: 0.0001201057 | Q78: 0.648 | S78: No data | T78: 0.00032399158 | V78: 1.7782 | W78: -0.5502 | AB78: 0.63228977 | AD78: -1.2827089 | AE78: -14.351851 | AG78: 5.2644444 | AH78: 10.419444 | AI78: 1.49 | AJ78: 2.66 | AK78: -8.123 | AM78: -0.094450645
A79: BLIN | C79: 0.0016 | D79: 0.07141433 | E79: -0.21345995 | F79: -0.7305046 | H79: 0.6657 | I79: 0.48565853 | J79: -0.061528455 | M79: -0.559 | N79: 0.51568264 | P79: 0.0011056911 | Q79: 4.166 | S79: No data | T79: 0.13023284 | V79: -0.1359 | W79: -0.1573 | AB79: 0.67107123 | AD79: -9.051501 | AE79: -15.317925 | AG79: 9.77952 | AH79: 8.56272 | AI79: 0.852 | AJ79: 12.11 | AK79: -0.946 | AM79: -0.41584945
A80: AMPG | C80: 0.9347 | D80: 0.43794656 | E80: -0.36927375 | F80: -0.04057577 | H80: 0.2307 | I80: 0.3873108 | J80: -0.2966053 | M80: -8.61305 | N80: 1.4593937 | P80: 0.09687333 | Q80: 4.37919 | S80: No data | T80: 0.17754653 | V80: -0.2329 | W80: -0.1683 | AB80: 3.429027 | AD80: -10.314636 | AE80: -8.017611 | AG80: 64.11759 | AH80: 69.05608 | AI80: 3.75 | AJ80: 20.64 | AK80: -6.69496 | AM80: 0.84518844
A81: PERF | C81: 0.1447 | D81: 0.15145504 | E81: 0.055719193 | F81: 0.0655276 | H81: 0.7577 | I81: 0.55640423 | J81: 0.013049132 | M81: 13.587 | N81: 1.4523784 | P81: 0.0062928805 | Q81: 14.304 | S81: 2.14 | T81: 0.6585711 | V81: -0.8294 | W81: 0.0302 | Z81: 31.766432 | AA81: 29.20792 | AB81: 2.694646 | AD81: 61.197594 | AE81: 3.932104 | AG81: 174.16342 | AH81: 53.4255 | AI81: 1.77 | AJ81: 101.85 | AK81: 0.873 | AM81: -0.96865416
A82: CREX | C82: -0.1837 | D82: 0.19030169 | E82: -0.8696768 | F82: -13.214953 | H82: 0.4313 | I82: 0.5288902 | J82: -0.017823704 | M82: -4.675 | N82: 2.9588609 | P82: 0.055772398 | Q82: 1.719 | S82: No data | T82: 0.005125192 | V82: 0.9982 | W82: -0.1423 | AB82: 0.74290097 | AD82: -69.33747 | AE82: -11.71692 | AG82: 32.924255 | AH82: 54.7766 | AI82: 3.13 | AJ82: 10.52 | AK82: -0.79 | AM82: -0.4308674
A83: ZENV | C83: 0.248 | D83: 0.43559247 | E83: -2.2933233 | F83: 0.043592673 | H83: 0.2227 | I83: 0.17131892 | J83: -0.0013156792 | M83: 41.702 | N83: -1.4890913 | P83: 0.039321862 | Q83: 36.048 | S83: 19.839 | T83: 0.011863515 | V83: 0.103 | W83: -0.0688 | AB83: 0.22863969 | AD83: -226.73402 | AE83: 7.8510365 | AG83: 52.567287 | AH83: 60.701176 | AI83: 0.885 | AJ83: 52.57 | AK83: -1.444 | AM83: -0.06630851
A84: EFOI | C84: -0.3535 | D84: -0.2530165 | E84: -0.16811846 | F84: -0.5484324 | H84: 0.1949 | I84: 0.3580119 | J84: -0.23996894 | M84: -0.85 | N84: 0.72649574 | P84: 0.013978773 | Q84: 0.325 | S84: No data | T84: 0.17259958 | V84: -0.2856688 | W84: -0.1835 | AB84: 3.417551 | AD84: -13.274002 | AE84: -14.476471 | AG84: 12.569894 | AH84: 12.305 | AI84: 2.3 | AJ84: 5.74 | AK84: -0.927 | AM84: -0.26629978
A85: AWRE | C85: 0.0273 | D85: 0.11028489 | E85: -0.26251754 | F85: -0.25 | H85: 0.9202 | I85: 0.84755296 | J85: -0.34471282 | M85: -5.809 | N85: 7.0583234 | P85: 0.0025819037 | Q85: 7.848 | S85: No data | T85: 0 | V85: 0 | W85: -0.1391 | AB85: 2.2928395 | AD85: -6.6514482 | AE85: -6.8793077 | AG85: 41.46497 | AH85: 39.9619 | AI85: 1.87 | AJ85: 21.37 | AK85: -6.008 | AM85: -0.07328069
A86: NNDM | C86: 0.4168 | D86: 0.35547808 | E86: -1.2361499 | F86: 2.0424788 | H86: 0.3362 | I86: 1.0514133 | J86: -1.5477593 | M86: -104.1 | N86: 1.3624228 | P86: 0.014799672 | Q86: 31.69 | S86: 105.885 | T86: 0.15302627 | V86: -0.6156162 | W86: -0.3173 | AB86: 4.5940056 | AD86: -0.03313798 | AE86: -0.0402488 | AG86: 364.4488 | AH86: 4.1899 | AI86: 1.73 | AJ86: 216.93 | AK86: -126.438 | AM86: -0.19502638
A87: USIO | C87: 0.0324 | D87: 0.22585636 | E87: -0.014199194 | F87: -1.1434889 | H87: 0.2375 | I87: 0.021600645 | J87: -0.013550672 | M87: 10.50015 | N87: -0.29864204 | P87: 0.017113512 | Q87: No data | S87: 4.87654 | T87: 0.049059216 | V87: -0.6307 | W87: -0.0037 | AB87: 0.44695348 | AD87: -27.241072 | AE87: 2.4407768 | AG87: 37.357124 | AH87: 25.6284 | AI87: 1.37 | AJ87: 27.31 | AK87: -0.9408 | AM87: -0.027219826
A88: PXHI | C88: 0.1061 | D88: 0.7341018 | E88: -0.40171218 | F88: 2.6766396 | H88: 0.0556 | I88: 0.07033074 | J88: -0.14415678 | M88: -0.47704 | N88: 0.2767294 | P88: 0.007193514 | Q88: No data | S88: No data | T88: 0 | V88: 1.6712 | W88: -1.0033 | AA88: No data | AB88: 0.7772175 | AD88: -5.9165764 | AE88: -132.61322 | AG88: 66.427734 | AH88: 63.26181 | AI88: 1.7 | AJ88: 33.91 | AK88: -10.69225 | AM88: 0.18844342
A89: BEEM | C89: -0.5456 | D89: 0.43670586 | E89: -1.6044359 | F89: 1.498465 | H89: 0.1495 | I89: 0 | J89: -0.937003 | M89: -6.654 | N89: 2.0819774 | P89: 0.028914269 | Q89: No data | S89: 3.348 | T89: 0.07506558 | V89: -0.1181 | W89: -0.5872 | AB89: 1.2341405 | AD89: -1.1962662 | AE89: -4.6608357 | AG89: 31.683863 | AH89: 31.0132 | AI89: 1.87 | AJ89: 18.26 | AK89: -25.925 | AM89: 0.437743
A90: MCHX | C90: -0.0432 | D90: 0.24602051 | E90: -0.1099294 | F90: 0.1547847 | H90: 0.6368 | I90: 0.5164107 | J90: -0.021185528 | M90: -1.839 | N90: 1.3672862 | P90: 0.02548716 | Q90: 10.358 | S90: 5.083 | T90: 0.1235387 | V90: -0.3207689 | W90: -0.1156 | AB90: 1.6461291 | AD90: -67.29861 | AE90: -36.04629 | AG90: 77.709694 | AH90: 66.28913 | AI90: 1.743 | AJ90: 43.91 | AK90: -0.985 | AM90: -0.52421474
A91: AXTI | C91: -0.0454 | D91: 0.008301023 | E91: -0.4890605 | F91: 1.2447573 | H91: 0.1197 | I91: 0.26931077 | J91: -0.16800532 | M91: -18.927 | N91: 1.1233975 | P91: 0.03463879 | Q91: 10.789 | S91: No data | T91: 0.06918457 | V91: 0.24246433 | W91: -0.0683 | AB91: 14.238951 | AD91: -87.61331 | AE91: -70.29618 | AG91: 1287.0587 | AH91: 1330.4957 | AI91: 22.1 | AJ91: 46.62 | AK91: -15.186 | AM91: -0.04510794
A92: NTIP | C92: -0.9203 | D92: -0.40713984 | E92: -0.1 | F92: 0.17871901 | H92: 0.72 | I92: 22.833334 | J92: -20.873333 | M92: -1.332 | N92: -5.946429 | P92: 2.76 | Q92: No data | S92: No data | T92: 0.31345445 | V92: -0.3176451 | W92: -0.0511 | AA92: No data | AB92: 202.33733 | AD92: -5.406132 | AE92: -12.707658 | AG92: 29.665558 | AH92: 16.9266 | AI92: 1.33 | AJ92: 22.82 | AK92: -3.131 | AM92: 0.027693862
A93: MAPS | C93: 0.0059 | D93: No data | E93: 0.050152652 | F93: -5.325288 | H93: 0.9502 | I93: 0.8129444 | J93: 0.12384485 | M93: 21.046 | N93: 0.83208793 | P93: 0.06411979 | Q93: No data | S93: 62.591 | T93: 0.32445532 | V93: -1.0999 | W93: 0.0422 | Z93: 16.92433 | AA93: 5.5477123 | AB93: 0.7442533 | AD93: 3.1909094 | AE93: 3.366784 | AG93: 135.26137 | AH93: 70.85734 | AI93: 0.8488 | AJ93: 157.22 | AK93: 22.206 | AM93: 0.29276338
A94: VRAR | C94: 0.166 | D94: 0.21225941 | E94: -0.12200047 | F94: -0.6471735 | H94: 0.6539 | I94: 0.5767147 | J94: -0.25192 | M94: -1.18009 | N94: 0.29608396 | P94: 0.0043348535 | Q94: 3.3408 | S94: No data | T94: 0.30313483 | V94: -0.3444 | W94: -0.1284 | AB94: 2.355007 | AD94: -7.0211315 | AE94: -14.221289 | AG94: 23.605688 | AH94: 16.7824 | AI94: 1.06 | AJ94: 21.08 | AK94: -2.39027 | AM94: -0.25281414
A95: MINM | C95: -0.9404 | D95: -0.4284927 | E95: -1.4871806 | F95: -0.73739344 | H95: -0.1205 | I95: 1.7404478 | J95: -2.3875718 | M95: -2.64308 | N95: -0.94150585 | P95: 0.009523053 | Q95: 0.20161 | S95: No data | T95: 0.44256693 | V95: -12.3385 | W95: -1.4473 | AB95: 8.433268 | AD95: -3.4939773 | AE95: -6.6388717 | AG95: 17.7388 | AH95: 17.54707 | AI95: 3.61 | AJ95: 3.71 | AK95: -5.02209 | AM95: 0.14879398
A96: MOGO | C96: -0.0149 | D96: 0.09141019 | E96: 0.31380892 | F96: -1.4832947 | H96: 0.9508 | I96: 0.6020875 | J96: No data | M96: -3.442 | N96: 0.45040566 | P96: 0.035167247 | Q96: No data | S96: No data | T96: 0.08321877 | V96: 0.8984 | W96: 0.0417 | Z96: 5.2579765 | AB96: 0.5709697 | AE96: -31.707582 | AG96: 35.713142 | AH96: 109.1375 | AI96: 1.07 | AJ96: No data | AK96: No data | AM96: No data
A97: ONFO | C97: 0.3071 | D97: 0.6296757 | E97: -0.3321621 | F97: -0.24665508 | H97: 0.5851 | I97: 0.7710847 | J97: 0.017273232 | M97: -1.00934 | N97: 0.7813197 | P97: 0.86042 | Q97: No data | S97: 0.51426 | T97: 0 | V97: 0.7029 | W97: -0.1276 | AB97: 0.38595587 | AD97: 36.486225 | AE97: -7.0164423 | AG97: 4.621767 | AH97: 7.081976 | AI97: 0.7401 | AJ97: 5.86 | AK97: 0.1941 | AM97: -0.018040085
A98: SYTA | C98: 0.4913 | D98: 0.026245484 | E98: -1.3839265 | F98: -0.20028944 | H98: 0.1607 | I98: 0.14935829 | J98: -0.91067785 | M98: -18.40329 | N98: 1.4027668 | P98: 0.24102226 | Q98: 0.5729 | S98: 6.48388 | T98: 0.32304993 | V98: -0.34219405 | W98: -0.9972 | AB98: 3.2007692 | AD98: -2.9824872 | AE98: -1.7538903 | AG98: 38.0373 | AH98: 32.27737 | AI98: 3.07 | AJ98: 12.39 | AK98: -10.82235 | AM98: 0.21723185
A99: MTBLY | C99: 0.2577 | D99: 0.23355521 | E99: -0.003062868 | F99: 0.9226848 | H99: 0.7455 | I99: 0.48036242 | J99: -0.033713844 | M99: -3.404 | N99: -1.2161486 | P99: 0.012838935 | Q99: 23.01 | S99: No data | T99: 0.31328502 | V99: -0.26214936 | W99: -0.0353 | AB99: 0.7526276 | AD99: -17.470402 | AE99: -13.005287 | AG99: 56.568996 | AH99: 44.269997 | AI99: 3.058 | AJ99: 738.85 | AK99: -2.534 | AM99: -0.64563173
A100: PROM | C100: 0.2728 | D100: -0.033729747 | E100: 0.038322467 | F100: 0.3936 | H100: 0.6824 | I100: 0.2550001 | J100: 0.44438004 | M100: 18.883 | N100: 1.3415986 | P100: 0.046087984 | Q100: 5.441 | S100: 3.425 | T100: 0.08514182 | V100: -1.3579 | W100: 0.2062 | Z100: 22.702087 | AA100: No data | AB100: 2.4249003 | AD100: 6.7677298 | AE100: 14.285955 | AG100: 300.01 | AH100: 269.7617 | AI100: No data | AJ100: 250.01 | AK100: 39.86 | AM100: 0.0016600527
...

Sheet US - Utilities
A1: Ticker | B1: Company Name | C1: Popular | D1: MCC Link | E1: MCC Link | F1: MKT CAP | G1: REV | H1: REV YoY | I1: REV 5YR CAGR | J1: EBITDA | K1: EBITDA YoY | L1: EBITDA 5Y CAGR | M1: EV/EBITDA | N1: EPS | O1: EPS YoY | P1: NI 5YR CAGR | Q1: ROA | R1: ROE | S1: P/B | T1: P/E | U1: FORWARD P/E | V1: DIVIDEND % | W1: EV | X1: STOCK PRICE | Y1: SHARES OUT
A2: WAVE | B2: Eco Wave Power | C2: Lowest | D2: [READ PITCH](https://community.microcapclub.com/forums/topic/3423-eco-wave-power-wave/#comment-76327) | E2: =IFERROR(__xludf.DUMMYFUNCTION("IFERROR(HYPERLINK(REGEXEXTRACT(D2,""\(([^)]*)\)""),REGEXEXTRACT(D2,""\[([^\]]+)\]"")),"""") "),"READ PITCH") -> READ PITCH | F2: =VLOOKUP($A2, RawData!$A:$AJ, 33, FALSE) -> 34.82723 | G2: =VLOOKUP($A2, RawData!$A:$AJ, 2, FALSE) | H2: =VLOOKUP($A2, RawData!$A:$AJ, 3, FALSE) -> 0.2645 | I2: =VLOOKUP($A2, RawData!$A:$AJ, 4, FALSE) -> No data | J2: =VLOOKUP($A2, RawData!$A:$AM, 37, FALSE) -> -2.143 | K2: =VLOOKUP($A2, RawData!$A:$AM, 38, FALSE) | L2: =VLOOKUP($A2, RawData!$A:$AM, 39, FALSE) -> No data | M2: =VLOOKUP($A2, RawData!$A:$AJ, 30, FALSE) -> -13.758749 | N2: =VLOOKUP($A2, RawData!$A:$AJ, 5, FALSE) -> -0.3556507 | O2: =VLOOKUP($A2, RawData!$A:$AJ, 6, FALSE) -> No data | P2: =VLOOKUP($A2, RawData!$A:$AJ, 7, FALSE) | Q2: =VLOOKUP($A2, RawData!$A:$AJ, 23, FALSE) -> -0.2247 | R2: =VLOOKUP($A2, RawData!$A:$AJ, 24, FALSE) | S2: =VLOOKUP($A2, RawData!$A:$AJ, 29, FALSE) | T2: =VLOOKUP($A2, RawData!$A:$AJ, 26, FALSE) | U2: =VLOOKUP($A2, RawData!$A:$AJ, 27, FALSE) | V2: =VLOOKUP($A2, RawData!$A:$AJ,32, FALSE) | W2: =VLOOKUP($A2, RawData!$A:$AJ, 33, FALSE) -> 34.82723 | X2: =VLOOKUP($A2, RawData!$A:$AJ, 35, FALSE) -> 5.9 | Y2: =VLOOKUP($A2, RawData!$A:$AJ, 36, FALSE) -> 5.84
A3: EUSP | B3: EuroSite Power Inc. | C3: Lowest | D3: [READ PITCH](https://community.microcapclub.com/forums/topic/4564-eurosite-power-inc-eusp/#comment-92070) | E3: =IFERROR(__xludf.DUMMYFUNCTION("IFERROR(HYPERLINK(REGEXEXTRACT(D3,""\(([^)]*)\)""),REGEXEXTRACT(D3,""\[([^\]]+)\]"")),"""") "),"READ PITCH") -> READ PITCH | F3: =VLOOKUP($A3, RawData!$A:$AJ, 33, FALSE) -> 4.19544 | G3: =VLOOKUP($A3, RawData!$A:$AJ, 2, FALSE) -> No data | H3: =VLOOKUP($A3, RawData!$A:$AJ, 3, FALSE) -> -0.56 | I3: =VLOOKUP($A3, RawData!$A:$AJ, 4, FALSE) -> 0.045778085 | J3: =VLOOKUP($A3, RawData!$A:$AM, 37, FALSE) -> -7.18099 | K3: =VLOOKUP($A3, RawData!$A:$AM, 38, FALSE) -> No data | L3: =VLOOKUP($A3, RawData!$A:$AM, 39, FALSE) -> 0.32108018 | M3: =VLOOKUP($A3, RawData!$A:$AJ, 30, FALSE) -> 0.30796728 | N3: =VLOOKUP($A3, RawData!$A:$AJ, 5, FALSE) -> -0.091298684 | O3: =VLOOKUP($A3, RawData!$A:$AJ, 6, FALSE) -> -20.9459 | P3: =VLOOKUP($A3, RawData!$A:$AJ, 7, FALSE) -> No data | Q3: =VLOOKUP($A3, RawData!$A:$AJ, 23, FALSE) -> -0.8302 | R3: =VLOOKUP($A3, RawData!$A:$AJ, 24, FALSE) -> No data | S3: =VLOOKUP($A3, RawData!$A:$AJ, 29, FALSE) -> No data | T3: =VLOOKUP($A3, RawData!$A:$AJ, 26, FALSE) | U3: =VLOOKUP($A3, RawData!$A:$AJ, 27, FALSE) -> No data | V3: =VLOOKUP($A3, RawData!$A:$AJ,32, FALSE) -> No data | W3: =VLOOKUP($A3, RawData!$A:$AJ, 33, FALSE) -> 4.19544 | X3: =VLOOKUP($A3, RawData!$A:$AJ, 35, FALSE) -> 0.051 | Y3: =VLOOKUP($A3, RawData!$A:$AJ, 36, FALSE) -> 82.26
A4: ENG | B4: ENGlobal | C4: Lowest | D4: [READ PITCH](https://community.microcapclub.com/forums/topic/3501-englobal-eng/#comment-77741) | E4: =IFERROR(__xludf.DUMMYFUNCTION("IFERROR(HYPERLINK(REGEXEXTRACT(D4,""\(([^)]*)\)""),REGEXEXTRACT(D4,""\[([^\]]+)\]"")),"""") "),"READ PITCH") -> READ PITCH | F4: =VLOOKUP($A4, RawData!$A:$AJ, 33, FALSE) -> 2.32 | G4: =VLOOKUP($A4, RawData!$A:$AJ, 2, FALSE) | H4: =VLOOKUP($A4, RawData!$A:$AJ, 3, FALSE) -> -0.3871 | I4: =VLOOKUP($A4, RawData!$A:$AJ, 4, FALSE) -> -0.13786851 | J4: =VLOOKUP($A4, RawData!$A:$AM, 37, FALSE) -> -5.585 | K4: =VLOOKUP($A4, RawData!$A:$AM, 38, FALSE) | L4: =VLOOKUP($A4, RawData!$A:$AM, 39, FALSE) -> 0.019537123 | M4: =VLOOKUP($A4, RawData!$A:$AJ, 30, FALSE) -> -0.67358994 | N4: =VLOOKUP($A4, RawData!$A:$AJ, 5, FALSE) -> -1.3306202 | O4: =VLOOKUP($A4, RawData!$A:$AJ, 6, FALSE) -> -0.6921076 | P4: =VLOOKUP($A4, RawData!$A:$AJ, 7, FALSE) | Q4: =VLOOKUP($A4, RawData!$A:$AJ, 23, FALSE) -> -0.4368 | R4: =VLOOKUP($A4, RawData!$A:$AJ, 24, FALSE) | S4: =VLOOKUP($A4, RawData!$A:$AJ, 29, FALSE) | T4: =VLOOKUP($A4, RawData!$A:$AJ, 26, FALSE) | U4: =VLOOKUP($A4, RawData!$A:$AJ, 27, FALSE) -> 1.0699426 | V4: =VLOOKUP($A4, RawData!$A:$AJ,32, FALSE) | W4: =VLOOKUP($A4, RawData!$A:$AJ, 33, FALSE) -> 2.32 | X4: =VLOOKUP($A4, RawData!$A:$AJ, 35, FALSE) -> No data | Y4: =VLOOKUP($A4, RawData!$A:$AJ, 36, FALSE) -> 5.16
A5: GNE | B5: Genie Energy | C5: Low | D5: [READ PITCH](https://community.microcapclub.com/forums/topic/3199-genie-energy-ltd-gne/#comment-72283) | E5: =IFERROR(__xludf.DUMMYFUNCTION("IFERROR(HYPERLINK(REGEXEXTRACT(D5,""\(([^)]*)\)""),REGEXEXTRACT(D5,""\[([^\]]+)\]"")),"""") "),"READ PITCH") -> READ PITCH | F5: =VLOOKUP($A5, RawData!$A:$AJ, 33, FALSE) -> 377.5485 | G5: =VLOOKUP($A5, RawData!$A:$AJ, 2, FALSE) | H5: =VLOOKUP($A5, RawData!$A:$AJ, 3, FALSE) -> 0.1312 | I5: =VLOOKUP($A5, RawData!$A:$AJ, 4, FALSE) -> 0.06155537 | J5: =VLOOKUP($A5, RawData!$A:$AM, 37, FALSE) -> 1.878 | K5: =VLOOKUP($A5, RawData!$A:$AM, 38, FALSE) | L5: =VLOOKUP($A5, RawData!$A:$AM, 39, FALSE) -> -0.4143127 | M5: =VLOOKUP($A5, RawData!$A:$AJ, 30, FALSE) -> 150.76901 | N5: =VLOOKUP($A5, RawData!$A:$AJ, 5, FALSE) -> 0.18308796 | O5: =VLOOKUP($A5, RawData!$A:$AJ, 6, FALSE) -> 0.41564506 | P5: =VLOOKUP($A5, RawData!$A:$AJ, 7, FALSE) | Q5: =VLOOKUP($A5, RawData!$A:$AJ, 23, FALSE) -> 0.0127 | R5: =VLOOKUP($A5, RawData!$A:$AJ, 24, FALSE) | S5: =VLOOKUP($A5, RawData!$A:$AJ, 29, FALSE) | T5: =VLOOKUP($A5, RawData!$A:$AJ, 26, FALSE) -> 79.08767 | U5: =VLOOKUP($A5, RawData!$A:$AJ, 27, FALSE) -> 24.905401 | V5: =VLOOKUP($A5, RawData!$A:$AJ,32, FALSE) | W5: =VLOOKUP($A5, RawData!$A:$AJ, 33, FALSE) -> 377.5485 | X5: =VLOOKUP($A5, RawData!$A:$AJ, 35, FALSE) -> 14.48 | Y5: =VLOOKUP($A5, RawData!$A:$AJ, 36, FALSE) -> 26.49

Sheet US - Technology
A1: Ticker | B1: Company Name | C1: Popular | D1: MCC Link | E1: MCC Link | F1: MKT CAP | G1: REV | H1: REV YoY | I1: REV 5YR CAGR | J1: EBITDA | K1: EBITDA YoY | L1: EBITDA 5Y CAGR | M1: EV/EBITDA | N1: EPS | O1: EPS YoY | P1: NI 5YR CAGR | Q1: GM | R1: OPmargin | S1: FCF | T1: FCF YoY | U1: ROA | V1: ROE | W1: CROCI | X1: PE | Y1: FORWARD PE | Z1: P/S | AA1: EV/FCF | AB1: DIVIDEND % | AC1: EV | AD1: STOCK PRICE | AE1: SHARES OUT
A2: GAME | B2: Gamesquare Holdings | C2: Low | D2: [READ PITCH](https://community.microcapclub.com/forums/topic/1573-gamesquare-holdings-inc-game/#comment-35335) | E2: =IFERROR(__xludf.DUMMYFUNCTION("IFERROR(HYPERLINK(REGEXEXTRACT(D2,""\(([^)]*)\)""),REGEXEXTRACT(D2,""\[([^\]]+)\]"")),"""") "),"READ PITCH") -> READ PITCH | F2: =VLOOKUP($A2, RawData!$A:$AJ, 33, FALSE) -> 46.263557 | G2: =VLOOKUP($A2, RawData!$A:$AJ, 2, FALSE) | H2: =VLOOKUP($A2, RawData!$A:$AJ, 3, FALSE) -> -0.4248 | I2: =VLOOKUP($A2, RawData!$A:$AJ, 4, FALSE) -> -0.12822299 | J2: =VLOOKUP($A2, RawData!$A:$AM, 37, FALSE) -> -35.05172 | K2: =VLOOKUP($A2, RawData!$A:$AM, 38, FALSE) | L2: =VLOOKUP($A2, RawData!$A:$AM, 39, FALSE) -> -0.15716498 | M2: =VLOOKUP($A2, RawData!$A:$AJ, 30, FALSE) -> -1.1254569 | N2: =VLOOKUP($A2, RawData!$A:$AJ, 5, FALSE) -> -0.31139722 | O2: =VLOOKUP($A2, RawData!$A:$AJ, 6, FALSE) -> -0.46814975 | P2: =VLOOKUP($A2, RawData!$A:$AJ, 7, FALSE) | Q2: =VLOOKUP($A2, RawData!$A:$AJ, 8, FALSE) -> 0.1917 | R2: =VLOOKUP($A2, RawData!$A:$AJ, 11, FALSE) | S2: =VLOOKUP($A2, RawData!$A:$AJ, 13, FALSE) -> -22.84184 | T2: =VLOOKUP($A2, RawData!$A:$AJ, 14, FALSE) -> 0.720281 | U2: =VLOOKUP($A2, RawData!$A:$AJ, 23, FALSE) -> -0.3931 | V2: =VLOOKUP($A2, RawData!$A:$AJ, 24, FALSE) | W2: =VLOOKUP($A2, RawData!$A:$AJ, 25, FALSE) | X2: =VLOOKUP($A2, RawData!$A:$AJ, 26, FALSE) | Y2: =VLOOKUP($A2, RawData!$A:$AJ, 27, FALSE) | Z2: =VLOOKUP($A2, RawData!$A:$AJ, 28, FALSE) -> 0.633634 | AA2: =VLOOKUP($A2, RawData!$A:$AJ, 31, FALSE) -> -1.7270608 | AB2: =VLOOKUP($A2, RawData!$A:$AJ,32, FALSE) | AC2: =VLOOKUP($A2, RawData!$A:$AJ, 34, FALSE) -> 39.449177 | AD2: =VLOOKUP($A2, RawData!$A:$AJ, 35, FALSE) -> 0.4621 | AE2: =VLOOKUP($A2, RawData!$A:$AJ, 36, FALSE) -> 98.38
A3: PI | B3: Impinj | C3: Low | D3: [READ PITCH](https://community.microcapclub.com/forums/topic/2036-impinj-pi/#comment-46319) | E3: =IFERROR(__xludf.DUMMYFUNCTION("IFERROR(HYPERLINK(REGEXEXTRACT(D3,""\(([^)]*)\)""),REGEXEXTRACT(D3,""\[([^\]]+)\]"")),"""") "),"READ PITCH") -> READ PITCH | F3: =VLOOKUP($A3, RawData!$A:$AJ, 33, FALSE) -> 6404.815 | G3: =VLOOKUP($A3, RawData!$A:$AJ, 2, FALSE) | H3: =VLOOKUP($A3, RawData!$A:$AJ, 3, FALSE) -> 0.0424 | I3: =VLOOKUP($A3, RawData!$A:$AJ, 4, FALSE) -> 0.20215866 | J3: =VLOOKUP($A3, RawData!$A:$AM, 37, FALSE) -> 7.213 | K3: =VLOOKUP($A3, RawData!$A:$AM, 38, FALSE) | L3: =VLOOKUP($A3, RawData!$A:$AM, 39, FALSE) -> -0.030969055 | M3: =VLOOKUP($A3, RawData!$A:$AJ, 30, FALSE) -> 788.76843 | N3: =VLOOKUP($A3, RawData!$A:$AJ, 5, FALSE) -> -0.4117569 | O3: =VLOOKUP($A3, RawData!$A:$AJ, 6, FALSE) -> -1.2009693 | P3: =VLOOKUP($A3, RawData!$A:$AJ, 7, FALSE) | Q3: =VLOOKUP($A3, RawData!$A:$AJ, 8, FALSE) -> 0.5221 | R3: =VLOOKUP($A3, RawData!$A:$AJ, 11, FALSE) | S3: =VLOOKUP($A3, RawData!$A:$AJ, 13, FALSE) -> 40.267 | T3: =VLOOKUP($A3, RawData!$A:$AJ, 14, FALSE) -> 0.3955268 | U3: =VLOOKUP($A3, RawData!$A:$AJ, 23, FALSE) -> -0.0249 | V3: =VLOOKUP($A3, RawData!$A:$AJ, 24, FALSE) | W3: =VLOOKUP($A3, RawData!$A:$AJ, 25, FALSE) | X3: =VLOOKUP($A3, RawData!$A:$AJ, 26, FALSE) | Y3: =VLOOKUP($A3, RawData!$A:$AJ, 27, FALSE) -> 86.15877 | Z3: =VLOOKUP($A3, RawData!$A:$AJ, 28, FALSE) -> 15.177392 | AA3: =VLOOKUP($A3, RawData!$A:$AJ, 31, FALSE) -> 141.29155 | AB3: =VLOOKUP($A3, RawData!$A:$AJ,32, FALSE) | AC3: =VLOOKUP($A3, RawData!$A:$AJ, 34, FALSE) -> 5689.3867 | AD3: =VLOOKUP($A3, RawData!$A:$AJ, 35, FALSE) -> 181.36 | AE3: =VLOOKUP($A3, RawData!$A:$AJ, 36, FALSE) -> 30.11
A4: IDT | B4: IDT Corporation | C4: Lowest | D4: [READ PITCH](https://community.microcapclub.com/forums/topic/2350-idt-corporation-idt/#comment-54574) | E4: =IFERROR(__xludf.DUMMYFUNCTION("IFERROR(HYPERLINK(REGEXEXTRACT(D4,""\(([^)]*)\)""),REGEXEXTRACT(D4,""\[([^\]]+)\]"")),"""") "),"READ PITCH") -> READ PITCH | F4: =VLOOKUP($A4, RawData!$A:$AJ, 33, FALSE) -> 1272.4558 | G4: =VLOOKUP($A4, RawData!$A:$AJ, 2, FALSE) | H4: =VLOOKUP($A4, RawData!$A:$AJ, 3, FALSE) -> 0.0252 | I4: =VLOOKUP($A4, RawData!$A:$AJ, 4, FALSE) -> -0.015953567 | J4: =VLOOKUP($A4, RawData!$A:$AM, 37, FALSE) -> 128.926 | K4: =VLOOKUP($A4, RawData!$A:$AM, 38, FALSE) | L4: =VLOOKUP($A4, RawData!$A:$AM, 39, FALSE) -> 0.19638498 | M4: =VLOOKUP($A4, RawData!$A:$AJ, 30, FALSE) -> 8.653185 | N4: =VLOOKUP($A4, RawData!$A:$AJ, 5, FALSE) -> 3.2392502 | O4: =VLOOKUP($A4, RawData!$A:$AJ, 6, FALSE) -> 0.096753284 | P4: =VLOOKUP($A4, RawData!$A:$AJ, 7, FALSE) | Q4: =VLOOKUP($A4, RawData!$A:$AJ, 8, FALSE) -> 0.367 | R4: =VLOOKUP($A4, RawData!$A:$AJ, 11, FALSE) | S4: =VLOOKUP($A4, RawData!$A:$AJ, 13, FALSE) -> 92.905 | T4: =VLOOKUP($A4, RawData!$A:$AJ, 14, FALSE) -> 2.1266053 | U4: =VLOOKUP($A4, RawData!$A:$AJ, 23, FALSE) -> 0.1322 | V4: =VLOOKUP($A4, RawData!$A:$AJ, 24, FALSE) | W4: =VLOOKUP($A4, RawData!$A:$AJ, 25, FALSE) | X4: =VLOOKUP($A4, RawData!$A:$AJ, 26, FALSE) -> 16.068533 | Y4: =VLOOKUP($A4, RawData!$A:$AJ, 27, FALSE) -> 15.501221 | Z4: =VLOOKUP($A4, RawData!$A:$AJ, 28, FALSE) -> 1.0483767 | AA4: =VLOOKUP($A4, RawData!$A:$AJ, 31, FALSE) -> 12.008185 | AB4: =VLOOKUP($A4, RawData!$A:$AJ,32, FALSE) | AC4: =VLOOKUP($A4, RawData!$A:$AJ, 34, FALSE) -> 1115.6205 | AD4: =VLOOKUP($A4, RawData!$A:$AJ, 35, FALSE) -> 52.05 | AE4: =VLOOKUP($A4, RawData!$A:$AJ, 36, FALSE) -> 25.07
A5: BKTI | B5: BK Technologies | C5: Medium | D5: [READ PITCH](https://community.microcapclub.com/forums/topic/3773-bk-technologies-bkti/#comment-81787) | E5: =IFERROR(__xludf.DUMMYFUNCTION("IFERROR(HYPERLINK(REGEXEXTRACT(D5,""\(([^)]*)\)""),REGEXEXTRACT(D5,""\[([^\]]+)\]"")),"""") "),"READ PITCH") -> READ PITCH | F5: =VLOOKUP($A5, RawData!$A:$AJ, 33, FALSE) -> 288.68884 | G5: =VLOOKUP($A5, RawData!$A:$AJ, 2, FALSE) | H5: =VLOOKUP($A5, RawData!$A:$AJ, 3, FALSE) -> 0.0463 | I5: =VLOOKUP($A5, RawData!$A:$AJ, 4, FALSE) -> 0.1438503 | J5: =VLOOKUP($A5, RawData!$A:$AM, 37, FALSE) -> 13.289 | K5: =VLOOKUP($A5, RawData!$A:$AM, 38, FALSE) | L5: =VLOOKUP($A5, RawData!$A:$AM, 39, FALSE) -> 0.74884135 | M5: =VLOOKUP($A5, RawData!$A:$AJ, 30, FALSE) -> 23.659426 | N5: =VLOOKUP($A5, RawData!$A:$AJ, 5, FALSE) -> 3.1868632 | O5: =VLOOKUP($A5, RawData!$A:$AJ, 6, FALSE) -> 3.362202 | P5: =VLOOKUP($A5, RawData!$A:$AJ, 7, FALSE) | Q5: =VLOOKUP($A5, RawData!$A:$AJ, 8, FALSE) -> 0.4366 | R5: =VLOOKUP($A5, RawData!$A:$AJ, 11, FALSE) | S5: =VLOOKUP($A5, RawData!$A:$AJ, 13, FALSE) -> 12.283 | T5: =VLOOKUP($A5, RawData!$A:$AJ, 14, FALSE) -> 8.8942795 | U5: =VLOOKUP($A5, RawData!$A:$AJ, 23, FALSE) -> 0.2218 | V5: =VLOOKUP($A5, RawData!$A:$AJ, 24, FALSE) | W5: =VLOOKUP($A5, RawData!$A:$AJ, 25, FALSE) | X5: =VLOOKUP($A5, RawData!$A:$AJ, 26, FALSE) -> 27.447052 | Y5: =VLOOKUP($A5, RawData!$A:$AJ, 27, FALSE) -> 21.765203 | Z5: =VLOOKUP($A5, RawData!$A:$AJ, 28, FALSE) -> 4.1654506 | AA5: =VLOOKUP($A5, RawData!$A:$AJ, 31, FALSE) -> 25.597176 | AB5: =VLOOKUP($A5, RawData!$A:$AJ,32, FALSE) | AC5: =VLOOKUP($A5, RawData!$A:$AJ, 34, FALSE) -> 314.4101 | AD5: =VLOOKUP($A5, RawData!$A:$AJ, 35, FALSE) -> 87.47 | AE5: =VLOOKUP($A5, RawData!$A:$AJ, 36, FALSE) -> 3.73
A6: RDVT | B6: Red Violet | C6: Medium | D6: [READ PITCH](https://community.microcapclub.com/forums/topic/2089-red-violet-rdvt/#comment-47842) | E6: =IFERROR(__xludf.DUMMYFUNCTION("IFERROR(HYPERLINK(REGEXEXTRACT(D6,""\(([^)]*)\)""),REGEXEXTRACT(D6,""\[([^\]]+)\]"")),"""") "),"READ PITCH") -> READ PITCH | F6: =VLOOKUP($A6, RawData!$A:$AJ, 33, FALSE) -> 745.3378 | G6: =VLOOKUP($A6, RawData!$A:$AJ, 2, FALSE) | H6: =VLOOKUP($A6, RawData!$A:$AJ, 3, FALSE) -> 0.2227 | I6: =VLOOKUP($A6, RawData!$A:$AJ, 4, FALSE) -> 0.2003615 | J6: =VLOOKUP($A6, RawData!$A:$AM, 37, FALSE) -> 22.293 | K6: =VLOOKUP($A6, RawData!$A:$AM, 38, FALSE) | L6: =VLOOKUP($A6, RawData!$A:$AM, 39, FALSE) -> No data | M6: =VLOOKUP($A6, RawData!$A:$AJ, 30, FALSE) -> 30.11736 | N6: =VLOOKUP($A6, RawData!$A:$AJ, 5, FALSE) -> 0.79503196 | O6: =VLOOKUP($A6, RawData!$A:$AJ, 6, FALSE) -> 1.2094674 | P6: =VLOOKUP($A6, RawData!$A:$AJ, 7, FALSE) | Q6: =VLOOKUP($A6, RawData!$A:$AJ, 8, FALSE) -> 0.835 | R6: =VLOOKUP($A6, RawData!$A:$AJ, 11, FALSE) | S6: =VLOOKUP($A6, RawData!$A:$AJ, 13, FALSE) -> 18.936 | T6: =VLOOKUP($A6, RawData!$A:$AJ, 14, FALSE) -> 1.5683286 | U6: =VLOOKUP($A6, RawData!$A:$AJ, 23, FALSE) -> 0.1081 | V6: =VLOOKUP($A6, RawData!$A:$AJ, 24, FALSE) | W6: =VLOOKUP($A6, RawData!$A:$AJ, 25, FALSE) | X6: =VLOOKUP($A6, RawData!$A:$AJ, 26, FALSE) -> 63.98485 | Y6: =VLOOKUP($A6, RawData!$A:$AJ, 27, FALSE) -> 43.60722 | Z6: =VLOOKUP($A6, RawData!$A:$AJ, 28, FALSE) -> 8.293414 | AA6: =VLOOKUP($A6, RawData!$A:$AJ, 31, FALSE) -> 35.456608 | AB6: =VLOOKUP($A6, RawData!$A:$AJ,32, FALSE) | AC6: =VLOOKUP($A6, RawData!$A:$AJ, 34, FALSE) -> 671.4063 | AD6: =VLOOKUP($A6, RawData!$A:$AJ, 35, FALSE) -> 50.87 | AE6: =VLOOKUP($A6, RawData!$A:$AJ, 36, FALSE) -> 14.09
A7: INOD | B7: Innodata | C7: Low | D7: [READ PITCH](https://community.microcapclub.com/forums/topic/1236-innodata-inod/#comment-28632) | E7: =IFERROR(__xludf.DUMMYFUNCTION("IFERROR(HYPERLINK(REGEXEXTRACT(D7,""\(([^)]*)\)""),REGEXEXTRACT(D7,""\[([^\]]+)\]"")),"""") "),"READ PITCH") -> READ PITCH | F7: =VLOOKUP($A7, RawData!$A:$AJ, 33, FALSE) -> 2107.9204 | G7: =VLOOKUP($A7, RawData!$A:$AJ, 2, FALSE) | H7: =VLOOKUP($A7, RawData!$A:$AJ, 3, FALSE) -> 0.7357 | I7: =VLOOKUP($A7, RawData!$A:$AJ, 4, FALSE) -> 0.3285289 | J7: =VLOOKUP($A7, RawData!$A:$AM, 37, FALSE) -> 46.686 | K7: =VLOOKUP($A7, RawData!$A:$AM, 38, FALSE) | L7: =VLOOKUP($A7, RawData!$A:$AM, 39, FALSE) -> 0.7872666 | M7: =VLOOKUP($A7, RawData!$A:$AJ, 30, FALSE) -> 41.706306 | N7: =VLOOKUP($A7, RawData!$A:$AJ, 5, FALSE) -> 1.055995 | O7: =VLOOKUP($A7, RawData!$A:$AJ, 6, FALSE) -> 0.68085533 | P7: =VLOOKUP($A7, RawData!$A:$AJ, 7, FALSE) | Q7: =VLOOKUP($A7, RawData!$A:$AJ, 8, FALSE) -> 0.4132 | R7: =VLOOKUP($A7, RawData!$A:$AJ, 11, FALSE) | S7: =VLOOKUP($A7, RawData!$A:$AJ, 13, FALSE) -> 40.697 | T7: =VLOOKUP($A7, RawData!$A:$AJ, 14, FALSE) -> 3.68933 | U7: =VLOOKUP($A7, RawData!$A:$AJ, 23, FALSE) -> 0.2567 | V7: =VLOOKUP($A7, RawData!$A:$AJ, 24, FALSE) | W7: =VLOOKUP($A7, RawData!$A:$AJ, 25, FALSE) | X7: =VLOOKUP($A7, RawData!$A:$AJ, 26, FALSE) -> 59.81089 | Y7: =VLOOKUP($A7, RawData!$A:$AJ, 27, FALSE) -> 70.241 | Z7: =VLOOKUP($A7, RawData!$A:$AJ, 28, FALSE) -> 8.43839 | AA7: =VLOOKUP($A7, RawData!$A:$AJ, 31, FALSE) -> 47.843838 | AB7: =VLOOKUP($A7, RawData!$A:$AJ,32, FALSE) | AC7: =VLOOKUP($A7, RawData!$A:$AJ, 34, FALSE) -> 1947.1006 | AD7: =VLOOKUP($A7, RawData!$A:$AJ, 35, FALSE) -> 63.16 | AE7: =VLOOKUP($A7, RawData!$A:$AJ, 36, FALSE) -> 31.86
A8: EACO | B8: EACO Corporation | C8: Low | D8: [READ PITCH](https://community.microcapclub.com/forums/topic/1049-eaco-corporation-eaco/#comment-22708) | E8: =IFERROR(__xludf.DUMMYFUNCTION("IFERROR(HYPERLINK(REGEXEXTRACT(D8,""\(([^)]*)\)""),REGEXEXTRACT(D8,""\[([^\]]+)\]"")),"""") "),"READ PITCH") -> READ PITCH | F8: =VLOOKUP($A8, RawData!$A:$AJ, 33, FALSE) -> 413.23517 | G8: =VLOOKUP($A8, RawData!$A:$AJ, 2, FALSE) | H8: =VLOOKUP($A8, RawData!$A:$AJ, 3, FALSE) -> 0.1631 | I8: =VLOOKUP($A8, RawData!$A:$AJ, 4, FALSE) -> 0.12024409 | J8: =VLOOKUP($A8, RawData!$A:$AM, 37, FALSE) -> 41.932 | K8: =VLOOKUP($A8, RawData!$A:$AM, 38, FALSE) | L8: =VLOOKUP($A8, RawData!$A:$AM, 39, FALSE) -> 0.25658518 | M8: =VLOOKUP($A8, RawData!$A:$AJ, 30, FALSE) -> 9.878493 | N8: =VLOOKUP($A8, RawData!$A:$AJ, 5, FALSE) -> 6.1020575 | O8: =VLOOKUP($A8, RawData!$A:$AJ, 6, FALSE) -> 1.0429871 | P8: =VLOOKUP($A8, RawData!$A:$AJ, 7, FALSE) | Q8: =VLOOKUP($A8, RawData!$A:$AJ, 8, FALSE) -> 0.3011 | R8: =VLOOKUP($A8, RawData!$A:$AJ, 11, FALSE) | S8: =VLOOKUP($A8, RawData!$A:$AJ, 13, FALSE) -> 18.429 | T8: =VLOOKUP($A8, RawData!$A:$AJ, 14, FALSE) -> -0.7756313 | U8: =VLOOKUP($A8, RawData!$A:$AJ, 23, FALSE) -> 0.1472 | V8: =VLOOKUP($A8, RawData!$A:$AJ, 24, FALSE) | W8: =VLOOKUP($A8, RawData!$A:$AJ, 25, FALSE) | X8: =VLOOKUP($A8, RawData!$A:$AJ, 26, FALSE) -> 13.929728 | Y8: =VLOOKUP($A8, RawData!$A:$AJ, 27, FALSE) | Z8: =VLOOKUP($A8, RawData!$A:$AJ, 28, FALSE) -> 1.027658 | AA8: =VLOOKUP($A8, RawData!$A:$AJ, 31, FALSE) -> 22.476803 | AB8: =VLOOKUP($A8, RawData!$A:$AJ,32, FALSE) | AC8: =VLOOKUP($A8, RawData!$A:$AJ, 34, FALSE) -> 414.225 | AD8: =VLOOKUP($A8, RawData!$A:$AJ, 35, FALSE) -> 85 | AE8: =VLOOKUP($A8, RawData!$A:$AJ, 36, FALSE) -> 4.86
A9: IIIV | B9: i3 Verticals | C9: Low | D9: [READ PITCH](https://community.microcapclub.com/forums/topic/4122-i3-verticals-inc-iiiv/#comment-85768) | E9: =IFERROR(__xludf.DUMMYFUNCTION("IFERROR(HYPERLINK(REGEXEXTRACT(D9,""\(([^)]*)\)""),REGEXEXTRACT(D9,""\[([^\]]+)\]"")),"""") "),"READ PITCH") -> READ PITCH | F9: =VLOOKUP($A9, RawData!$A:$AJ, 33, FALSE) -> 884.8759 | G9: =VLOOKUP($A9, RawData!$A:$AJ, 2, FALSE) | H9: =VLOOKUP($A9, RawData!$A:$AJ, 3, FALSE) -> -0.2369 | I9: =VLOOKUP($A9, RawData!$A:$AJ, 4, FALSE) -> 0.0904248 | J9: =VLOOKUP($A9, RawData!$A:$AM, 37, FALSE) -> 40.91 | K9: =VLOOKUP($A9, RawData!$A:$AM, 38, FALSE) | L9: =VLOOKUP($A9, RawData!$A:$AM, 39, FALSE) -> 0.11801729 | M9: =VLOOKUP($A9, RawData!$A:$AJ, 30, FALSE) -> 19.736616 | N9: =VLOOKUP($A9, RawData!$A:$AJ, 5, FALSE) -> 0.5524884 | O9: =VLOOKUP($A9, RawData!$A:$AJ, 6, FALSE) -> -0.8439366 | P9: =VLOOKUP($A9, RawData!$A:$AJ, 7, FALSE) | Q9: =VLOOKUP($A9, RawData!$A:$AJ, 8, FALSE) -> 0.6647 | R9: =VLOOKUP($A9, RawData!$A:$AJ, 11, FALSE) | S9: =VLOOKUP($A9, RawData!$A:$AJ, 13, FALSE) -> -4.441 | T9: =VLOOKUP($A9, RawData!$A:$AJ, 14, FALSE) -> -0.13457575 | U9: =VLOOKUP($A9, RawData!$A:$AJ, 23, FALSE) -> 0.0271 | V9: =VLOOKUP($A9, RawData!$A:$AJ, 24, FALSE) | W9: =VLOOKUP($A9, RawData!$A:$AJ, 25, FALSE) | X9: =VLOOKUP($A9, RawData!$A:$AJ, 26, FALSE) -> 48.906002 | Y9: =VLOOKUP($A9, RawData!$A:$AJ, 27, FALSE) -> 23.408056 | Z9: =VLOOKUP($A9, RawData!$A:$AJ, 28, FALSE) -> 3.774949 | AA9: =VLOOKUP($A9, RawData!$A:$AJ, 31, FALSE) -> -181.81152 | AB9: =VLOOKUP($A9, RawData!$A:$AJ,32, FALSE) | AC9: =VLOOKUP($A9, RawData!$A:$AJ, 34, FALSE) -> 807.425 | AD9: =VLOOKUP($A9, RawData!$A:$AJ, 35, FALSE) -> 27.02 | AE9: =VLOOKUP($A9, RawData!$A:$AJ, 36, FALSE) -> 32.35
A10: GLAE | B10: GlassBridge Enterprises | C10: Low | D10: [READ PITCH](https://community.microcapclub.com/forums/topic/1324-glassbridge-enterprises-glae/#comment-29369) | E10: =IFERROR(__xludf.DUMMYFUNCTION("IFERROR(HYPERLINK(REGEXEXTRACT(D10,""\(([^)]*)\)""),REGEXEXTRACT(D10,""\[([^\]]+)\]"")),"""") "),"READ PITCH") -> READ PITCH | F10: =VLOOKUP($A10, RawData!$A:$AJ, 33, FALSE) -> 0.7 | G10: =VLOOKUP($A10, RawData!$A:$AJ, 2, FALSE) | H10: =VLOOKUP($A10, RawData!$A:$AJ, 3, FALSE) -> 1 | I10: =VLOOKUP($A10, RawData!$A:$AJ, 4, FALSE) -> 0.14869836 | J10: =VLOOKUP($A10, RawData!$A:$AM, 37, FALSE) -> No data | K10: =VLOOKUP($A10, RawData!$A:$AM, 38, FALSE) | L10: =VLOOKUP($A10, RawData!$A:$AM, 39, FALSE) -> No data | M10: =VLOOKUP($A10, RawData!$A:$AJ, 30, FALSE) | N10: =VLOOKUP($A10, RawData!$A:$AJ, 5, FALSE) -> -133.33333 | O10: =VLOOKUP($A10, RawData!$A:$AJ, 6, FALSE) -> -1.2 | P10: =VLOOKUP($A10, RawData!$A:$AJ, 7, FALSE) | Q10: =VLOOKUP($A10, RawData!$A:$AJ, 8, FALSE) -> 1 | R10: =VLOOKUP($A10, RawData!$A:$AJ, 11, FALSE) | S10: =VLOOKUP($A10, RawData!$A:$AJ, 13, FALSE) -> -3.4 | T10: =VLOOKUP($A10, RawData!$A:$AJ, 14, FALSE) -> 0.8292683 | U10: =VLOOKUP($A10, RawData!$A:$AJ, 23, FALSE) -> -0.2439 | V10: =VLOOKUP($A10, RawData!$A:$AJ, 24, FALSE) | W10: =VLOOKUP($A10, RawData!$A:$AJ, 25, FALSE) | X10: =VLOOKUP($A10, RawData!$A:$AJ, 26, FALSE) | Y10: =VLOOKUP($A10, RawData!$A:$AJ, 27, FALSE) | Z10: =VLOOKUP($A10, RawData!$A:$AJ, 28, FALSE) -> 4.2 | AA10: =VLOOKUP($A10, RawData!$A:$AJ, 31, FALSE) -> -3.7764707 | AB10: =VLOOKUP($A10, RawData!$A:$AJ,32, FALSE) | AC10: =VLOOKUP($A10, RawData!$A:$AJ, 34, FALSE) -> 12.84 | AD10: =VLOOKUP($A10, RawData!$A:$AJ, 35, FALSE) -> 28 | AE10: =VLOOKUP($A10, RawData!$A:$AJ, 36, FALSE) -> 0.03
A11: FC | B11: Franklin Covey | C11: Low | D11: [READ PITCH](https://community.microcapclub.com/forums/topic/4356-franklin-covey-fc/#comment-88993) | E11: =IFERROR(__xludf.DUMMYFUNCTION("IFERROR(HYPERLINK(REGEXEXTRACT(D11,""\(([^)]*)\)""),REGEXEXTRACT(D11,""\[([^\]]+)\]"")),"""") "),"READ PITCH") -> READ PITCH | F11: =VLOOKUP($A11, RawData!$A:$AJ, 33, FALSE) -> 225.53098 | G11: =VLOOKUP($A11, RawData!$A:$AJ, 2, FALSE) | H11: =VLOOKUP($A11, RawData!$A:$AJ, 3, FALSE) -> -0.0899 | I11: =VLOOKUP($A11, RawData!$A:$AJ, 4, FALSE) -> 0.061245136 | J11: =VLOOKUP($A11, RawData!$A:$AM, 37, FALSE) -> 14.162 | K11: =VLOOKUP($A11, RawData!$A:$AM, 38, FALSE) | L11: =VLOOKUP($A11, RawData!$A:$AM, 39, FALSE) -> -0.0015182684 | M11: =VLOOKUP($A11, RawData!$A:$AJ, 30, FALSE) -> 14.923895 | N11: =VLOOKUP($A11, RawData!$A:$AJ, 5, FALSE) -> 0.25230262 | O11: =VLOOKUP($A11, RawData!$A:$AJ, 6, FALSE) -> -0.8689001 | P11: =VLOOKUP($A11, RawData!$A:$AJ, 7, FALSE) | Q11: =VLOOKUP($A11, RawData!$A:$AJ, 8, FALSE) -> 0.7604 | R11: =VLOOKUP($A11, RawData!$A:$AJ, 11, FALSE) | S11: =VLOOKUP($A11, RawData!$A:$AJ, 13, FALSE) -> 13.163 | T11: =VLOOKUP($A11, RawData!$A:$AJ, 14, FALSE) -> 0.26486507 | U11: =VLOOKUP($A11, RawData!$A:$AJ, 23, FALSE) -> -0.0062 | V11: =VLOOKUP($A11, RawData!$A:$AJ, 24, FALSE) | W11: =VLOOKUP($A11, RawData!$A:$AJ, 25, FALSE) | X11: =VLOOKUP($A11, RawData!$A:$AJ, 26, FALSE) -> 78.952805 | Y11: =VLOOKUP($A11, RawData!$A:$AJ, 27, FALSE) -> 58.008152 | Z11: =VLOOKUP($A11, RawData!$A:$AJ, 28, FALSE) -> 0.9069904 | AA11: =VLOOKUP($A11, RawData!$A:$AJ, 31, FALSE) -> 16.056538 | AB11: =VLOOKUP($A11, RawData!$A:$AJ,32, FALSE) | AC11: =VLOOKUP($A11, RawData!$A:$AJ, 34, FALSE) -> 211.3522 | AD11: =VLOOKUP($A11, RawData!$A:$AJ, 35, FALSE) -> 19.92 | AE11: =VLOOKUP($A11, RawData!$A:$AJ, 36, FALSE) -> 12.16
A12: AVNW | B12: Aviat Networks | C12: Lowest | D12: [READ PITCH](https://community.microcapclub.com/forums/topic/3390-aviat-networks-avnw/#comment-75905) | E12: =IFERROR(__xludf.DUMMYFUNCTION("IFERROR(HYPERLINK(REGEXEXTRACT(D12,""\(([^)]*)\)""),REGEXEXTRACT(D12,""\[([^\]]+)\]"")),"""") "),"READ PITCH") -> READ PITCH | F12: =VLOOKUP($A12, RawData!$A:$AJ, 33, FALSE) -> 274.66278 | G12: =VLOOKUP($A12, RawData!$A:$AJ, 2, FALSE) | H12: =VLOOKUP($A12, RawData!$A:$AJ, 3, FALSE) -> 0.1089 | I12: =VLOOKUP($A12, RawData!$A:$AJ, 4, FALSE) -> 0.12976143 | J12: =VLOOKUP($A12, RawData!$A:$AM, 37, FALSE) -> 40.438 | K12: =VLOOKUP($A12, RawData!$A:$AM, 38, FALSE) | L12: =VLOOKUP($A12, RawData!$A:$AM, 39, FALSE) -> 0.25286326 | M12: =VLOOKUP($A12, RawData!$A:$AJ, 30, FALSE) -> 7.9107966 | N12: =VLOOKUP($A12, RawData!$A:$AJ, 5, FALSE) -> 1.0422119 | O12: =VLOOKUP($A12, RawData!$A:$AJ, 6, FALSE) -> -3.6116316 | P12: =VLOOKUP($A12, RawData!$A:$AJ, 7, FALSE) | Q12: =VLOOKUP($A12, RawData!$A:$AJ, 8, FALSE) -> 0.3425 | R12: =VLOOKUP($A12, RawData!$A:$AJ, 11, FALSE) | S12: =VLOOKUP($A12, RawData!$A:$AJ, 13, FALSE) -> 11.868 | T12: =VLOOKUP($A12, RawData!$A:$AJ, 14, FALSE) -> -0.17378317 | U12: =VLOOKUP($A12, RawData!$A:$AJ, 23, FALSE) -> 0.0214 | V12: =VLOOKUP($A12, RawData!$A:$AJ, 24, FALSE) | W12: =VLOOKUP($A12, RawData!$A:$AJ, 25, FALSE) | X12: =VLOOKUP($A12, RawData!$A:$AJ, 26, FALSE) -> 20.792318 | Y12: =VLOOKUP($A12, RawData!$A:$AJ, 27, FALSE) -> 8.618701 | Z12: =VLOOKUP($A12, RawData!$A:$AJ, 28, FALSE) -> 0.61354935 | AA12: =VLOOKUP($A12, RawData!$A:$AJ, 31, FALSE) -> 26.954567 | AB12: =VLOOKUP($A12, RawData!$A:$AJ,32, FALSE) | AC12: =VLOOKUP($A12, RawData!$A:$AJ, 34, FALSE) -> 319.8968 | AD12: =VLOOKUP($A12, RawData!$A:$AJ, 35, FALSE) -> 21.67 | AE12: =VLOOKUP($A12, RawData!$A:$AJ, 36, FALSE) -> 12.84
A13: CCRD | B13: CoreCard | C13: Medium High | D13: [READ PITCH](https://community.microcapclub.com/forums/topic/2329-corecard-corporation-ccrd/#comment-54126) | E13: =IFERROR(__xludf.DUMMYFUNCTION("IFERROR(HYPERLINK(REGEXEXTRACT(D13,""\(([^)]*)\)""),REGEXEXTRACT(D13,""\[([^\]]+)\]"")),"""") "),"READ PITCH") -> READ PITCH | F13: =VLOOKUP($A13, RawData!$A:$AJ, 33, FALSE) -> 183.9 | G13: =VLOOKUP($A13, RawData!$A:$AJ, 2, FALSE) | H13: =VLOOKUP($A13, RawData!$A:$AJ, 3, FALSE) -> 0.2361 | I13: =VLOOKUP($A13, RawData!$A:$AJ, 4, FALSE) -> 0.1262796 | J13: =VLOOKUP($A13, RawData!$A:$AM, 37, FALSE) -> 14.139 | K13: =VLOOKUP($A13, RawData!$A:$AM, 38, FALSE) | L13: =VLOOKUP($A13, RawData!$A:$AM, 39, FALSE) -> 0.008844381 | M13: =VLOOKUP($A13, RawData!$A:$AJ, 30, FALSE) -> 11.885643 | N13: =VLOOKUP($A13, RawData!$A:$AJ, 5, FALSE) -> 1.028498 | O13: =VLOOKUP($A13, RawData!$A:$AJ, 6, FALSE) -> 4.0326633 | P13: =VLOOKUP($A13, RawData!$A:$AJ, 7, FALSE) | Q13: =VLOOKUP($A13, RawData!$A:$AJ, 8, FALSE) -> 0.4541 | R13: =VLOOKUP($A13, RawData!$A:$AJ, 11, FALSE) | S13: =VLOOKUP($A13, RawData!$A:$AJ, 13, FALSE) -> 8.916 | T13: =VLOOKUP($A13, RawData!$A:$AJ, 14, FALSE) -> 207.34883 | U13: =VLOOKUP($A13, RawData!$A:$AJ, 23, FALSE) -> 0.123 | V13: =VLOOKUP($A13, RawData!$A:$AJ, 24, FALSE) | W13: =VLOOKUP($A13, RawData!$A:$AJ, 25, FALSE) | X13: =VLOOKUP($A13, RawData!$A:$AJ, 26, FALSE) -> 24.297565 | Y13: =VLOOKUP($A13, RawData!$A:$AJ, 27, FALSE) -> 22.272728 | Z13: =VLOOKUP($A13, RawData!$A:$AJ, 28, FALSE) -> 3.0038283 | AA13: =VLOOKUP($A13, RawData!$A:$AJ, 31, FALSE) -> 18.84826 | AB13: =VLOOKUP($A13, RawData!$A:$AJ,32, FALSE) | AC13: =VLOOKUP($A13, RawData!$A:$AJ, 34, FALSE) -> 168.0511 | AD13: =VLOOKUP($A13, RawData!$A:$AJ, 35, FALSE) -> 23.6 | AE13: =VLOOKUP($A13, RawData!$A:$AJ, 36, FALSE) -> 7.79
A14: ACFN | B14: Acorn Energy | C14: High | D14: [READ PITCH](https://community.microcapclub.com/forums/topic/4634-acorn-energy-inc-acfn/) | E14: =IFERROR(__xludf.DUMMYFUNCTION("IFERROR(HYPERLINK(REGEXEXTRACT(D14,""\(([^)]*)\)""),REGEXEXTRACT(D14,""\[([^\]]+)\]"")),"""") "),"READ PITCH") -> READ PITCH | F14: =VLOOKUP($A14, RawData!$A:$AJ, 33, FALSE) -> 51.26969 | G14: =VLOOKUP($A14, RawData!$A:$AJ, 2, FALSE) | H14: =VLOOKUP($A14, RawData!$A:$AJ, 3, FALSE) -> 0.363 | I14: =VLOOKUP($A14, RawData!$A:$AJ, 4, FALSE) -> 0.1484058 | J14: =VLOOKUP($A14, RawData!$A:$AM, 37, FALSE) -> 2.058 | K14: =VLOOKUP($A14, RawData!$A:$AM, 38, FALSE) | L14: =VLOOKUP($A14, RawData!$A:$AM, 39, FALSE) -> -0.4104765 | M14: =VLOOKUP($A14, RawData!$A:$AJ, 30, FALSE) -> 23.335278 | N14: =VLOOKUP($A14, RawData!$A:$AJ, 5, FALSE) -> 2.5176 | O14: =VLOOKUP($A14, RawData!$A:$AJ, 6, FALSE) -> 54.210526 | P14: =VLOOKUP($A14, RawData!$A:$AJ, 7, FALSE) | Q14: =VLOOKUP($A14, RawData!$A:$AJ, 8, FALSE) -> 0.7281 | R14: =VLOOKUP($A14, RawData!$A:$AJ, 11, FALSE) | S14: =VLOOKUP($A14, RawData!$A:$AJ, 13, FALSE) -> 0.849 | T14: =VLOOKUP($A14, RawData!$A:$AJ, 14, FALSE) -> -141.5 | U14: =VLOOKUP($A14, RawData!$A:$AJ, 23, FALSE) -> 0.5661 | V14: =VLOOKUP($A14, RawData!$A:$AJ, 24, FALSE) | W14: =VLOOKUP($A14, RawData!$A:$AJ, 25, FALSE) | X14: =VLOOKUP($A14, RawData!$A:$AJ, 26, FALSE) -> 7.9996824 | Y14: =VLOOKUP($A14, RawData!$A:$AJ, 27, FALSE) | Z14: =VLOOKUP($A14, RawData!$A:$AJ, 28, FALSE) -> 4.5831056 | AA14: =VLOOKUP($A14, RawData!$A:$AJ, 31, FALSE) -> 56.565372 | AB14: =VLOOKUP($A14, RawData!$A:$AJ,32, FALSE) | AC14: =VLOOKUP($A14, RawData!$A:$AJ, 34, FALSE) -> 48.024 | AD14: =VLOOKUP($A14, RawData!$A:$AJ, 35, FALSE) -> 20.14 | AE14: =VLOOKUP($A14, RawData!$A:$AJ, 36, FALSE) -> 2.5
A15: TSAT | B15: Telesat | C15: Low | D15: [READ PITCH](https://community.microcapclub.com/forums/topic/3887-telesat-corporation-tsat/#comment-83043) | E15: =IFERROR(__xludf.DUMMYFUNCTION("IFERROR(HYPERLINK(REGEXEXTRACT(D15,""\(([^)]*)\)""),REGEXEXTRACT(D15,""\[([^\]]+)\]"")),"""") "),"READ PITCH") -> READ PITCH | F15: =VLOOKUP($A15, RawData!$A:$AJ, 33, FALSE) -> 474.00955 | G15: =VLOOKUP($A15, RawData!$A:$AJ, 2, FALSE) | H15: =VLOOKUP($A15, RawData!$A:$AJ, 3, FALSE) -> -0.2579 | I15: =VLOOKUP($A15, RawData!$A:$AJ, 4, FALSE) -> -0.12115695 | J15: =VLOOKUP($A15, RawData!$A:$AM, 37, FALSE) -> 21.358 | K15: =VLOOKUP($A15, RawData!$A:$AM, 38, FALSE) | L15: =VLOOKUP($A15, RawData!$A:$AM, 39, FALSE) -> -0.5451669 | M15: =VLOOKUP($A15, RawData!$A:$AJ, 30, FALSE) -> 163.88249 | N15: =VLOOKUP($A15, RawData!$A:$AJ, 5, FALSE) -> -3.055823 | O15: =VLOOKUP($A15, RawData!$A:$AJ, 6, FALSE) -> -4.2065806 | P15: =VLOOKUP($A15, RawData!$A:$AJ, 7, FALSE) | Q15: =VLOOKUP($A15, RawData!$A:$AJ, 8, FALSE) -> 0.9429 | R15: =VLOOKUP($A15, RawData!$A:$AJ, 11, FALSE) | S15: =VLOOKUP($A15, RawData!$A:$AJ, 13, FALSE) -> -1009.604 | T15: =VLOOKUP($A15, RawData!$A:$AJ, 14, FALSE) -> 1.9206115 | U15: =VLOOKUP($A15, RawData!$A:$AJ, 23, FALSE) -> -0.0225 | V15: =VLOOKUP($A15, RawData!$A:$AJ, 24, FALSE) | W15: =VLOOKUP($A15, RawData!$A:$AJ, 25, FALSE) | X15: =VLOOKUP($A15, RawData!$A:$AJ, 26, FALSE) | Y15: =VLOOKUP($A15, RawData!$A:$AJ, 27, FALSE) | Z15: =VLOOKUP($A15, RawData!$A:$AJ, 28, FALSE) -> 1.4564012 | AA15: =VLOOKUP($A15, RawData!$A:$AJ, 31, FALSE) -> -3.46692 | AB15: =VLOOKUP($A15, RawData!$A:$AJ,32, FALSE) | AC15: =VLOOKUP($A15, RawData!$A:$AJ, 34, FALSE) -> 2520.8516 | AD15: =VLOOKUP($A15, RawData!$A:$AJ, 35, FALSE) -> 33.78 | AE15: =VLOOKUP($A15, RawData!$A:$AJ, 36, FALSE) -> 51.09
A16: CSPI | B16: CSP Inc. | C16: Medium | D16: [READ PITCH](https://community.microcapclub.com/forums/topic/4176-csp-inc-cspi/#comment-86378) | E16: =IFERROR(__xludf.DUMMYFUNCTION("IFERROR(HYPERLINK(REGEXEXTRACT(D16,""\(([^)]*)\)""),REGEXEXTRACT(D16,""\[([^\]]+)\]"")),"""") "),"READ PITCH") -> READ PITCH | F16: =VLOOKUP($A16, RawData!$A:$AJ, 33, FALSE) -> 114.54882 | G16: =VLOOKUP($A16, RawData!$A:$AJ, 2, FALSE) | H16: =VLOOKUP($A16, RawData!$A:$AJ, 3, FALSE) -> -0.2162 | I16: =VLOOKUP($A16, RawData!$A:$AJ, 4, FALSE) -> -0.07033556 | J16: =VLOOKUP($A16, RawData!$A:$AM, 37, FALSE) -> -2.94 | K16: =VLOOKUP($A16, RawData!$A:$AM, 38, FALSE) | L16: =VLOOKUP($A16, RawData!$A:$AM, 39, FALSE) -> 0.26239598 | M16: =VLOOKUP($A16, RawData!$A:$AJ, 30, FALSE) -> -30.354218 | N16: =VLOOKUP($A16, RawData!$A:$AJ, 5, FALSE) -> -0.009229209 | O16: =VLOOKUP($A16, RawData!$A:$AJ, 6, FALSE) -> -0.7283582 | P16: =VLOOKUP($A16, RawData!$A:$AJ, 7, FALSE) | Q16: =VLOOKUP($A16, RawData!$A:$AJ, 8, FALSE) -> 0.3248 | R16: =VLOOKUP($A16, RawData!$A:$AJ, 11, FALSE) | S16: =VLOOKUP($A16, RawData!$A:$AJ, 13, FALSE) -> 1.894 | T16: =VLOOKUP($A16, RawData!$A:$AJ, 14, FALSE) -> 0.4735 | U16: =VLOOKUP($A16, RawData!$A:$AJ, 23, FALSE) -> -0.0013 | V16: =VLOOKUP($A16, RawData!$A:$AJ, 24, FALSE) | W16: =VLOOKUP($A16, RawData!$A:$AJ, 25, FALSE) | X16: =VLOOKUP($A16, RawData!$A:$AJ, 26, FALSE) | Y16: =VLOOKUP($A16, RawData!$A:$AJ, 27, FALSE) -> No data | Z16: =VLOOKUP($A16, RawData!$A:$AJ, 28, FALSE) -> 2.6744697 | AA16: =VLOOKUP($A16, RawData!$A:$AJ, 31, FALSE) -> 47.11795 | AB16: =VLOOKUP($A16, RawData!$A:$AJ,32, FALSE) | AC16: =VLOOKUP($A16, RawData!$A:$AJ, 34, FALSE) -> 89.2414 | AD16: =VLOOKUP($A16, RawData!$A:$AJ, 35, FALSE) -> 11.74 | AE16: =VLOOKUP($A16, RawData!$A:$AJ, 36, FALSE) -> 9.86
A17: SPOK | B17: Spok Holdings | C17: Low | D17: [READ PITCH](https://community.microcapclub.com/forums/topic/3683-spok-holdings-spok/#comment-80588) | E17: =IFERROR(__xludf.DUMMYFUNCTION("IFERROR(HYPERLINK(REGEXEXTRACT(D17,""\(([^)]*)\)""),REGEXEXTRACT(D17,""\[([^\]]+)\]"")),"""") "),"READ PITCH") -> READ PITCH | F17: =VLOOKUP($A17, RawData!$A:$AJ, 33, FALSE) -> 268.31177 | G17: =VLOOKUP($A17, RawData!$A:$AJ, 2, FALSE) | H17: =VLOOKUP($A17, RawData!$A:$AJ, 3, FALSE) -> 0.0147 | I17: =VLOOKUP($A17, RawData!$A:$AJ, 4, FALSE) -> -0.014334536 | J17: =VLOOKUP($A17, RawData!$A:$AM, 37, FALSE) -> 24.705 | K17: =VLOOKUP($A17, RawData!$A:$AM, 38, FALSE) | L17: =VLOOKUP($A17, RawData!$A:$AM, 39, FALSE) -> 0.3226834 | M17: =VLOOKUP($A17, RawData!$A:$AJ, 30, FALSE) -> 10.174661 | N17: =VLOOKUP($A17, RawData!$A:$AJ, 5, FALSE) -> 0.8055825 | O17: =VLOOKUP($A17, RawData!$A:$AJ, 6, FALSE) -> 0.12998775 | P17: =VLOOKUP($A17, RawData!$A:$AJ, 7, FALSE) | Q17: =VLOOKUP($A17, RawData!$A:$AJ, 8, FALSE) -> 0.6274 | R17: =VLOOKUP($A17, RawData!$A:$AJ, 11, FALSE) | S17: =VLOOKUP($A17, RawData!$A:$AJ, 13, FALSE) -> 22.623 | T17: =VLOOKUP($A17, RawData!$A:$AJ, 14, FALSE) -> 0.7818829 | U17: =VLOOKUP($A17, RawData!$A:$AJ, 23, FALSE) -> 0.079 | V17: =VLOOKUP($A17, RawData!$A:$AJ, 24, FALSE) | W17: =VLOOKUP($A17, RawData!$A:$AJ, 25, FALSE) | X17: =VLOOKUP($A17, RawData!$A:$AJ, 26, FALSE) -> 16.435312 | Y17: =VLOOKUP($A17, RawData!$A:$AJ, 27, FALSE) -> 16.22549 | Z17: =VLOOKUP($A17, RawData!$A:$AJ, 28, FALSE) -> 1.9518101 | AA17: =VLOOKUP($A17, RawData!$A:$AJ, 31, FALSE) -> 11.111037 | AB17: =VLOOKUP($A17, RawData!$A:$AJ,32, FALSE) | AC17: =VLOOKUP($A17, RawData!$A:$AJ, 34, FALSE) -> 251.365 | AD17: =VLOOKUP($A17, RawData!$A:$AJ, 35, FALSE) -> 13.24 | AE17: =VLOOKUP($A17, RawData!$A:$AJ, 36, FALSE) -> 20.6
A18: SILC | B18: Silicom | C18: Low | D18: [READ PITCH](https://community.microcapclub.com/forums/topic/1454-silicom-silc/#comment-31959) | E18: =IFERROR(__xludf.DUMMYFUNCTION("IFERROR(HYPERLINK(REGEXEXTRACT(D18,""\(([^)]*)\)""),REGEXEXTRACT(D18,""\[([^\]]+)\]"")),"""") "),"READ PITCH") -> READ PITCH | F18: =VLOOKUP($A18, RawData!$A:$AJ, 33, FALSE) -> 88.98035 | G18: =VLOOKUP($A18, RawData!$A:$AJ, 2, FALSE) | H18: =VLOOKUP($A18, RawData!$A:$AJ, 3, FALSE) -> -0.4262 | I18: =VLOOKUP($A18, RawData!$A:$AJ, 4, FALSE) -> -0.022336941 | J18: =VLOOKUP($A18, RawData!$A:$AM, 37, FALSE) -> 0 | K18: =VLOOKUP($A18, RawData!$A:$AM, 38, FALSE) | L18: =VLOOKUP($A18, RawData!$A:$AM, 39, FALSE) -> -0.22127618 | M18: =VLOOKUP($A18, RawData!$A:$AJ, 30, FALSE) | N18: =VLOOKUP($A18, RawData!$A:$AJ, 5, FALSE) -> 0 | O18: =VLOOKUP($A18, RawData!$A:$AJ, 6, FALSE) -> -1.1495436 | P18: =VLOOKUP($A18, RawData!$A:$AJ, 7, FALSE) | Q18: =VLOOKUP($A18, RawData!$A:$AJ, 8, FALSE) -> 0.2896 | R18: =VLOOKUP($A18, RawData!$A:$AJ, 11, FALSE) | S18: =VLOOKUP($A18, RawData!$A:$AJ, 13, FALSE) -> 0 | T18: =VLOOKUP($A18, RawData!$A:$AJ, 14, FALSE) -> 17.513794 | U18: =VLOOKUP($A18, RawData!$A:$AJ, 23, FALSE) -> -0.0984 | V18: =VLOOKUP($A18, RawData!$A:$AJ, 24, FALSE) | W18: =VLOOKUP($A18, RawData!$A:$AJ, 25, FALSE) | X18: =VLOOKUP($A18, RawData!$A:$AJ, 26, FALSE) | Y18: =VLOOKUP($A18, RawData!$A:$AJ, 27, FALSE) | Z18: =VLOOKUP($A18, RawData!$A:$AJ, 28, FALSE) -> 1.4409026 | AA18: =VLOOKUP($A18, RawData!$A:$AJ, 31, FALSE) | AB18: =VLOOKUP($A18, RawData!$A:$AJ,32, FALSE) | AC18: =VLOOKUP($A18, RawData!$A:$AJ, 34, FALSE) -> 84.483 | AD18: =VLOOKUP($A18, RawData!$A:$AJ, 35, FALSE) -> 14.9 | AE18: =VLOOKUP($A18, RawData!$A:$AJ, 36, FALSE) -> 5.67
A19: SODI | B19: Solitron Devices | C19: Medium | D19: [READ PITCH](https://community.microcapclub.com/forums/topic/2871-solitron-devices-sodi/#comment-66366) | E19: =IFERROR(__xludf.DUMMYFUNCTION("IFERROR(HYPERLINK(REGEXEXTRACT(D19,""\(([^)]*)\)""),REGEXEXTRACT(D19,""\[([^\]]+)\]"")),"""") "),"READ PITCH") -> READ PITCH | F19: =VLOOKUP($A19, RawData!$A:$AJ, 33, FALSE) -> 39.761353 | G19: =VLOOKUP($A19, RawData!$A:$AJ, 2, FALSE) | H19: =VLOOKUP($A19, RawData!$A:$AJ, 3, FALSE) -> -0.1594 | I19: =VLOOKUP($A19, RawData!$A:$AJ, 4, FALSE) -> 0.05985148 | J19: =VLOOKUP($A19, RawData!$A:$AM, 37, FALSE) -> 0.479 | K19: =VLOOKUP($A19, RawData!$A:$AM, 38, FALSE) | L19: =VLOOKUP($A19, RawData!$A:$AM, 39, FALSE) -> -0.14264044 | M19: =VLOOKUP($A19, RawData!$A:$AJ, 30, FALSE) -> 89.98852 | N19: =VLOOKUP($A19, RawData!$A:$AJ, 5, FALSE) -> -0.17272727 | O19: =VLOOKUP($A19, RawData!$A:$AJ, 6, FALSE) -> -1.0566008 | P19: =VLOOKUP($A19, RawData!$A:$AJ, 7, FALSE) | Q19: =VLOOKUP($A19, RawData!$A:$AJ, 8, FALSE) -> 0.2126 | R19: =VLOOKUP($A19, RawData!$A:$AJ, 11, FALSE) | S19: =VLOOKUP($A19, RawData!$A:$AJ, 13, FALSE) -> 1.472 | T19: =VLOOKUP($A19, RawData!$A:$AJ, 14, FALSE) -> 3.0413222 | U19: =VLOOKUP($A19, RawData!$A:$AJ, 23, FALSE) -> -0.0148 | V19: =VLOOKUP($A19, RawData!$A:$AJ, 24, FALSE) | W19: =VLOOKUP($A19, RawData!$A:$AJ, 25, FALSE) | X19: =VLOOKUP($A19, RawData!$A:$AJ, 26, FALSE) | Y19: =VLOOKUP($A19, RawData!$A:$AJ, 27, FALSE) -> No data | Z19: =VLOOKUP($A19, RawData!$A:$AJ, 28, FALSE) -> 3.1935618 | AA19: =VLOOKUP($A19, RawData!$A:$AJ, 31, FALSE) -> 29.282948 | AB19: =VLOOKUP($A19, RawData!$A:$AJ,32, FALSE) | AC19: =VLOOKUP($A19, RawData!$A:$AJ, 34, FALSE) -> 43.1045 | AD19: =VLOOKUP($A19, RawData!$A:$AJ, 35, FALSE) -> 21 | AE19: =VLOOKUP($A19, RawData!$A:$AJ, 36, FALSE) -> 2.09
A20: THRY | B20: Thryv Holdings, Inc. | C20: Medium | D20: [READ PITCH](https://community.microcapclub.com/forums/topic/5021-thryv-holdings-inc-thry/#comment-97946) | E20: =IFERROR(__xludf.DUMMYFUNCTION("IFERROR(HYPERLINK(REGEXEXTRACT(D20,""\(([^)]*)\)""),REGEXEXTRACT(D20,""\[([^\]]+)\]"")),"""") "),"READ PITCH") -> READ PITCH | F20: =VLOOKUP($A20, RawData!$A:$AJ, 33, FALSE) -> 241.41597 | G20: =VLOOKUP($A20, RawData!$A:$AJ, 2, FALSE) | H20: =VLOOKUP($A20, RawData!$A:$AJ, 3, FALSE) -> -0.1073 | I20: =VLOOKUP($A20, RawData!$A:$AJ, 4, FALSE) -> -0.019909434 | J20: =VLOOKUP($A20, RawData!$A:$AM, 37, FALSE) -> 110.116 | K20: =VLOOKUP($A20, RawData!$A:$AM, 38, FALSE) | L20: =VLOOKUP($A20, RawData!$A:$AM, 39, FALSE) -> -0.18989244 | M20: =VLOOKUP($A20, RawData!$A:$AJ, 30, FALSE) -> 4.503289 | N20: =VLOOKUP($A20, RawData!$A:$AJ, 5, FALSE) -> 0.40959156 | O20: =VLOOKUP($A20, RawData!$A:$AJ, 6, FALSE) -> -1.0525557 | P20: =VLOOKUP($A20, RawData!$A:$AJ, 7, FALSE) | Q20: =VLOOKUP($A20, RawData!$A:$AJ, 8, FALSE) -> 0.6736 | R20: =VLOOKUP($A20, RawData!$A:$AJ, 11, FALSE) | S20: =VLOOKUP($A20, RawData!$A:$AJ, 13, FALSE) -> 36.166 | T20: =VLOOKUP($A20, RawData!$A:$AJ, 14, FALSE) -> 0.49513978 | U20: =VLOOKUP($A20, RawData!$A:$AJ, 23, FALSE) -> 0.0255 | V20: =VLOOKUP($A20, RawData!$A:$AJ, 24, FALSE) | W20: =VLOOKUP($A20, RawData!$A:$AJ, 25, FALSE) | X20: =VLOOKUP($A20, RawData!$A:$AJ, 26, FALSE) -> 13.403597 | Y20: =VLOOKUP($A20, RawData!$A:$AJ, 27, FALSE) -> 10.574368 | Z20: =VLOOKUP($A20, RawData!$A:$AJ, 28, FALSE) -> 0.3067393 | AA20: =VLOOKUP($A20, RawData!$A:$AJ, 31, FALSE) -> 13.711337 | AB20: =VLOOKUP($A20, RawData!$A:$AJ,32, FALSE) | AC20: =VLOOKUP($A20, RawData!$A:$AJ, 34, FALSE) -> 495.8842 | AD20: =VLOOKUP($A20, RawData!$A:$AJ, 35, FALSE) -> 5.49 | AE20: =VLOOKUP($A20, RawData!$A:$AJ, 36, FALSE) -> 43.58
A21: GAMB | B21: Gambling.com Group Ltd | C21: Low | D21: [READ PITCH](https://community.microcapclub.com/forums/topic/4512-gamblingcom-group-ltd-gamb/#comment-91092) | E21: =IFERROR(__xludf.DUMMYFUNCTION("IFERROR(HYPERLINK(REGEXEXTRACT(D21,""\(([^)]*)\)""),REGEXEXTRACT(D21,""\[([^\]]+)\]"")),"""") "),"READ PITCH") -> READ PITCH | F21: =VLOOKUP($A21, RawData!$A:$AJ, 33, FALSE) -> 185.49243 | G21: =VLOOKUP($A21, RawData!$A:$AJ, 2, FALSE) | H21: =VLOOKUP($A21, RawData!$A:$AJ, 3, FALSE) -> 0.2421 | I21: =VLOOKUP($A21, RawData!$A:$AJ, 4, FALSE) -> 0.38248485 | J21: =VLOOKUP($A21, RawData!$A:$AM, 37, FALSE) -> 13.447 | K21: =VLOOKUP($A21, RawData!$A:$AM, 38, FALSE) | L21: =VLOOKUP($A21, RawData!$A:$AM, 39, FALSE) -> -0.056652006 | M21: =VLOOKUP($A21, RawData!$A:$AJ, 30, FALSE) -> 19.141623 | N21: =VLOOKUP($A21, RawData!$A:$AJ, 5, FALSE) -> 0.053852715 | O21: =VLOOKUP($A21, RawData!$A:$AJ, 6, FALSE) -> -0.9479942 | P21: =VLOOKUP($A21, RawData!$A:$AJ, 7, FALSE) | Q21: =VLOOKUP($A21, RawData!$A:$AJ, 8, FALSE) -> 0.9317 | R21: =VLOOKUP($A21, RawData!$A:$AJ, 11, FALSE) | S21: =VLOOKUP($A21, RawData!$A:$AJ, 13, FALSE) -> 41.879 | T21: =VLOOKUP($A21, RawData!$A:$AJ, 14, FALSE) -> 26.966516 | U21: =VLOOKUP($A21, RawData!$A:$AJ, 23, FALSE) -> 0.0069 | V21: =VLOOKUP($A21, RawData!$A:$AJ, 24, FALSE) | W21: =VLOOKUP($A21, RawData!$A:$AJ, 25, FALSE) | X21: =VLOOKUP($A21, RawData!$A:$AJ, 26, FALSE) -> 93.21721 | Y21: =VLOOKUP($A21, RawData!$A:$AJ, 27, FALSE) | Z21: =VLOOKUP($A21, RawData!$A:$AJ, 28, FALSE) -> 1.1425999 | AA21: =VLOOKUP($A21, RawData!$A:$AJ, 31, FALSE) -> 6.1462164 | AB21: =VLOOKUP($A21, RawData!$A:$AJ,32, FALSE) | AC21: =VLOOKUP($A21, RawData!$A:$AJ, 34, FALSE) -> 257.3974 | AD21: =VLOOKUP($A21, RawData!$A:$AJ, 35, FALSE) -> 5.02 | AE21: =VLOOKUP($A21, RawData!$A:$AJ, 36, FALSE) -> 35.17
A22: INLX | B22: Intellinetics | C22: Low | D22: [READ PITCH](https://community.microcapclub.com/forums/topic/3261-intellinetics-inlx/#comment-73710) | E22: =IFERROR(__xludf.DUMMYFUNCTION("IFERROR(HYPERLINK(REGEXEXTRACT(D22,""\(([^)]*)\)""),REGEXEXTRACT(D22,""\[([^\]]+)\]"")),"""") "),"READ PITCH") -> READ PITCH | F22: =VLOOKUP($A22, RawData!$A:$AJ, 33, FALSE) -> 36.056942 | G22: =VLOOKUP($A22, RawData!$A:$AJ, 2, FALSE) | H22: =VLOOKUP($A22, RawData!$A:$AJ, 3, FALSE) -> -0.0263 | I22: =VLOOKUP($A22, RawData!$A:$AJ, 4, FALSE) -> 0.24878028 | J22: =VLOOKUP($A22, RawData!$A:$AM, 37, FALSE) -> -0.19138 | K22: =VLOOKUP($A22, RawData!$A:$AM, 38, FALSE) | L22: =VLOOKUP($A22, RawData!$A:$AM, 39, FALSE) -> -0.3473945 | M22: =VLOOKUP($A22, RawData!$A:$AJ, 30, FALSE) -> -181.42876 | N22: =VLOOKUP($A22, RawData!$A:$AJ, 5, FALSE) -> -0.38877454 | O22: =VLOOKUP($A22, RawData!$A:$AJ, 6, FALSE) -> -11.167007 | P22: =VLOOKUP($A22, RawData!$A:$AJ, 7, FALSE) | Q22: =VLOOKUP($A22, RawData!$A:$AJ, 8, FALSE) -> 0.655 | R22: =VLOOKUP($A22, RawData!$A:$AJ, 11, FALSE) | S22: =VLOOKUP($A22, RawData!$A:$AJ, 13, FALSE) -> 1.35092 | T22: =VLOOKUP($A22, RawData!$A:$AJ, 14, FALSE) -> 0.6290957 | U22: =VLOOKUP($A22, RawData!$A:$AJ, 23, FALSE) -> -0.0958 | V22: =VLOOKUP($A22, RawData!$A:$AJ, 24, FALSE) | W22: =VLOOKUP($A22, RawData!$A:$AJ, 25, FALSE) | X22: =VLOOKUP($A22, RawData!$A:$AJ, 26, FALSE) | Y22: =VLOOKUP($A22, RawData!$A:$AJ, 27, FALSE) | Z22: =VLOOKUP($A22, RawData!$A:$AJ, 28, FALSE) -> 2.1353362 | AA22: =VLOOKUP($A22, RawData!$A:$AJ, 31, FALSE) -> 25.702362 | AB22: =VLOOKUP($A22, RawData!$A:$AJ,32, FALSE) | AC22: =VLOOKUP($A22, RawData!$A:$AJ, 34, FALSE) -> 34.721832 | AD22: =VLOOKUP($A22, RawData!$A:$AJ, 35, FALSE) -> 8.1638 | AE22: =VLOOKUP($A22, RawData!$A:$AJ, 36, FALSE) -> 4.48
A23: QXO | B23: QXO Inc | C23: Medium | D23: [READ PITCH](https://community.microcapclub.com/forums/topic/1753-qxo-inc-qxo/#comment-39287) | E23: =IFERROR(__xludf.DUMMYFUNCTION("IFERROR(HYPERLINK(REGEXEXTRACT(D23,""\(([^)]*)\)""),REGEXEXTRACT(D23,""\[([^\]]+)\]"")),"""") "),"READ PITCH") -> READ PITCH | F23: =VLOOKUP($A23, RawData!$A:$AJ, 33, FALSE) -> 16647.37 | G23: =VLOOKUP($A23, RawData!$A:$AJ, 2, FALSE) | H23: =VLOOKUP($A23, RawData!$A:$AJ, 3, FALSE) -> 81.0375 | I23: =VLOOKUP($A23, RawData!$A:$AJ, 4, FALSE) -> 32.85121 | J23: =VLOOKUP($A23, RawData!$A:$AM, 37, FALSE) -> 211.806 | K23: =VLOOKUP($A23, RawData!$A:$AM, 38, FALSE) | L23: =VLOOKUP($A23, RawData!$A:$AM, 39, FALSE) -> No data | M23: =VLOOKUP($A23, RawData!$A:$AJ, 30, FALSE) -> 85.85466 | N23: =VLOOKUP($A23, RawData!$A:$AJ, 5, FALSE) -> -0.2637287 | O23: =VLOOKUP($A23, RawData!$A:$AJ, 6, FALSE) -> -11.401957 | P23: =VLOOKUP($A23, RawData!$A:$AJ, 7, FALSE) | Q23: =VLOOKUP($A23, RawData!$A:$AJ, 8, FALSE) -> 0.2249 | R23: =VLOOKUP($A23, RawData!$A:$AJ, 11, FALSE) | S23: =VLOOKUP($A23, RawData!$A:$AJ, 13, FALSE) -> 78.922 | T23: =VLOOKUP($A23, RawData!$A:$AJ, 14, FALSE) -> 2.5809157 | U23: =VLOOKUP($A23, RawData!$A:$AJ, 23, FALSE) -> -0.0162 | V23: =VLOOKUP($A23, RawData!$A:$AJ, 24, FALSE) | W23: =VLOOKUP($A23, RawData!$A:$AJ, 25, FALSE) | X23: =VLOOKUP($A23, RawData!$A:$AJ, 26, FALSE) | Y23: =VLOOKUP($A23, RawData!$A:$AJ, 27, FALSE) -> 82.51473 | Z23: =VLOOKUP($A23, RawData!$A:$AJ, 28, FALSE) -> 3.6908894 | AA23: =VLOOKUP($A23, RawData!$A:$AJ, 31, FALSE) -> 230.41145 | AB23: =VLOOKUP($A23, RawData!$A:$AJ,32, FALSE) | AC23: =VLOOKUP($A23, RawData!$A:$AJ, 34, FALSE) -> 18184.533 | AD23: =VLOOKUP($A23, RawData!$A:$AJ, 35, FALSE) -> 25.52 | AE23: =VLOOKUP($A23, RawData!$A:$AJ, 36, FALSE) -> 674.39
A24: OOMA | B24: OOMA | C24: Lowest | D24: [READ PITCH](https://community.microcapclub.com/forums/topic/2485-ooma-inc-ooma/#comment-57608) | E24: =IFERROR(__xludf.DUMMYFUNCTION("IFERROR(HYPERLINK(REGEXEXTRACT(D24,""\(([^)]*)\)""),REGEXEXTRACT(D24,""\[([^\]]+)\]"")),"""") "),"READ PITCH") -> READ PITCH | F24: =VLOOKUP($A24, RawData!$A:$AJ, 33, FALSE) -> 317.12402 | G24: =VLOOKUP($A24, RawData!$A:$AJ, 2, FALSE) | H24: =VLOOKUP($A24, RawData!$A:$AJ, 3, FALSE) -> 0.0422 | I24: =VLOOKUP($A24, RawData!$A:$AJ, 4, FALSE) -> 0.09820402 | J24: =VLOOKUP($A24, RawData!$A:$AM, 37, FALSE) -> 17.246 | K24: =VLOOKUP($A24, RawData!$A:$AM, 38, FALSE) | L24: =VLOOKUP($A24, RawData!$A:$AM, 39, FALSE) -> 1.3713306 | M24: =VLOOKUP($A24, RawData!$A:$AJ, 30, FALSE) -> 17.94503 | N24: =VLOOKUP($A24, RawData!$A:$AJ, 5, FALSE) -> 0.08137681 | O24: =VLOOKUP($A24, RawData!$A:$AJ, 6, FALSE) -> -1.2314509 | P24: =VLOOKUP($A24, RawData!$A:$AJ, 7, FALSE) | Q24: =VLOOKUP($A24, RawData!$A:$AJ, 8, FALSE) -> 0.61 | R24: =VLOOKUP($A24, RawData!$A:$AJ, 11, FALSE) | S24: =VLOOKUP($A24, RawData!$A:$AJ, 13, FALSE) -> 18.885 | T24: =VLOOKUP($A24, RawData!$A:$AJ, 14, FALSE) -> 1.0217497 | U24: =VLOOKUP($A24, RawData!$A:$AJ, 23, FALSE) -> 0.015 | V24: =VLOOKUP($A24, RawData!$A:$AJ, 24, FALSE) | W24: =VLOOKUP($A24, RawData!$A:$AJ, 25, FALSE) | X24: =VLOOKUP($A24, RawData!$A:$AJ, 26, FALSE) -> 147.46216 | Y24: =VLOOKUP($A24, RawData!$A:$AJ, 27, FALSE) -> 19.392475 | Z24: =VLOOKUP($A24, RawData!$A:$AJ, 28, FALSE) -> 1.2539992 | AA24: =VLOOKUP($A24, RawData!$A:$AJ, 31, FALSE) -> 16.38761 | AB24: =VLOOKUP($A24, RawData!$A:$AJ,32, FALSE) | AC24: =VLOOKUP($A24, RawData!$A:$AJ, 34, FALSE) -> 309.48 | AD24: =VLOOKUP($A24, RawData!$A:$AJ, 35, FALSE) -> 12 | AE24: =VLOOKUP($A24, RawData!$A:$AJ, 36, FALSE) -> 27.6
A25: MGNI | B25: Magnite | C25: Low | D25: [READ PITCH](https://community.microcapclub.com/forums/topic/2449-magnite-mgni/) | E25: =IFERROR(__xludf.DUMMYFUNCTION("IFERROR(HYPERLINK(REGEXEXTRACT(D25,""\(([^)]*)\)""),REGEXEXTRACT(D25,""\[([^\]]+)\]"")),"""") "),"READ PITCH") -> READ PITCH | F25: =VLOOKUP($A25, RawData!$A:$AJ, 33, FALSE) -> 2339.3057 | G25: =VLOOKUP($A25, RawData!$A:$AJ, 2, FALSE) | H25: =VLOOKUP($A25, RawData!$A:$AJ, 3, FALSE) -> 0.0627 | I25: =VLOOKUP($A25, RawData!$A:$AJ, 4, FALSE) -> 0.30154607 | J25: =VLOOKUP($A25, RawData!$A:$AM, 37, FALSE) -> 141.891 | K25: =VLOOKUP($A25, RawData!$A:$AM, 38, FALSE) | L25: =VLOOKUP($A25, RawData!$A:$AM, 39, FALSE) -> 0.8258396 | M25: =VLOOKUP($A25, RawData!$A:$AJ, 30, FALSE) -> 16.01217 | N25: =VLOOKUP($A25, RawData!$A:$AJ, 5, FALSE) -> 0.4035503 | O25: =VLOOKUP($A25, RawData!$A:$AJ, 6, FALSE) -> 2.3522234 | P25: =VLOOKUP($A25, RawData!$A:$AJ, 7, FALSE) | Q25: =VLOOKUP($A25, RawData!$A:$AJ, 8, FALSE) -> 0.623 | R25: =VLOOKUP($A25, RawData!$A:$AJ, 11, FALSE) | S25: =VLOOKUP($A25, RawData!$A:$AJ, 13, FALSE) -> 160.728 | T25: =VLOOKUP($A25, RawData!$A:$AJ, 14, FALSE) -> 1.0249268 | U25: =VLOOKUP($A25, RawData!$A:$AJ, 23, FALSE) -> 0.0204 | V25: =VLOOKUP($A25, RawData!$A:$AJ, 24, FALSE) | W25: =VLOOKUP($A25, RawData!$A:$AJ, 25, FALSE) | X25: =VLOOKUP($A25, RawData!$A:$AJ, 26, FALSE) -> 37.91349 | Y25: =VLOOKUP($A25, RawData!$A:$AJ, 27, FALSE) -> 17.821783 | Z25: =VLOOKUP($A25, RawData!$A:$AJ, 28, FALSE) -> 3.1283154 | AA25: =VLOOKUP($A25, RawData!$A:$AJ, 31, FALSE) -> 14.135577 | AB25: =VLOOKUP($A25, RawData!$A:$AJ,32, FALSE) | AC25: =VLOOKUP($A25, RawData!$A:$AJ, 34, FALSE) -> 2271.983 | AD25: =VLOOKUP($A25, RawData!$A:$AJ, 35, FALSE) -> 15.3 | AE25: =VLOOKUP($A25, RawData!$A:$AJ, 36, FALSE) -> 143.65
A26: NEON | B26: Neonode | C26: Medium | D26: [READ PITCH](https://community.microcapclub.com/forums/topic/209-neonode-neon/#comment-1166) | E26: =IFERROR(__xludf.DUMMYFUNCTION("IFERROR(HYPERLINK(REGEXEXTRACT(D26,""\(([^)]*)\)""),REGEXEXTRACT(D26,""\[([^\]]+)\]"")),"""") "),"READ PITCH") -> READ PITCH | F26: =VLOOKUP($A26, RawData!$A:$AJ, 33, FALSE) -> 31.384066 | G26: =VLOOKUP($A26, RawData!$A:$AJ, 2, FALSE) | H26: =VLOOKUP($A26, RawData!$A:$AJ, 3, FALSE) -> -0.4854 | I26: =VLOOKUP($A26, RawData!$A:$AJ, 4, FALSE) -> -0.15698351 | J26: =VLOOKUP($A26, RawData!$A:$AM, 37, FALSE) -> 8.743 | K26: =VLOOKUP($A26, RawData!$A:$AM, 38, FALSE) | L26: =VLOOKUP($A26, RawData!$A:$AM, 39, FALSE) -> 0.012710306 | M26: =VLOOKUP($A26, RawData!$A:$AJ, 30, FALSE) -> 2.2865608 | N26: =VLOOKUP($A26, RawData!$A:$AJ, 5, FALSE) -> 0.5353397 | O26: =VLOOKUP($A26, RawData!$A:$AJ, 6, FALSE) -> -1.832453 | P26: =VLOOKUP($A26, RawData!$A:$AJ, 7, FALSE) | Q26: =VLOOKUP($A26, RawData!$A:$AJ, 8, FALSE) -> 0.9654 | R26: =VLOOKUP($A26, RawData!$A:$AJ, 11, FALSE) | S26: =VLOOKUP($A26, RawData!$A:$AJ, 13, FALSE) -> -5.89 | T26: =VLOOKUP($A26, RawData!$A:$AJ, 14, FALSE) -> 0.8742764 | U26: =VLOOKUP($A26, RawData!$A:$AJ, 23, FALSE) -> 0.4317 | V26: =VLOOKUP($A26, RawData!$A:$AJ, 24, FALSE) | W26: =VLOOKUP($A26, RawData!$A:$AJ, 25, FALSE) | X26: =VLOOKUP($A26, RawData!$A:$AJ, 26, FALSE) -> 3.5117888 | Y26: =VLOOKUP($A26, RawData!$A:$AJ, 27, FALSE) | Z26: =VLOOKUP($A26, RawData!$A:$AJ, 28, FALSE) -> 14.358853 | AA26: =VLOOKUP($A26, RawData!$A:$AJ, 31, FALSE) -> -3.3941257 | AB26: =VLOOKUP($A26, RawData!$A:$AJ,32, FALSE) | AC26: =VLOOKUP($A26, RawData!$A:$AJ, 34, FALSE) -> 19.9914 | AD26: =VLOOKUP($A26, RawData!$A:$AJ, 35, FALSE) -> 1.88 | AE26: =VLOOKUP($A26, RawData!$A:$AJ, 36, FALSE) -> 16.78
A27: AEYE | B27: AudioEye | C27: Medium | D27: [READ PITCH](https://community.microcapclub.com/forums/topic/2185-audioeye-aeye/#comment-50335) | E27: =IFERROR(__xludf.DUMMYFUNCTION("IFERROR(HYPERLINK(REGEXEXTRACT(D27,""\(([^)]*)\)""),REGEXEXTRACT(D27,""\[([^\]]+)\]"")),"""") "),"READ PITCH") -> READ PITCH | F27: =VLOOKUP($A27, RawData!$A:$AJ, 33, FALSE) -> 118.03896 | G27: =VLOOKUP($A27, RawData!$A:$AJ, 2, FALSE) | H27: =VLOOKUP($A27, RawData!$A:$AJ, 3, FALSE) -> 0.1857 | I27: =VLOOKUP($A27, RawData!$A:$AJ, 4, FALSE) -> 0.16468386 | J27: =VLOOKUP($A27, RawData!$A:$AM, 37, FALSE) -> 0.985 | K27: =VLOOKUP($A27, RawData!$A:$AM, 38, FALSE) | L27: =VLOOKUP($A27, RawData!$A:$AM, 39, FALSE) -> -0.28026178 | M27: =VLOOKUP($A27, RawData!$A:$AJ, 30, FALSE) -> 129.07837 | N27: =VLOOKUP($A27, RawData!$A:$AJ, 5, FALSE) -> -0.28285024 | O27: =VLOOKUP($A27, RawData!$A:$AJ, 6, FALSE) -> 0.064868145 | P27: =VLOOKUP($A27, RawData!$A:$AJ, 7, FALSE) | Q27: =VLOOKUP($A27, RawData!$A:$AJ, 8, FALSE) -> 0.7861 | R27: =VLOOKUP($A27, RawData!$A:$AJ, 11, FALSE) | S27: =VLOOKUP($A27, RawData!$A:$AJ, 13, FALSE) -> 0.829 | T27: =VLOOKUP($A27, RawData!$A:$AJ, 14, FALSE) -> 0.81434184 | U27: =VLOOKUP($A27, RawData!$A:$AJ, 23, FALSE) -> -0.1104 | V27: =VLOOKUP($A27, RawData!$A:$AJ, 24, FALSE) | W27: =VLOOKUP($A27, RawData!$A:$AJ, 25, FALSE) | X27: =VLOOKUP($A27, RawData!$A:$AJ, 26, FALSE) | Y27: =VLOOKUP($A27, RawData!$A:$AJ, 27, FALSE) | Z27: =VLOOKUP($A27, RawData!$A:$AJ, 28, FALSE) -> 3.0029135 | AA27: =VLOOKUP($A27, RawData!$A:$AJ, 31, FALSE) -> 153.36815 | AB27: =VLOOKUP($A27, RawData!$A:$AJ,32, FALSE) | AC27: =VLOOKUP($A27, RawData!$A:$AJ, 34, FALSE) -> 127.1422 | AD27: =VLOOKUP($A27, RawData!$A:$AJ, 35, FALSE) -> 9.56 | AE27: =VLOOKUP($A27, RawData!$A:$AJ, 36, FALSE) -> 12.42
A28: AGS | B28: PlayAGS | C28: Low | D28: [READ PITCH](https://community.microcapclub.com/forums/topic/3187-playags-inc-ags/#comment-72000) | E28: =IFERROR(__xludf.DUMMYFUNCTION("IFERROR(HYPERLINK(REGEXEXTRACT(D28,""\(([^)]*)\)""),REGEXEXTRACT(D28,""\[([^\]]+)\]"")),"""") "),"READ PITCH") -> READ PITCH | F28: =VLOOKUP($A28, RawData!$A:$AJ, 33, FALSE) -> 518.4 | G28: =VLOOKUP($A28, RawData!$A:$AJ, 2, FALSE) | H28: =VLOOKUP($A28, RawData!$A:$AJ, 3, FALSE) -> 0.066 | I28: =VLOOKUP($A28, RawData!$A:$AJ, 4, FALSE) -> 0.066023216 | J28: =VLOOKUP($A28, RawData!$A:$AM, 37, FALSE) -> 164.856 | K28: =VLOOKUP($A28, RawData!$A:$AM, 38, FALSE) | L28: =VLOOKUP($A28, RawData!$A:$AM, 39, FALSE) -> 0.10334572 | M28: =VLOOKUP($A28, RawData!$A:$AJ, 30, FALSE) -> 6.1567907 | N28: =VLOOKUP($A28, RawData!$A:$AJ, 5, FALSE) -> 1.3215129 | O28: =VLOOKUP($A28, RawData!$A:$AJ, 6, FALSE) -> 9.751862 | P28: =VLOOKUP($A28, RawData!$A:$AJ, 7, FALSE) | Q28: =VLOOKUP($A28, RawData!$A:$AJ, 8, FALSE) -> 0.8747 | R28: =VLOOKUP($A28, RawData!$A:$AJ, 11, FALSE) | S28: =VLOOKUP($A28, RawData!$A:$AJ, 13, FALSE) -> 24.917 | T28: =VLOOKUP($A28, RawData!$A:$AJ, 14, FALSE) -> 0.5554515 | U28: =VLOOKUP($A28, RawData!$A:$AJ, 23, FALSE) -> 0.0798 | V28: =VLOOKUP($A28, RawData!$A:$AJ, 24, FALSE) | W28: =VLOOKUP($A28, RawData!$A:$AJ, 25, FALSE) | X28: =VLOOKUP($A28, RawData!$A:$AJ, 26, FALSE) -> 9.451289 | Y28: =VLOOKUP($A28, RawData!$A:$AJ, 27, FALSE) -> 16.172123 | Z28: =VLOOKUP($A28, RawData!$A:$AJ, 28, FALSE) -> 1.316834 | AA28: =VLOOKUP($A28, RawData!$A:$AJ, 31, FALSE) -> 40.734596 | AB28: =VLOOKUP($A28, RawData!$A:$AJ,32, FALSE) | AC28: =VLOOKUP($A28, RawData!$A:$AJ, 34, FALSE) -> 1014.9839 | AD28: =VLOOKUP($A28, RawData!$A:$AJ, 35, FALSE) -> 12.49 | AE28: =VLOOKUP($A28, RawData!$A:$AJ, 36, FALSE) -> 41.51
A29: RDCM | B29: Radcom | C29: Medium | D29: [READ PITCH](https://community.microcapclub.com/forums/topic/854-radcom-ltd-rdcm/#comment-16705) | E29: =IFERROR(__xludf.DUMMYFUNCTION("IFERROR(HYPERLINK(REGEXEXTRACT(D29,""\(([^)]*)\)""),REGEXEXTRACT(D29,""\[([^\]]+)\]"")),"""") "),"READ PITCH") -> READ PITCH | F29: =VLOOKUP($A29, RawData!$A:$AJ, 33, FALSE) -> 208.06052 | G29: =VLOOKUP($A29, RawData!$A:$AJ, 2, FALSE) | H29: =VLOOKUP($A29, RawData!$A:$AJ, 3, FALSE) -> 0.1204 | I29: =VLOOKUP($A29, RawData!$A:$AJ, 4, FALSE) -> 0.13718125 | J29: =VLOOKUP($A29, RawData!$A:$AM, 37, FALSE) -> 9.94 | K29: =VLOOKUP($A29, RawData!$A:$AM, 38, FALSE) | L29: =VLOOKUP($A29, RawData!$A:$AM, 39, FALSE) -> -0.45185173 | M29: =VLOOKUP($A29, RawData!$A:$AJ, 30, FALSE) -> 20.674507 | N29: =VLOOKUP($A29, RawData!$A:$AJ, 5, FALSE) -> 0.58515286 | O29: =VLOOKUP($A29, RawData!$A:$AJ, 6, FALSE) -> 0.9627537 | P29: =VLOOKUP($A29, RawData!$A:$AJ, 7, FALSE) | Q29: =VLOOKUP($A29, RawData!$A:$AJ, 8, FALSE) -> 0.7332 | R29: =VLOOKUP($A29, RawData!$A:$AJ, 11, FALSE) | S29: =VLOOKUP($A29, RawData!$A:$AJ, 13, FALSE) -> -3.45 | T29: =VLOOKUP($A29, RawData!$A:$AJ, 14, FALSE) -> 0.8603491 | U29: =VLOOKUP($A29, RawData!$A:$AJ, 23, FALSE) -> 0.0713 | V29: =VLOOKUP($A29, RawData!$A:$AJ, 24, FALSE) | W29: =VLOOKUP($A29, RawData!$A:$AJ, 25, FALSE) | X29: =VLOOKUP($A29, RawData!$A:$AJ, 26, FALSE) -> 21.908806 | Y29: =VLOOKUP($A29, RawData!$A:$AJ, 27, FALSE) -> 12.085218 | Z29: =VLOOKUP($A29, RawData!$A:$AJ, 28, FALSE) -> 3.0672328 | AA29: =VLOOKUP($A29, RawData!$A:$AJ, 31, FALSE) -> -59.56655 | AB29: =VLOOKUP($A29, RawData!$A:$AJ,32, FALSE) | AC29: =VLOOKUP($A29, RawData!$A:$AJ, 34, FALSE) -> 205.5046 | AD29: =VLOOKUP($A29, RawData!$A:$AJ, 35, FALSE) -> 12.82 | AE29: =VLOOKUP($A29, RawData!$A:$AJ, 36, FALSE) -> 16.03
A30: BNED | B30: Barnes & Noble Education | C30: Low | D30: [READ PITCH](https://community.microcapclub.com/forums/topic/3637-barnes-noble-education-bned/) | E30: =IFERROR(__xludf.DUMMYFUNCTION("IFERROR(HYPERLINK(REGEXEXTRACT(D30,""\(([^)]*)\)""),REGEXEXTRACT(D30,""\[([^\]]+)\]"")),"""") "),"READ PITCH") -> READ PITCH | F30: =VLOOKUP($A30, RawData!$A:$AJ, 33, FALSE) -> 283.29736 | G30: =VLOOKUP($A30, RawData!$A:$AJ, 2, FALSE) | H30: =VLOOKUP($A30, RawData!$A:$AJ, 3, FALSE) -> 0.0138 | I30: =VLOOKUP($A30, RawData!$A:$AJ, 4, FALSE) -> -0.04034894 | J30: =VLOOKUP($A30, RawData!$A:$AM, 37, FALSE) -> 9.884 | K30: =VLOOKUP($A30, RawData!$A:$AM, 38, FALSE) | L30: =VLOOKUP($A30, RawData!$A:$AM, 39, FALSE) -> -0.099583894 | M30: =VLOOKUP($A30, RawData!$A:$AJ, 30, FALSE) -> 43.844345 | N30: =VLOOKUP($A30, RawData!$A:$AJ, 5, FALSE) -> -2.055683 | O30: =VLOOKUP($A30, RawData!$A:$AJ, 6, FALSE) -> -0.14804222 | P30: =VLOOKUP($A30, RawData!$A:$AJ, 7, FALSE) | Q30: =VLOOKUP($A30, RawData!$A:$AJ, 8, FALSE) -> 0.2239 | R30: =VLOOKUP($A30, RawData!$A:$AJ, 11, FALSE) | S30: =VLOOKUP($A30, RawData!$A:$AJ, 13, FALSE) -> -68.689 | T30: =VLOOKUP($A30, RawData!$A:$AJ, 14, FALSE) -> -3.8654473 | U30: =VLOOKUP($A30, RawData!$A:$AJ, 23, FALSE) -> -0.0691 | V30: =VLOOKUP($A30, RawData!$A:$AJ, 24, FALSE) | W30: =VLOOKUP($A30, RawData!$A:$AJ, 25, FALSE) | X30: =VLOOKUP($A30, RawData!$A:$AJ, 26, FALSE) | Y30: =VLOOKUP($A30, RawData!$A:$AJ, 27, FALSE) | Z30: =VLOOKUP($A30, RawData!$A:$AJ, 28, FALSE) -> 0.19220723 | AA30: =VLOOKUP($A30, RawData!$A:$AJ, 31, FALSE) -> -6.3089795 | AB30: =VLOOKUP($A30, RawData!$A:$AJ,32, FALSE) | AC30: =VLOOKUP($A30, RawData!$A:$AJ, 34, FALSE) -> 433.3575 | AD30: =VLOOKUP($A30, RawData!$A:$AJ, 35, FALSE) -> 8.85 | AE30: =VLOOKUP($A30, RawData!$A:$AJ, 36, FALSE) -> 34.05
A31: ASUR | B31: Asure Software | C31: Low | D31: [READ PITCH](https://community.microcapclub.com/forums/topic/320-asure-software-asur/#comment-3513) | E31: =IFERROR(__xludf.DUMMYFUNCTION("IFERROR(HYPERLINK(REGEXEXTRACT(D31,""\(([^)]*)\)""),REGEXEXTRACT(D31,""\[([^\]]+)\]"")),"""") "),"READ PITCH") -> READ PITCH | F31: =VLOOKUP($A31, RawData!$A:$AJ, 33, FALSE) -> 261.81335 | G31: =VLOOKUP($A31, RawData!$A:$AJ, 2, FALSE) | H31: =VLOOKUP($A31, RawData!$A:$AJ, 3, FALSE) -> 0.1454 | I31: =VLOOKUP($A31, RawData!$A:$AJ, 4, FALSE) -> 0.14631532 | J31: =VLOOKUP($A31, RawData!$A:$AM, 37, FALSE) -> 12.931 | K31: =VLOOKUP($A31, RawData!$A:$AM, 38, FALSE) | L31: =VLOOKUP($A31, RawData!$A:$AM, 39, FALSE) -> 0.31969485 | M31: =VLOOKUP($A31, RawData!$A:$AJ, 30, FALSE) -> 25.073792 | N31: =VLOOKUP($A31, RawData!$A:$AJ, 5, FALSE) -> -0.61552596 | O31: =VLOOKUP($A31, RawData!$A:$AJ, 6, FALSE) -> 0.40622172 | P31: =VLOOKUP($A31, RawData!$A:$AJ, 7, FALSE) | Q31: =VLOOKUP($A31, RawData!$A:$AJ, 8, FALSE) -> 0.671 | R31: =VLOOKUP($A31, RawData!$A:$AJ, 11, FALSE) | S31: =VLOOKUP($A31, RawData!$A:$AJ, 13, FALSE) -> -8.562 | T31: =VLOOKUP($A31, RawData!$A:$AJ, 14, FALSE) -> 0.37021664 | U31: =VLOOKUP($A31, RawData!$A:$AJ, 23, FALSE) -> -0.0362 | V31: =VLOOKUP($A31, RawData!$A:$AJ, 24, FALSE) | W31: =VLOOKUP($A31, RawData!$A:$AJ, 25, FALSE) | X31: =VLOOKUP($A31, RawData!$A:$AJ, 26, FALSE) | Y31: =VLOOKUP($A31, RawData!$A:$AJ, 27, FALSE) -> 14.319161 | Z31: =VLOOKUP($A31, RawData!$A:$AJ, 28, FALSE) -> 2.0858583 | AA31: =VLOOKUP($A31, RawData!$A:$AJ, 31, FALSE) -> -37.868397 | AB31: =VLOOKUP($A31, RawData!$A:$AJ,32, FALSE) | AC31: =VLOOKUP($A31, RawData!$A:$AJ, 34, FALSE) -> 324.2292 | AD31: =VLOOKUP($A31, RawData!$A:$AJ, 35, FALSE) -> 9.92 | AE31: =VLOOKUP($A31, RawData!$A:$AJ, 36, FALSE) -> 27.76
A32: RELL | B32: Richardson Electronics | C32: High | D32: [READ PITCH](https://community.microcapclub.com/forums/topic/2233-richardson-electronics-rell/#comment-51693) | E32: =IFERROR(__xludf.DUMMYFUNCTION("IFERROR(HYPERLINK(REGEXEXTRACT(D32,""\(([^)]*)\)""),REGEXEXTRACT(D32,""\[([^\]]+)\]"")),"""") "),"READ PITCH") -> READ PITCH | F32: =VLOOKUP($A32, RawData!$A:$AJ, 33, FALSE) -> 151.12935 | G32: =VLOOKUP($A32, RawData!$A:$AJ, 2, FALSE) | H32: =VLOOKUP($A32, RawData!$A:$AJ, 3, FALSE) -> 0.0617 | I32: =VLOOKUP($A32, RawData!$A:$AJ, 4, FALSE) -> 0.063783444 | J32: =VLOOKUP($A32, RawData!$A:$AM, 37, FALSE) -> 3.069 | K32: =VLOOKUP($A32, RawData!$A:$AM, 38, FALSE) | L32: =VLOOKUP($A32, RawData!$A:$AM, 39, FALSE) -> 0.22119126 | M32: =VLOOKUP($A32, RawData!$A:$AJ, 30, FALSE) -> 39.04324 | N32: =VLOOKUP($A32, RawData!$A:$AJ, 5, FALSE) -> 0.012146308 | O32: =VLOOKUP($A32, RawData!$A:$AJ, 6, FALSE) -> -1.3055556 | P32: =VLOOKUP($A32, RawData!$A:$AJ, 7, FALSE) | Q32: =VLOOKUP($A32, RawData!$A:$AJ, 8, FALSE) -> 0.3113 | R32: =VLOOKUP($A32, RawData!$A:$AJ, 11, FALSE) | S32: =VLOOKUP($A32, RawData!$A:$AJ, 13, FALSE) -> 8.597 | T32: =VLOOKUP($A32, RawData!$A:$AJ, 14, FALSE) -> 4.115366 | U32: =VLOOKUP($A32, RawData!$A:$AJ, 23, FALSE) -> 0.0009 | V32: =VLOOKUP($A32, RawData!$A:$AJ, 24, FALSE) | W32: =VLOOKUP($A32, RawData!$A:$AJ, 25, FALSE) | X32: =VLOOKUP($A32, RawData!$A:$AJ, 26, FALSE) -> 883.396 | Y32: =VLOOKUP($A32, RawData!$A:$AJ, 27, FALSE) -> 43.406147 | Z32: =VLOOKUP($A32, RawData!$A:$AJ, 28, FALSE) -> 0.7411076 | AA32: =VLOOKUP($A32, RawData!$A:$AJ, 31, FALSE) -> 13.93785 | AB32: =VLOOKUP($A32, RawData!$A:$AJ,32, FALSE) | AC32: =VLOOKUP($A32, RawData!$A:$AJ, 34, FALSE) -> 119.8237 | AD32: =VLOOKUP($A32, RawData!$A:$AJ, 35, FALSE) -> 10.73 | AE32: =VLOOKUP($A32, RawData!$A:$AJ, 36, FALSE) -> 14.49
A33: EXPI | B33: eXp World Holdings | C33: Low | D33: [READ PITCH](https://community.microcapclub.com/forums/topic/1842-exp-world-holdings-expi/#comment-42014) | E33: =IFERROR(__xludf.DUMMYFUNCTION("IFERROR(HYPERLINK(REGEXEXTRACT(D33,""\(([^)]*)\)""),REGEXEXTRACT(D33,""\[([^\]]+)\]"")),"""") "),"READ PITCH") -> READ PITCH | F33: =VLOOKUP($A33, RawData!$A:$AJ, 33, FALSE) -> 1531.1859 | G33: =VLOOKUP($A33, RawData!$A:$AJ, 2, FALSE) | H33: =VLOOKUP($A33, RawData!$A:$AJ, 3, FALSE) -> -0.1637 | I33: =VLOOKUP($A33, RawData!$A:$AJ, 4, FALSE) -> 0.20546083 | J33: =VLOOKUP($A33, RawData!$A:$AM, 37, FALSE) -> -4.642 | K33: =VLOOKUP($A33, RawData!$A:$AM, 38, FALSE) | L33: =VLOOKUP($A33, RawData!$A:$AM, 39, FALSE) -> 0.6583921 | M33: =VLOOKUP($A33, RawData!$A:$AJ, 30, FALSE) -> -288.8033 | N33: =VLOOKUP($A33, RawData!$A:$AJ, 5, FALSE) -> -0.1216822 | O33: =VLOOKUP($A33, RawData!$A:$AJ, 6, FALSE) -> -0.42658794 | P33: =VLOOKUP($A33, RawData!$A:$AJ, 7, FALSE) | Q33: =VLOOKUP($A33, RawData!$A:$AJ, 8, FALSE) -> 0.0692 | R33: =VLOOKUP($A33, RawData!$A:$AJ, 11, FALSE) | S33: =VLOOKUP($A33, RawData!$A:$AJ, 13, FALSE) -> 108.388 | T33: =VLOOKUP($A33, RawData!$A:$AJ, 14, FALSE) -> 0.533395 | U33: =VLOOKUP($A33, RawData!$A:$AJ, 23, FALSE) -> -0.0438 | V33: =VLOOKUP($A33, RawData!$A:$AJ, 24, FALSE) | W33: =VLOOKUP($A33, RawData!$A:$AJ, 25, FALSE) | X33: =VLOOKUP($A33, RawData!$A:$AJ, 26, FALSE) | Y33: =VLOOKUP($A33, RawData!$A:$AJ, 27, FALSE) | Z33: =VLOOKUP($A33, RawData!$A:$AJ, 28, FALSE) -> 0.3903017 | AA33: =VLOOKUP($A33, RawData!$A:$AJ, 31, FALSE) -> 12.368758 | AB33: =VLOOKUP($A33, RawData!$A:$AJ,32, FALSE) | AC33: =VLOOKUP($A33, RawData!$A:$AJ, 34, FALSE) -> 1340.625 | AD33: =VLOOKUP($A33, RawData!$A:$AJ, 35, FALSE) -> 9.15 | AE33: =VLOOKUP($A33, RawData!$A:$AJ, 36, FALSE) -> 158.84
A34: ACCS | B34: Access Newswire | C34: High | D34: [READ PITCH](https://community.microcapclub.com/forums/topic/1566-access-newswire-inc-accs/#comment-35278) | E34: =IFERROR(__xludf.DUMMYFUNCTION("IFERROR(HYPERLINK(REGEXEXTRACT(D34,""\(([^)]*)\)""),REGEXEXTRACT(D34,""\[([^\]]+)\]"")),"""") "),"READ PITCH") -> READ PITCH | F34: =VLOOKUP($A34, RawData!$A:$AJ, 33, FALSE) -> 37.52722 | G34: =VLOOKUP($A34, RawData!$A:$AJ, 2, FALSE) | H34: =VLOOKUP($A34, RawData!$A:$AJ, 3, FALSE) -> -0.3445 | I34: =VLOOKUP($A34, RawData!$A:$AJ, 4, FALSE) -> 0.029354563 | J34: =VLOOKUP($A34, RawData!$A:$AM, 37, FALSE) -> -14.847 | K34: =VLOOKUP($A34, RawData!$A:$AM, 38, FALSE) | L34: =VLOOKUP($A34, RawData!$A:$AM, 39, FALSE) -> No data | M34: =VLOOKUP($A34, RawData!$A:$AJ, 30, FALSE) -> -2.668694 | N34: =VLOOKUP($A34, RawData!$A:$AJ, 5, FALSE) -> -1.4855297 | O34: =VLOOKUP($A34, RawData!$A:$AJ, 6, FALSE) -> 8.827351 | P34: =VLOOKUP($A34, RawData!$A:$AJ, 7, FALSE) | Q34: =VLOOKUP($A34, RawData!$A:$AJ, 8, FALSE) -> 0.7708 | R34: =VLOOKUP($A34, RawData!$A:$AJ, 11, FALSE) | S34: =VLOOKUP($A34, RawData!$A:$AJ, 13, FALSE) -> 3.011 | T34: =VLOOKUP($A34, RawData!$A:$AJ, 14, FALSE) -> 2.7077339 | U34: =VLOOKUP($A34, RawData!$A:$AJ, 23, FALSE) -> -0.1121 | V34: =VLOOKUP($A34, RawData!$A:$AJ, 24, FALSE) | W34: =VLOOKUP($A34, RawData!$A:$AJ, 25, FALSE) | X34: =VLOOKUP($A34, RawData!$A:$AJ, 26, FALSE) | Y34: =VLOOKUP($A34, RawData!$A:$AJ, 27, FALSE) -> 18.600954 | Z34: =VLOOKUP($A34, RawData!$A:$AJ, 28, FALSE) -> 2.0892644 | AA34: =VLOOKUP($A34, RawData!$A:$AJ, 31, FALSE) -> 13.159117 | AB34: =VLOOKUP($A34, RawData!$A:$AJ,32, FALSE) | AC34: =VLOOKUP($A34, RawData!$A:$AJ, 34, FALSE) -> 39.6221 | AD34: =VLOOKUP($A34, RawData!$A:$AJ, 35, FALSE) -> 10.53 | AE34: =VLOOKUP($A34, RawData!$A:$AJ, 36, FALSE) -> 3.87
A35: MITK | B35: Mitek Systems | C35: Low | D35: [READ PITCH](https://community.microcapclub.com/forums/topic/3884-mitek-systems-mitk/#comment-83014) | E35: =IFERROR(__xludf.DUMMYFUNCTION("IFERROR(HYPERLINK(REGEXEXTRACT(D35,""\(([^)]*)\)""),REGEXEXTRACT(D35,""\[([^\]]+)\]"")),"""") "),"READ PITCH") -> READ PITCH | F35: =VLOOKUP($A35, RawData!$A:$AJ, 33, FALSE) -> 487.61346 | G35: =VLOOKUP($A35, RawData!$A:$AJ, 2, FALSE) | H35: =VLOOKUP($A35, RawData!$A:$AJ, 3, FALSE) -> 0.0442 | I35: =VLOOKUP($A35, RawData!$A:$AJ, 4, FALSE) -> 0.1214368 | J35: =VLOOKUP($A35, RawData!$A:$AM, 37, FALSE) -> 50.989 | K35: =VLOOKUP($A35, RawData!$A:$AM, 38, FALSE) | L35: =VLOOKUP($A35, RawData!$A:$AM, 39, FALSE) -> 0.16470626 | M35: =VLOOKUP($A35, RawData!$A:$AJ, 30, FALSE) -> 9.223078 | N35: =VLOOKUP($A35, RawData!$A:$AJ, 5, FALSE) -> 0.19268346 | O35: =VLOOKUP($A35, RawData!$A:$AJ, 6, FALSE) -> 1.6833435 | P35: =VLOOKUP($A35, RawData!$A:$AJ, 7, FALSE) | Q35: =VLOOKUP($A35, RawData!$A:$AJ, 8, FALSE) -> 0.8509 | R35: =VLOOKUP($A35, RawData!$A:$AJ, 11, FALSE) | S35: =VLOOKUP($A35, RawData!$A:$AJ, 13, FALSE) -> 54.185 | T35: =VLOOKUP($A35, RawData!$A:$AJ, 14, FALSE) -> 1.7912396 | U35: =VLOOKUP($A35, RawData!$A:$AJ, 23, FALSE) -> 0.0204 | V35: =VLOOKUP($A35, RawData!$A:$AJ, 24, FALSE) | W35: =VLOOKUP($A35, RawData!$A:$AJ, 25, FALSE) | X35: =VLOOKUP($A35, RawData!$A:$AJ, 26, FALSE) -> 53.196056 | Y35: =VLOOKUP($A35, RawData!$A:$AJ, 27, FALSE) -> 9.1855755 | Z35: =VLOOKUP($A35, RawData!$A:$AJ, 28, FALSE) -> 2.603984 | AA35: =VLOOKUP($A35, RawData!$A:$AJ, 31, FALSE) -> 8.679071 | AB35: =VLOOKUP($A35, RawData!$A:$AJ,32, FALSE) | AC35: =VLOOKUP($A35, RawData!$A:$AJ, 34, FALSE) -> 470.2755 | AD35: =VLOOKUP($A35, RawData!$A:$AJ, 35, FALSE) -> 10.25 | AE35: =VLOOKUP($A35, RawData!$A:$AJ, 36, FALSE) -> 45.65
A36: CTLP | B36: Cantaloupe | C36: Low | D36: [READ PITCH](https://community.microcapclub.com/forums/topic/1667-cantaloupe-ctlp/#comment-37955) | E36: =IFERROR(__xludf.DUMMYFUNCTION("IFERROR(HYPERLINK(REGEXEXTRACT(D36,""\(([^)]*)\)""),REGEXEXTRACT(D36,""\[([^\]]+)\]"")),"""") "),"READ PITCH") -> READ PITCH | F36: =VLOOKUP($A36, RawData!$A:$AJ, 33, FALSE) -> 788.92883 | G36: =VLOOKUP($A36, RawData!$A:$AJ, 2, FALSE) | H36: =VLOOKUP($A36, RawData!$A:$AJ, 3, FALSE) -> 0.1294 | I36: =VLOOKUP($A36, RawData!$A:$AJ, 4, FALSE) -> 0.1481149 | J36: =VLOOKUP($A36, RawData!$A:$AM, 37, FALSE) -> -4.98 | K36: =VLOOKUP($A36, RawData!$A:$AM, 38, FALSE) | L36: =VLOOKUP($A36, RawData!$A:$AM, 39, FALSE) -> 0.15815394 | M36: =VLOOKUP($A36, RawData!$A:$AJ, 30, FALSE) -> -157.21867 | N36: =VLOOKUP($A36, RawData!$A:$AJ, 5, FALSE) -> 0.8146811 | O36: =VLOOKUP($A36, RawData!$A:$AJ, 6, FALSE) -> 3.4285293 | P36: =VLOOKUP($A36, RawData!$A:$AJ, 7, FALSE) | Q36: =VLOOKUP($A36, RawData!$A:$AJ, 8, FALSE) -> 0.4111 | R36: =VLOOKUP($A36, RawData!$A:$AJ, 11, FALSE) | S36: =VLOOKUP($A36, RawData!$A:$AJ, 13, FALSE) -> 22.685 | T36: =VLOOKUP($A36, RawData!$A:$AJ, 14, FALSE) -> -3.3463638 | U36: =VLOOKUP($A36, RawData!$A:$AJ, 23, FALSE) -> 0.1662 | V36: =VLOOKUP($A36, RawData!$A:$AJ, 24, FALSE) | W36: =VLOOKUP($A36, RawData!$A:$AJ, 25, FALSE) | X36: =VLOOKUP($A36, RawData!$A:$AJ, 26, FALSE) -> 13.318094 | Y36: =VLOOKUP($A36, RawData!$A:$AJ, 27, FALSE) -> 23.725182 | Z36: =VLOOKUP($A36, RawData!$A:$AJ, 28, FALSE) -> 2.558332 | AA36: =VLOOKUP($A36, RawData!$A:$AJ, 31, FALSE) -> 34.51395 | AB36: =VLOOKUP($A36, RawData!$A:$AJ,32, FALSE) | AC36: =VLOOKUP($A36, RawData!$A:$AJ, 34, FALSE) -> 782.949 | AD36: =VLOOKUP($A36, RawData!$A:$AJ, 35, FALSE) -> 10.85 | AE36: =VLOOKUP($A36, RawData!$A:$AJ, 36, FALSE) -> 73.7
A37: AEHR | B37: Aehr Test Systems | C37: Low | D37: [READ PITCH](https://community.microcapclub.com/forums/topic/3485-aehr-test-systems-aehr/#comment-77391) | E37: =IFERROR(__xludf.DUMMYFUNCTION("IFERROR(HYPERLINK(REGEXEXTRACT(D37,""\(([^)]*)\)""),REGEXEXTRACT(D37,""\[([^\]]+)\]"")),"""") "),"READ PITCH") -> READ PITCH | F37: =VLOOKUP($A37, RawData!$A:$AJ, 33, FALSE) -> 773.5699 | G37: =VLOOKUP($A37, RawData!$A:$AJ, 2, FALSE) | H37: =VLOOKUP($A37, RawData!$A:$AJ, 3, FALSE) -> -0.0323 | I37: =VLOOKUP($A37, RawData!$A:$AJ, 4, FALSE) -> 0.24810356 | J37: =VLOOKUP($A37, RawData!$A:$AM, 37, FALSE) -> -6.132 | K37: =VLOOKUP($A37, RawData!$A:$AM, 38, FALSE) | L37: =VLOOKUP($A37, RawData!$A:$AM, 39, FALSE) -> 0.24019842 | M37: =VLOOKUP($A37, RawData!$A:$AJ, 30, FALSE) -> -123.39395 | N37: =VLOOKUP($A37, RawData!$A:$AJ, 5, FALSE) -> -0.22172609 | O37: =VLOOKUP($A37, RawData!$A:$AJ, 6, FALSE) -> -1.2283303 | P37: =VLOOKUP($A37, RawData!$A:$AJ, 7, FALSE) | Q37: =VLOOKUP($A37, RawData!$A:$AJ, 8, FALSE) -> 0.3621 | R37: =VLOOKUP($A37, RawData!$A:$AJ, 11, FALSE) | S37: =VLOOKUP($A37, RawData!$A:$AJ, 13, FALSE) -> -16.248 | T37: =VLOOKUP($A37, RawData!$A:$AJ, 14, FALSE) -> 37.786045 | U37: =VLOOKUP($A37, RawData!$A:$AJ, 23, FALSE) -> -0.0459 | V37: =VLOOKUP($A37, RawData!$A:$AJ, 24, FALSE) | W37: =VLOOKUP($A37, RawData!$A:$AJ, 25, FALSE) | X37: =VLOOKUP($A37, RawData!$A:$AJ, 26, FALSE) | Y37: =VLOOKUP($A37, RawData!$A:$AJ, 27, FALSE) -> 168.09062 | Z37: =VLOOKUP($A37, RawData!$A:$AJ, 28, FALSE) -> 13.716775 | AA37: =VLOOKUP($A37, RawData!$A:$AJ, 31, FALSE) -> -46.568913 | AB37: =VLOOKUP($A37, RawData!$A:$AJ,32, FALSE) | AC37: =VLOOKUP($A37, RawData!$A:$AJ, 34, FALSE) -> 756.6517 | AD37: =VLOOKUP($A37, RawData!$A:$AJ, 35, FALSE) -> 25.97 | AE37: =VLOOKUP($A37, RawData!$A:$AJ, 36, FALSE) -> 30.01
A38: MHH | B38: Mastech Digital | C38: Medium | D38: [READ PITCH](https://community.microcapclub.com/forums/topic/3148-mastech-digital-mhh/#comment-71440) | E38: =IFERROR(__xludf.DUMMYFUNCTION("IFERROR(HYPERLINK(REGEXEXTRACT(D38,""\(([^)]*)\)""),REGEXEXTRACT(D38,""\[([^\]]+)\]"")),"""") "),"READ PITCH") -> READ PITCH | F38: =VLOOKUP($A38, RawData!$A:$AJ, 33, FALSE) -> 84.80566 | G38: =VLOOKUP($A38, RawData!$A:$AJ, 2, FALSE) | H38: =VLOOKUP($A38, RawData!$A:$AJ, 3, FALSE) -> 0.0516 | I38: =VLOOKUP($A38, RawData!$A:$AJ, 4, FALSE) -> 0.002102193 | J38: =VLOOKUP($A38, RawData!$A:$AM, 37, FALSE) -> 4.045 | K38: =VLOOKUP($A38, RawData!$A:$AM, 38, FALSE) | L38: =VLOOKUP($A38, RawData!$A:$AM, 39, FALSE) -> -0.24195422 | M38: =VLOOKUP($A38, RawData!$A:$AJ, 30, FALSE) -> 13.746601 | N38: =VLOOKUP($A38, RawData!$A:$AJ, 5, FALSE) -> 0.07418803 | O38: =VLOOKUP($A38, RawData!$A:$AJ, 6, FALSE) -> -1.2172172 | P38: =VLOOKUP($A38, RawData!$A:$AJ, 7, FALSE) | Q38: =VLOOKUP($A38, RawData!$A:$AJ, 8, FALSE) -> 0.281 | R38: =VLOOKUP($A38, RawData!$A:$AJ, 11, FALSE) | S38: =VLOOKUP($A38, RawData!$A:$AJ, 13, FALSE) -> 7.28 | T38: =VLOOKUP($A38, RawData!$A:$AJ, 14, FALSE) -> 4.1576242 | U38: =VLOOKUP($A38, RawData!$A:$AJ, 23, FALSE) -> 0.0078 | V38: =VLOOKUP($A38, RawData!$A:$AJ, 24, FALSE) | W38: =VLOOKUP($A38, RawData!$A:$AJ, 25, FALSE) | X38: =VLOOKUP($A38, RawData!$A:$AJ, 26, FALSE) -> 96.241936 | Y38: =VLOOKUP($A38, RawData!$A:$AJ, 27, FALSE) -> 9.887142 | Z38: =VLOOKUP($A38, RawData!$A:$AJ, 28, FALSE) -> 0.41769 | AA38: =VLOOKUP($A38, RawData!$A:$AJ, 31, FALSE) -> 7.6380496 | AB38: =VLOOKUP($A38, RawData!$A:$AJ,32, FALSE) | AC38: =VLOOKUP($A38, RawData!$A:$AJ, 34, FALSE) -> 55.605 | AD38: =VLOOKUP($A38, RawData!$A:$AJ, 35, FALSE) -> 7.14 | AE38: =VLOOKUP($A38, RawData!$A:$AJ, 36, FALSE) -> 11.7
A39: AATC | B39: Autoscope Technologies | C39: Low | D39: [READ PITCH](https://community.microcapclub.com/forums/topic/4124-autoscope-technologies-corporation-aatc/#comment-85805) | E39: =IFERROR(__xludf.DUMMYFUNCTION("IFERROR(HYPERLINK(REGEXEXTRACT(D39,""\(([^)]*)\)""),REGEXEXTRACT(D39,""\[([^\]]+)\]"")),"""") "),"READ PITCH") -> READ PITCH | F39: =VLOOKUP($A39, RawData!$A:$AJ, 33, FALSE) -> 31.364702 | G39: =VLOOKUP($A39, RawData!$A:$AJ, 2, FALSE) | H39: =VLOOKUP($A39, RawData!$A:$AJ, 3, FALSE) -> -0.116 | I39: =VLOOKUP($A39, RawData!$A:$AJ, 4, FALSE) -> -0.041387446 | J39: =VLOOKUP($A39, RawData!$A:$AM, 37, FALSE) -> 5.307 | K39: =VLOOKUP($A39, RawData!$A:$AM, 38, FALSE) | L39: =VLOOKUP($A39, RawData!$A:$AM, 39, FALSE) -> 0.145564 | M39: =VLOOKUP($A39, RawData!$A:$AJ, 30, FALSE) -> 6.010175 | N39: =VLOOKUP($A39, RawData!$A:$AJ, 5, FALSE) -> 0.5878182 | O39: =VLOOKUP($A39, RawData!$A:$AJ, 6, FALSE) -> -0.54174346 | P39: =VLOOKUP($A39, RawData!$A:$AJ, 7, FALSE) | Q39: =VLOOKUP($A39, RawData!$A:$AJ, 8, FALSE) -> 0.9646 | R39: =VLOOKUP($A39, RawData!$A:$AJ, 11, FALSE) | S39: =VLOOKUP($A39, RawData!$A:$AJ, 13, FALSE) -> 6.281 | T39: =VLOOKUP($A39, RawData!$A:$AJ, 14, FALSE) -> 1.5167834 | U39: =VLOOKUP($A39, RawData!$A:$AJ, 23, FALSE) -> 0.2014 | V39: =VLOOKUP($A39, RawData!$A:$AJ, 24, FALSE) | W39: =VLOOKUP($A39, RawData!$A:$AJ, 25, FALSE) | X39: =VLOOKUP($A39, RawData!$A:$AJ, 26, FALSE) -> 10.122177 | Y39: =VLOOKUP($A39, RawData!$A:$AJ, 27, FALSE) | Z39: =VLOOKUP($A39, RawData!$A:$AJ, 28, FALSE) -> 2.782265 | AA39: =VLOOKUP($A39, RawData!$A:$AJ, 31, FALSE) -> 5.078172 | AB39: =VLOOKUP($A39, RawData!$A:$AJ,32, FALSE) | AC39: =VLOOKUP($A39, RawData!$A:$AJ, 34, FALSE) -> 31.896 | AD39: =VLOOKUP($A39, RawData!$A:$AJ, 35, FALSE) -> 6 | AE39: =VLOOKUP($A39, RawData!$A:$AJ, 36, FALSE) -> 5.5
A40: TSSI | B40: TSS Inc | C40: Medium | D40: [READ PITCH](https://community.microcapclub.com/forums/topic/2136-tss-inc-tssi/#comment-49169) | E40: =IFERROR(__xludf.DUMMYFUNCTION("IFERROR(HYPERLINK(REGEXEXTRACT(D40,""\(([^)]*)\)""),REGEXEXTRACT(D40,""\[([^\]]+)\]"")),"""") "),"READ PITCH") -> READ PITCH | F40: =VLOOKUP($A40, RawData!$A:$AJ, 33, FALSE) -> 249.22112 | G40: =VLOOKUP($A40, RawData!$A:$AJ, 2, FALSE) | H40: =VLOOKUP($A40, RawData!$A:$AJ, 3, FALSE) -> 0.9166 | I40: =VLOOKUP($A40, RawData!$A:$AJ, 4, FALSE) -> 0.3217636 | J40: =VLOOKUP($A40, RawData!$A:$AM, 37, FALSE) -> 10.601 | K40: =VLOOKUP($A40, RawData!$A:$AM, 38, FALSE) | L40: =VLOOKUP($A40, RawData!$A:$AM, 39, FALSE) -> 0.7171874 | M40: =VLOOKUP($A40, RawData!$A:$AJ, 30, FALSE) -> 24.350863 | N40: =VLOOKUP($A40, RawData!$A:$AJ, 5, FALSE) -> 0.16908145 | O40: =VLOOKUP($A40, RawData!$A:$AJ, 6, FALSE) -> 0.10838446 | P40: =VLOOKUP($A40, RawData!$A:$AJ, 7, FALSE) | Q40: =VLOOKUP($A40, RawData!$A:$AJ, 8, FALSE) -> 0.123 | R40: =VLOOKUP($A40, RawData!$A:$AJ, 11, FALSE) | S40: =VLOOKUP($A40, RawData!$A:$AJ, 13, FALSE) -> -42.079 | T40: =VLOOKUP($A40, RawData!$A:$AJ, 14, FALSE) -> -2.2913854 | U40: =VLOOKUP($A40, RawData!$A:$AJ, 23, FALSE) -> 0.0379 | V40: =VLOOKUP($A40, RawData!$A:$AJ, 24, FALSE) | W40: =VLOOKUP($A40, RawData!$A:$AJ, 25, FALSE) | X40: =VLOOKUP($A40, RawData!$A:$AJ, 26, FALSE) -> 62.514248 | Y40: =VLOOKUP($A40, RawData!$A:$AJ, 27, FALSE) -> 86.35621 | Z40: =VLOOKUP($A40, RawData!$A:$AJ, 28, FALSE) -> 1.2985369 | AA40: =VLOOKUP($A40, RawData!$A:$AJ, 31, FALSE) -> -6.1347346 | AB40: =VLOOKUP($A40, RawData!$A:$AJ,32, FALSE) | AC40: =VLOOKUP($A40, RawData!$A:$AJ, 34, FALSE) -> 258.1435 | AD40: =VLOOKUP($A40, RawData!$A:$AJ, 35, FALSE) -> 10.57 | AE40: =VLOOKUP($A40, RawData!$A:$AJ, 36, FALSE) -> 28.85
A41: CODA | B41: Coda Octopus Group | C41: Medium (old) | D41: [READ PITCH](https://community.microcapclub.com/forums/topic/688-coda-octopus-group-coda/#comment-12065) | E41: =IFERROR(__xludf.DUMMYFUNCTION("IFERROR(HYPERLINK(REGEXEXTRACT(D41,""\(([^)]*)\)""),REGEXEXTRACT(D41,""\[([^\]]+)\]"")),"""") "),"READ PITCH") -> READ PITCH | F41: =VLOOKUP($A41, RawData!$A:$AJ, 33, FALSE) -> 115.30089 | G41: =VLOOKUP($A41, RawData!$A:$AJ, 2, FALSE) | H41: =VLOOKUP($A41, RawData!$A:$AJ, 3, FALSE) -> 0.2934 | I41: =VLOOKUP($A41, RawData!$A:$AJ, 4, FALSE) -> 0.02787626 | J41: =VLOOKUP($A41, RawData!$A:$AM, 37, FALSE) -> 5.21794 | K41: =VLOOKUP($A41, RawData!$A:$AM, 38, FALSE) | L41: =VLOOKUP($A41, RawData!$A:$AM, 39, FALSE) -> 0.062692635 | M41: =VLOOKUP($A41, RawData!$A:$AJ, 30, FALSE) -> 20.086443 | N41: =VLOOKUP($A41, RawData!$A:$AJ, 5, FALSE) -> 0.30497244 | O41: =VLOOKUP($A41, RawData!$A:$AJ, 6, FALSE) -> 0.14409667 | P41: =VLOOKUP($A41, RawData!$A:$AJ, 7, FALSE) | Q41: =VLOOKUP($A41, RawData!$A:$AJ, 8, FALSE) -> 0.6592 | R41: =VLOOKUP($A41, RawData!$A:$AJ, 11, FALSE) | S41: =VLOOKUP($A41, RawData!$A:$AJ, 13, FALSE) -> 5.42756 | T41: =VLOOKUP($A41, RawData!$A:$AJ, 14, FALSE) -> -7.840009 | U41: =VLOOKUP($A41, RawData!$A:$AJ, 23, FALSE) -> 0.0579 | V41: =VLOOKUP($A41, RawData!$A:$AJ, 24, FALSE) | W41: =VLOOKUP($A41, RawData!$A:$AJ, 25, FALSE) | X41: =VLOOKUP($A41, RawData!$A:$AJ, 26, FALSE) -> 38.183777 | Y41: =VLOOKUP($A41, RawData!$A:$AJ, 27, FALSE) -> 30.722351 | Z41: =VLOOKUP($A41, RawData!$A:$AJ, 28, FALSE) -> 5.380752 | AA41: =VLOOKUP($A41, RawData!$A:$AJ, 31, FALSE) -> 19.310675 | AB41: =VLOOKUP($A41, RawData!$A:$AJ,32, FALSE) | AC41: =VLOOKUP($A41, RawData!$A:$AJ, 34, FALSE) -> 104.80985 | AD41: =VLOOKUP($A41, RawData!$A:$AJ, 35, FALSE) -> 11.645 | AE41: =VLOOKUP($A41, RawData!$A:$AJ, 36, FALSE) -> 11.25
A42: AXIL | B42: AXIL Brands, Inc. | C42: Low | D42: [READ PITCH](https://community.microcapclub.com/forums/topic/5042-axil-brands-inc-axil/#comment-98285) | E42: =IFERROR(__xludf.DUMMYFUNCTION("IFERROR(HYPERLINK(REGEXEXTRACT(D42,""\(([^)]*)\)""),REGEXEXTRACT(D42,""\[([^\]]+)\]"")),"""") "),"READ PITCH") -> READ PITCH | F42: =VLOOKUP($A42, RawData!$A:$AJ, 33, FALSE) -> 49.39891 | G42: =VLOOKUP($A42, RawData!$A:$AJ, 2, FALSE) | H42: =VLOOKUP($A42, RawData!$A:$AJ, 3, FALSE) -> 0.0007 | I42: =VLOOKUP($A42, RawData!$A:$AJ, 4, FALSE) -> 0.881705 | J42: =VLOOKUP($A42, RawData!$A:$AM, 37, FALSE) -> 1.92209 | K42: =VLOOKUP($A42, RawData!$A:$AM, 38, FALSE) | L42: =VLOOKUP($A42, RawData!$A:$AM, 39, FALSE) -> No data | M42: =VLOOKUP($A42, RawData!$A:$AJ, 30, FALSE) -> 26.082327 | N42: =VLOOKUP($A42, RawData!$A:$AJ, 5, FALSE) -> 0.1921716 | O42: =VLOOKUP($A42, RawData!$A:$AJ, 6, FALSE) -> -0.2529343 | P42: =VLOOKUP($A42, RawData!$A:$AJ, 7, FALSE) | Q42: =VLOOKUP($A42, RawData!$A:$AJ, 8, FALSE) -> 0.7014 | R42: =VLOOKUP($A42, RawData!$A:$AJ, 11, FALSE) | S42: =VLOOKUP($A42, RawData!$A:$AJ, 13, FALSE) -> -0.15481 | T42: =VLOOKUP($A42, RawData!$A:$AJ, 14, FALSE) -> -0.44051448 | U42: =VLOOKUP($A42, RawData!$A:$AJ, 23, FALSE) -> 0.0947 | V42: =VLOOKUP($A42, RawData!$A:$AJ, 24, FALSE) | W42: =VLOOKUP($A42, RawData!$A:$AJ, 25, FALSE) | X42: =VLOOKUP($A42, RawData!$A:$AJ, 26, FALSE) -> 41.62946 | Y42: =VLOOKUP($A42, RawData!$A:$AJ, 27, FALSE) -> No data | Z42: =VLOOKUP($A42, RawData!$A:$AJ, 28, FALSE) -> 1.9836773 | AA42: =VLOOKUP($A42, RawData!$A:$AJ, 31, FALSE) -> -323.83295 | AB42: =VLOOKUP($A42, RawData!$A:$AJ,32, FALSE) | AC42: =VLOOKUP($A42, RawData!$A:$AJ, 34, FALSE) -> 50.13258 | AD42: =VLOOKUP($A42, RawData!$A:$AJ, 35, FALSE) -> 8 | AE42: =VLOOKUP($A42, RawData!$A:$AJ, 36, FALSE) -> 6.76
A43: DUOT | B43: Duos Technologies | C43: Low Medium | D43: [READ PITCH](https://community.microcapclub.com/forums/topic/2435-duos-technologies-duot/#comment-56644) | E43: =IFERROR(__xludf.DUMMYFUNCTION("IFERROR(HYPERLINK(REGEXEXTRACT(D43,""\(([^)]*)\)""),REGEXEXTRACT(D43,""\[([^\]]+)\]"")),"""") "),"READ PITCH") -> READ PITCH | F43: =VLOOKUP($A43, RawData!$A:$AJ, 33, FALSE) -> 207.21518 | G43: =VLOOKUP($A43, RawData!$A:$AJ, 2, FALSE) | H43: =VLOOKUP($A43, RawData!$A:$AJ, 3, FALSE) -> 1.59 | I43: =VLOOKUP($A43, RawData!$A:$AJ, 4, FALSE) -> 0.1372892 | J43: =VLOOKUP($A43, RawData!$A:$AM, 37, FALSE) -> -6.84371 | K43: =VLOOKUP($A43, RawData!$A:$AM, 38, FALSE) | L43: =VLOOKUP($A43, RawData!$A:$AM, 39, FALSE) -> 0.05008719 | M43: =VLOOKUP($A43, RawData!$A:$AJ, 30, FALSE) -> -25.887815 | N43: =VLOOKUP($A43, RawData!$A:$AJ, 5, FALSE) -> -0.49188295 | O43: =VLOOKUP($A43, RawData!$A:$AJ, 6, FALSE) -> -0.045136247 | P43: =VLOOKUP($A43, RawData!$A:$AJ, 7, FALSE) | Q43: =VLOOKUP($A43, RawData!$A:$AJ, 8, FALSE) -> 0.2638 | R43: =VLOOKUP($A43, RawData!$A:$AJ, 11, FALSE) | S43: =VLOOKUP($A43, RawData!$A:$AJ, 13, FALSE) -> -16.47932 | T43: =VLOOKUP($A43, RawData!$A:$AJ, 14, FALSE) -> 1.4899052 | U43: =VLOOKUP($A43, RawData!$A:$AJ, 23, FALSE) -> -0.2364 | V43: =VLOOKUP($A43, RawData!$A:$AJ, 24, FALSE) | W43: =VLOOKUP($A43, RawData!$A:$AJ, 25, FALSE) | X43: =VLOOKUP($A43, RawData!$A:$AJ, 26, FALSE) | Y43: =VLOOKUP($A43, RawData!$A:$AJ, 27, FALSE) | Z43: =VLOOKUP($A43, RawData!$A:$AJ, 28, FALSE) -> 11.054488 | AA43: =VLOOKUP($A43, RawData!$A:$AJ, 31, FALSE) -> -10.750984 | AB43: =VLOOKUP($A43, RawData!$A:$AJ,32, FALSE) | AC43: =VLOOKUP($A43, RawData!$A:$AJ, 34, FALSE) -> 177.1687 | AD43: =VLOOKUP($A43, RawData!$A:$AJ, 35, FALSE) -> 10.3 | AE43: =VLOOKUP($A43, RawData!$A:$AJ, 36, FALSE) -> 20.42
A44: ALAR | B44: Alarum | C44: Medium | D44: [READ PITCH](https://community.microcapclub.com/forums/topic/4193-alarum-alar/#comment-86583) | E44: =IFERROR(__xludf.DUMMYFUNCTION("IFERROR(HYPERLINK(REGEXEXTRACT(D44,""\(([^)]*)\)""),REGEXEXTRACT(D44,""\[([^\]]+)\]"")),"""") "),"READ PITCH") -> READ PITCH | F44: =VLOOKUP($A44, RawData!$A:$AJ, 33, FALSE) -> 212.56042 | G44: =VLOOKUP($A44, RawData!$A:$AJ, 2, FALSE) | H44: =VLOOKUP($A44, RawData!$A:$AJ, 3, FALSE) -> 0.4297 | I44: =VLOOKUP($A44, RawData!$A:$AJ, 4, FALSE) -> No data | J44: =VLOOKUP($A44, RawData!$A:$AM, 37, FALSE) -> No data | K44: =VLOOKUP($A44, RawData!$A:$AM, 38, FALSE) | L44: =VLOOKUP($A44, RawData!$A:$AM, 39, FALSE) -> No data | M44: =VLOOKUP($A44, RawData!$A:$AJ, 30, FALSE) | N44: =VLOOKUP($A44, RawData!$A:$AJ, 5, FALSE) -> No data | O44: =VLOOKUP($A44, RawData!$A:$AJ, 6, FALSE) -> No data | P44: =VLOOKUP($A44, RawData!$A:$AJ, 7, FALSE) | Q44: =VLOOKUP($A44, RawData!$A:$AJ, 8, FALSE) -> 0.7092 | R44: =VLOOKUP($A44, RawData!$A:$AJ, 11, FALSE) | S44: =VLOOKUP($A44, RawData!$A:$AJ, 13, FALSE) -> No data | T44: =VLOOKUP($A44, RawData!$A:$AJ, 14, FALSE) -> No data | U44: =VLOOKUP($A44, RawData!$A:$AJ, 23, FALSE) -> 0.0322 | V44: =VLOOKUP($A44, RawData!$A:$AJ, 24, FALSE) | W44: =VLOOKUP($A44, RawData!$A:$AJ, 25, FALSE) | X44: =VLOOKUP($A44, RawData!$A:$AJ, 26, FALSE) | Y44: =VLOOKUP($A44, RawData!$A:$AJ, 27, FALSE) | Z44: =VLOOKUP($A44, RawData!$A:$AJ, 28, FALSE) | AA44: =VLOOKUP($A44, RawData!$A:$AJ, 31, FALSE) | AB44: =VLOOKUP($A44, RawData!$A:$AJ,32, FALSE) | AC44: =VLOOKUP($A44, RawData!$A:$AJ, 34, FALSE) -> 23.69217 | AD44: =VLOOKUP($A44, RawData!$A:$AJ, 35, FALSE) -> 9.63 | AE44: =VLOOKUP($A44, RawData!$A:$AJ, 36, FALSE) -> No data
A45: SEAC | B45: Seachange | C45: Low | D45: [READ PITCH](https://community.microcapclub.com/forums/topic/2450-seachange-seac/#comment-56881) | E45: =IFERROR(__xludf.DUMMYFUNCTION("IFERROR(HYPERLINK(REGEXEXTRACT(D45,""\(([^)]*)\)""),REGEXEXTRACT(D45,""\[([^\]]+)\]"")),"""") "),"READ PITCH") -> READ PITCH | F45: =VLOOKUP($A45, RawData!$A:$AJ, 33, FALSE) -> 9.070868 | G45: =VLOOKUP($A45, RawData!$A:$AJ, 2, FALSE) | H45: =VLOOKUP($A45, RawData!$A:$AJ, 3, FALSE) -> 0.1305 | I45: =VLOOKUP($A45, RawData!$A:$AJ, 4, FALSE) -> -0.16045333 | J45: =VLOOKUP($A45, RawData!$A:$AM, 37, FALSE) -> -9.439 | K45: =VLOOKUP($A45, RawData!$A:$AM, 38, FALSE) | L45: =VLOOKUP($A45, RawData!$A:$AM, 39, FALSE) -> 0.2931744 | M45: =VLOOKUP($A45, RawData!$A:$AJ, 30, FALSE) -> 0.5589575 | N45: =VLOOKUP($A45, RawData!$A:$AJ, 5, FALSE) -> -3.5356588 | O45: =VLOOKUP($A45, RawData!$A:$AJ, 6, FALSE) -> 0.4347279 | P45: =VLOOKUP($A45, RawData!$A:$AJ, 7, FALSE) | Q45: =VLOOKUP($A45, RawData!$A:$AJ, 8, FALSE) -> 0.655 | R45: =VLOOKUP($A45, RawData!$A:$AJ, 11, FALSE) | S45: =VLOOKUP($A45, RawData!$A:$AJ, 13, FALSE) -> -0.753 | T45: =VLOOKUP($A45, RawData!$A:$AJ, 14, FALSE) -> 0.17414431 | U45: =VLOOKUP($A45, RawData!$A:$AJ, 23, FALSE) -> -0.2198 | V45: =VLOOKUP($A45, RawData!$A:$AJ, 24, FALSE) | W45: =VLOOKUP($A45, RawData!$A:$AJ, 25, FALSE) | X45: =VLOOKUP($A45, RawData!$A:$AJ, 26, FALSE) | Y45: =VLOOKUP($A45, RawData!$A:$AJ, 27, FALSE) | Z45: =VLOOKUP($A45, RawData!$A:$AJ, 28, FALSE) -> 0.25987425 | AA45: =VLOOKUP($A45, RawData!$A:$AJ, 31, FALSE) -> 7.00664 | AB45: =VLOOKUP($A45, RawData!$A:$AJ,32, FALSE) | AC45: =VLOOKUP($A45, RawData!$A:$AJ, 34, FALSE) -> -5.276 | AD45: =VLOOKUP($A45, RawData!$A:$AJ, 35, FALSE) -> 3.51 | AE45: =VLOOKUP($A45, RawData!$A:$AJ, 36, FALSE) -> 2.58
A46: INTT | B46: inTEST Corporation | C46: Low | D46: [READ PITCH](https://community.microcapclub.com/forums/topic/4127-intest-corporation-intt/#comment-85829) | E46: =IFERROR(__xludf.DUMMYFUNCTION("IFERROR(HYPERLINK(REGEXEXTRACT(D46,""\(([^)]*)\)""),REGEXEXTRACT(D46,""\[([^\]]+)\]"")),"""") "),"READ PITCH") -> READ PITCH | F46: =VLOOKUP($A46, RawData!$A:$AJ, 33, FALSE) -> 100.7413 | G46: =VLOOKUP($A46, RawData!$A:$AJ, 2, FALSE) | H46: =VLOOKUP($A46, RawData!$A:$AJ, 3, FALSE) -> -0.0081 | I46: =VLOOKUP($A46, RawData!$A:$AJ, 4, FALSE) -> 0.18187235 | J46: =VLOOKUP($A46, RawData!$A:$AM, 37, FALSE) -> 5.615 | K46: =VLOOKUP($A46, RawData!$A:$AM, 38, FALSE) | L46: =VLOOKUP($A46, RawData!$A:$AM, 39, FALSE) -> 0.1048253 | M46: =VLOOKUP($A46, RawData!$A:$AJ, 30, FALSE) -> 16.172716 | N46: =VLOOKUP($A46, RawData!$A:$AJ, 5, FALSE) -> -0.06674679 | O46: =VLOOKUP($A46, RawData!$A:$AJ, 6, FALSE) -> -1.180147 | P46: =VLOOKUP($A46, RawData!$A:$AJ, 7, FALSE) | Q46: =VLOOKUP($A46, RawData!$A:$AJ, 8, FALSE) -> 0.424 | R46: =VLOOKUP($A46, RawData!$A:$AJ, 11, FALSE) | S46: =VLOOKUP($A46, RawData!$A:$AJ, 13, FALSE) -> 10.324 | T46: =VLOOKUP($A46, RawData!$A:$AJ, 14, FALSE) -> 1.5623487 | U46: =VLOOKUP($A46, RawData!$A:$AJ, 23, FALSE) -> -0.0055 | V46: =VLOOKUP($A46, RawData!$A:$AJ, 24, FALSE) | W46: =VLOOKUP($A46, RawData!$A:$AJ, 25, FALSE) | X46: =VLOOKUP($A46, RawData!$A:$AJ, 26, FALSE) | Y46: =VLOOKUP($A46, RawData!$A:$AJ, 27, FALSE) -> 314.11765 | Z46: =VLOOKUP($A46, RawData!$A:$AJ, 28, FALSE) -> 0.8217951 | AA46: =VLOOKUP($A46, RawData!$A:$AJ, 31, FALSE) -> 8.79599 | AB46: =VLOOKUP($A46, RawData!$A:$AJ,32, FALSE) | AC46: =VLOOKUP($A46, RawData!$A:$AJ, 34, FALSE) -> 90.8098 | AD46: =VLOOKUP($A46, RawData!$A:$AJ, 35, FALSE) -> 8.01 | AE46: =VLOOKUP($A46, RawData!$A:$AJ, 36, FALSE) -> 12.48
A47: MRAM | B47: Everspin Technologies | C47: Low | D47: [READ PITCH](https://community.microcapclub.com/forums/topic/4496-everspin-technologies-inc-mram/#comment-90925) | E47: =IFERROR(__xludf.DUMMYFUNCTION("IFERROR(HYPERLINK(REGEXEXTRACT(D47,""\(([^)]*)\)""),REGEXEXTRACT(D47,""\[([^\]]+)\]"")),"""") "),"READ PITCH") -> READ PITCH | F47: =VLOOKUP($A47, RawData!$A:$AJ, 33, FALSE) -> 271.5354 | G47: =VLOOKUP($A47, RawData!$A:$AJ, 2, FALSE) | H47: =VLOOKUP($A47, RawData!$A:$AJ, 3, FALSE) -> -0.0041 | I47: =VLOOKUP($A47, RawData!$A:$AJ, 4, FALSE) -> 0.051605757 | J47: =VLOOKUP($A47, RawData!$A:$AM, 37, FALSE) -> 1.139 | K47: =VLOOKUP($A47, RawData!$A:$AM, 38, FALSE) | L47: =VLOOKUP($A47, RawData!$A:$AM, 39, FALSE) -> -0.307943 | M47: =VLOOKUP($A47, RawData!$A:$AJ, 30, FALSE) -> 189.06673 | N47: =VLOOKUP($A47, RawData!$A:$AJ, 5, FALSE) -> -0.024846895 | O47: =VLOOKUP($A47, RawData!$A:$AJ, 6, FALSE) -> -1.3700325 | P47: =VLOOKUP($A47, RawData!$A:$AJ, 7, FALSE) | Q47: =VLOOKUP($A47, RawData!$A:$AJ, 8, FALSE) -> 0.5131 | R47: =VLOOKUP($A47, RawData!$A:$AJ, 11, FALSE) | S47: =VLOOKUP($A47, RawData!$A:$AJ, 13, FALSE) -> 4.678 | T47: =VLOOKUP($A47, RawData!$A:$AJ, 14, FALSE) -> 1.271887 | U47: =VLOOKUP($A47, RawData!$A:$AJ, 23, FALSE) -> -0.0072 | V47: =VLOOKUP($A47, RawData!$A:$AJ, 24, FALSE) | W47: =VLOOKUP($A47, RawData!$A:$AJ, 25, FALSE) | X47: =VLOOKUP($A47, RawData!$A:$AJ, 26, FALSE) | Y47: =VLOOKUP($A47, RawData!$A:$AJ, 27, FALSE) -> 50.165016 | Z47: =VLOOKUP($A47, RawData!$A:$AJ, 28, FALSE) -> 4.858208 | AA47: =VLOOKUP($A47, RawData!$A:$AJ, 31, FALSE) -> 46.03399 | AB47: =VLOOKUP($A47, RawData!$A:$AJ,32, FALSE) | AC47: =VLOOKUP($A47, RawData!$A:$AJ, 34, FALSE) -> 215.347 | AD47: =VLOOKUP($A47, RawData!$A:$AJ, 35, FALSE) -> 11.4 | AE47: =VLOOKUP($A47, RawData!$A:$AJ, 36, FALSE) -> 22.86
A48: CXDO | B48: Crexendo | C48: Medium | D48: [READ PITCH](https://community.microcapclub.com/forums/topic/2704-crexendo-cxdo/#comment-63206) | E48: =IFERROR(__xludf.DUMMYFUNCTION("IFERROR(HYPERLINK(REGEXEXTRACT(D48,""\(([^)]*)\)""),REGEXEXTRACT(D48,""\[([^\]]+)\]"")),"""") "),"READ PITCH") -> READ PITCH | F48: =VLOOKUP($A48, RawData!$A:$AJ, 33, FALSE) -> 206.51265 | G48: =VLOOKUP($A48, RawData!$A:$AJ, 2, FALSE) | H48: =VLOOKUP($A48, RawData!$A:$AJ, 3, FALSE) -> 0.1291 | I48: =VLOOKUP($A48, RawData!$A:$AJ, 4, FALSE) -> 0.33239052 | J48: =VLOOKUP($A48, RawData!$A:$AM, 37, FALSE) -> 7.328 | K48: =VLOOKUP($A48, RawData!$A:$AM, 38, FALSE) | L48: =VLOOKUP($A48, RawData!$A:$AM, 39, FALSE) -> 0.45597357 | M48: =VLOOKUP($A48, RawData!$A:$AJ, 30, FALSE) -> 26.200888 | N48: =VLOOKUP($A48, RawData!$A:$AJ, 5, FALSE) -> 0.1418809 | O48: =VLOOKUP($A48, RawData!$A:$AJ, 6, FALSE) -> 2.541836 | P48: =VLOOKUP($A48, RawData!$A:$AJ, 7, FALSE) | Q48: =VLOOKUP($A48, RawData!$A:$AJ, 8, FALSE) -> 0.744 | R48: =VLOOKUP($A48, RawData!$A:$AJ, 11, FALSE) | S48: =VLOOKUP($A48, RawData!$A:$AJ, 13, FALSE) -> 9.082 | T48: =VLOOKUP($A48, RawData!$A:$AJ, 14, FALSE) -> 1.3526958 | U48: =VLOOKUP($A48, RawData!$A:$AJ, 23, FALSE) -> 0.0624 | V48: =VLOOKUP($A48, RawData!$A:$AJ, 24, FALSE) | W48: =VLOOKUP($A48, RawData!$A:$AJ, 25, FALSE) | X48: =VLOOKUP($A48, RawData!$A:$AJ, 26, FALSE) -> 50.535343 | Y48: =VLOOKUP($A48, RawData!$A:$AJ, 27, FALSE) -> 20.360254 | Z48: =VLOOKUP($A48, RawData!$A:$AJ, 28, FALSE) -> 3.3209856 | AA48: =VLOOKUP($A48, RawData!$A:$AJ, 31, FALSE) -> 21.140728 | AB48: =VLOOKUP($A48, RawData!$A:$AJ,32, FALSE) | AC48: =VLOOKUP($A48, RawData!$A:$AJ, 34, FALSE) -> 192.0001 | AD48: =VLOOKUP($A48, RawData!$A:$AJ, 35, FALSE) -> 7.17 | AE48: =VLOOKUP($A48, RawData!$A:$AJ, 36, FALSE) -> 30.73
A49: AIOT | B49: PowerFleet | C49: Medium | D49: [READ PITCH](https://community.microcapclub.com/forums/topic/507-powerfleet-inc-aoit/) | E49: =IFERROR(__xludf.DUMMYFUNCTION("IFERROR(HYPERLINK(REGEXEXTRACT(D49,""\(([^)]*)\)""),REGEXEXTRACT(D49,""\[([^\]]+)\]"")),"""") "),"READ PITCH") -> READ PITCH | F49: =VLOOKUP($A49, RawData!$A:$AJ, 33, FALSE) -> 743.3958 | G49: =VLOOKUP($A49, RawData!$A:$AJ, 2, FALSE) | H49: =VLOOKUP($A49, RawData!$A:$AJ, 3, FALSE) -> 0.9297 | I49: =VLOOKUP($A49, RawData!$A:$AJ, 4, FALSE) -> 0.28976965 | J49: =VLOOKUP($A49, RawData!$A:$AM, 37, FALSE) -> 49.899 | K49: =VLOOKUP($A49, RawData!$A:$AM, 38, FALSE) | L49: =VLOOKUP($A49, RawData!$A:$AM, 39, FALSE) -> 0.96575135 | M49: =VLOOKUP($A49, RawData!$A:$AJ, 30, FALSE) -> 19.972464 | N49: =VLOOKUP($A49, RawData!$A:$AJ, 5, FALSE) -> -0.30869824 | O49: =VLOOKUP($A49, RawData!$A:$AJ, 6, FALSE) -> 0.13153282 | P49: =VLOOKUP($A49, RawData!$A:$AJ, 7, FALSE) | Q49: =VLOOKUP($A49, RawData!$A:$AJ, 8, FALSE) -> 0.5462 | R49: =VLOOKUP($A49, RawData!$A:$AJ, 11, FALSE) | S49: =VLOOKUP($A49, RawData!$A:$AJ, 13, FALSE) -> -24.913 | T49: =VLOOKUP($A49, RawData!$A:$AJ, 14, FALSE) -> 0.9907341 | U49: =VLOOKUP($A49, RawData!$A:$AJ, 23, FALSE) -> -0.0448 | V49: =VLOOKUP($A49, RawData!$A:$AJ, 24, FALSE) | W49: =VLOOKUP($A49, RawData!$A:$AJ, 25, FALSE) | X49: =VLOOKUP($A49, RawData!$A:$AJ, 26, FALSE) | Y49: =VLOOKUP($A49, RawData!$A:$AJ, 27, FALSE) | Z49: =VLOOKUP($A49, RawData!$A:$AJ, 28, FALSE) -> 1.7596855 | AA49: =VLOOKUP($A49, RawData!$A:$AJ, 31, FALSE) -> -40.003452 | AB49: =VLOOKUP($A49, RawData!$A:$AJ,32, FALSE) | AC49: =VLOOKUP($A49, RawData!$A:$AJ, 34, FALSE) -> 996.606 | AD49: =VLOOKUP($A49, RawData!$A:$AJ, 35, FALSE) -> 5.6 | AE49: =VLOOKUP($A49, RawData!$A:$AJ, 36, FALSE) -> 133.82
A50: HHS | B50: Harte Hanks | C50: Low | D50: [READ PITCH](https://community.microcapclub.com/forums/topic/3599-harte-hanks-hhs/#comment-79255) | E50: =IFERROR(__xludf.DUMMYFUNCTION("IFERROR(HYPERLINK(REGEXEXTRACT(D50,""\(([^)]*)\)""),REGEXEXTRACT(D50,""\[([^\]]+)\]"")),"""") "),"READ PITCH") -> READ PITCH | F50: =VLOOKUP($A50, RawData!$A:$AJ, 33, FALSE) -> 21.799496 | G50: =VLOOKUP($A50, RawData!$A:$AJ, 2, FALSE) | H50: =VLOOKUP($A50, RawData!$A:$AJ, 3, FALSE) -> -0.1107 | I50: =VLOOKUP($A50, RawData!$A:$AJ, 4, FALSE) -> -0.017350659 | J50: =VLOOKUP($A50, RawData!$A:$AM, 37, FALSE) -> 2.348 | K50: =VLOOKUP($A50, RawData!$A:$AM, 38, FALSE) | L50: =VLOOKUP($A50, RawData!$A:$AM, 39, FALSE) -> 0.23539628 | M50: =VLOOKUP($A50, RawData!$A:$AJ, 30, FALSE) -> 7.106644 | N50: =VLOOKUP($A50, RawData!$A:$AJ, 5, FALSE) -> -0.7354926 | O50: =VLOOKUP($A50, RawData!$A:$AJ, 6, FALSE) -> -0.8173715 | P50: =VLOOKUP($A50, RawData!$A:$AJ, 7, FALSE) | Q50: =VLOOKUP($A50, RawData!$A:$AJ, 8, FALSE) -> 0.1847 | R50: =VLOOKUP($A50, RawData!$A:$AJ, 11, FALSE) | S50: =VLOOKUP($A50, RawData!$A:$AJ, 13, FALSE) -> -0.39 | T50: =VLOOKUP($A50, RawData!$A:$AJ, 14, FALSE) -> 0.055045873 | U50: =VLOOKUP($A50, RawData!$A:$AJ, 23, FALSE) -> -0.0558 | V50: =VLOOKUP($A50, RawData!$A:$AJ, 24, FALSE) | W50: =VLOOKUP($A50, RawData!$A:$AJ, 25, FALSE) | X50: =VLOOKUP($A50, RawData!$A:$AJ, 26, FALSE) | Y50: =VLOOKUP($A50, RawData!$A:$AJ, 27, FALSE) -> 2.7854133 | Z50: =VLOOKUP($A50, RawData!$A:$AJ, 28, FALSE) -> 0.13501717 | AA50: =VLOOKUP($A50, RawData!$A:$AJ, 31, FALSE) -> -42.78564 | AB50: =VLOOKUP($A50, RawData!$A:$AJ,32, FALSE) | AC50: =VLOOKUP($A50, RawData!$A:$AJ, 34, FALSE) -> 16.6864 | AD50: =VLOOKUP($A50, RawData!$A:$AJ, 35, FALSE) -> 3.04 | AE50: =VLOOKUP($A50, RawData!$A:$AJ, 36, FALSE) -> 7.41
A51: WYY | B51: WidePoint Corporation | C51: Low | D51: [READ PITCH](https://community.microcapclub.com/forums/topic/5009-widepoint-corporation-wyy/#comment-97811) | E51: =IFERROR(__xludf.DUMMYFUNCTION("IFERROR(HYPERLINK(REGEXEXTRACT(D51,""\(([^)]*)\)""),REGEXEXTRACT(D51,""\[([^\]]+)\]"")),"""") "),"READ PITCH") -> READ PITCH | F51: =VLOOKUP($A51, RawData!$A:$AJ, 33, FALSE) -> 62.214397 | G51: =VLOOKUP($A51, RawData!$A:$AJ, 2, FALSE) | H51: =VLOOKUP($A51, RawData!$A:$AJ, 3, FALSE) -> 0.1625 | I51: =VLOOKUP($A51, RawData!$A:$AJ, 4, FALSE) -> -0.010384806 | J51: =VLOOKUP($A51, RawData!$A:$AM, 37, FALSE) -> 2.67422 | K51: =VLOOKUP($A51, RawData!$A:$AM, 38, FALSE) | L51: =VLOOKUP($A51, RawData!$A:$AM, 39, FALSE) -> -0.09479094 | M51: =VLOOKUP($A51, RawData!$A:$AJ, 30, FALSE) -> 22.597631 | N51: =VLOOKUP($A51, RawData!$A:$AJ, 5, FALSE) -> -0.21477655 | O51: =VLOOKUP($A51, RawData!$A:$AJ, 6, FALSE) -> -0.3760732 | P51: =VLOOKUP($A51, RawData!$A:$AJ, 7, FALSE) | Q51: =VLOOKUP($A51, RawData!$A:$AJ, 8, FALSE) -> 0.1339 | R51: =VLOOKUP($A51, RawData!$A:$AJ, 11, FALSE) | S51: =VLOOKUP($A51, RawData!$A:$AJ, 13, FALSE) -> 4.04287 | T51: =VLOOKUP($A51, RawData!$A:$AJ, 14, FALSE) -> -1.1820498 | U51: =VLOOKUP($A51, RawData!$A:$AJ, 23, FALSE) -> -0.0307 | V51: =VLOOKUP($A51, RawData!$A:$AJ, 24, FALSE) | W51: =VLOOKUP($A51, RawData!$A:$AJ, 25, FALSE) | X51: =VLOOKUP($A51, RawData!$A:$AJ, 26, FALSE) | Y51: =VLOOKUP($A51, RawData!$A:$AJ, 27, FALSE) | Z51: =VLOOKUP($A51, RawData!$A:$AJ, 28, FALSE) -> 0.46566314 | AA51: =VLOOKUP($A51, RawData!$A:$AJ, 31, FALSE) -> 14.947559 | AB51: =VLOOKUP($A51, RawData!$A:$AJ,32, FALSE) | AC51: =VLOOKUP($A51, RawData!$A:$AJ, 34, FALSE) -> 60.43104 | AD51: =VLOOKUP($A51, RawData!$A:$AJ, 35, FALSE) -> 6.8 | AE51: =VLOOKUP($A51, RawData!$A:$AJ, 36, FALSE) -> 9.89
A52: BLZE | B52: Backblaze | C52: Low | D52: [READ PITCH](https://community.microcapclub.com/forums/topic/4738-backblaze-inc-blze/#comment-94217) | E52: =IFERROR(__xludf.DUMMYFUNCTION("IFERROR(HYPERLINK(REGEXEXTRACT(D52,""\(([^)]*)\)""),REGEXEXTRACT(D52,""\[([^\]]+)\]"")),"""") "),"READ PITCH") -> READ PITCH | F52: =VLOOKUP($A52, RawData!$A:$AJ, 33, FALSE) -> 289.654 | G52: =VLOOKUP($A52, RawData!$A:$AJ, 2, FALSE) | H52: =VLOOKUP($A52, RawData!$A:$AJ, 3, FALSE) -> 0.1573 | I52: =VLOOKUP($A52, RawData!$A:$AJ, 4, FALSE) -> 0.22504596 | J52: =VLOOKUP($A52, RawData!$A:$AM, 37, FALSE) -> -6.388 | K52: =VLOOKUP($A52, RawData!$A:$AM, 38, FALSE) | L52: =VLOOKUP($A52, RawData!$A:$AM, 39, FALSE) -> -6.887837 | M52: =VLOOKUP($A52, RawData!$A:$AJ, 30, FALSE) -> -45.552597 | N52: =VLOOKUP($A52, RawData!$A:$AJ, 5, FALSE) -> -0.59923744 | O52: =VLOOKUP($A52, RawData!$A:$AJ, 6, FALSE) -> -0.25421682 | P52: =VLOOKUP($A52, RawData!$A:$AJ, 7, FALSE) | Q52: =VLOOKUP($A52, RawData!$A:$AJ, 8, FALSE) -> 0.5912 | R52: =VLOOKUP($A52, RawData!$A:$AJ, 11, FALSE) | S52: =VLOOKUP($A52, RawData!$A:$AJ, 13, FALSE) -> 3.083 | T52: =VLOOKUP($A52, RawData!$A:$AJ, 14, FALSE) -> -1.8178066 | U52: =VLOOKUP($A52, RawData!$A:$AJ, 23, FALSE) -> -0.1931 | V52: =VLOOKUP($A52, RawData!$A:$AJ, 24, FALSE) | W52: =VLOOKUP($A52, RawData!$A:$AJ, 25, FALSE) | X52: =VLOOKUP($A52, RawData!$A:$AJ, 26, FALSE) | Y52: =VLOOKUP($A52, RawData!$A:$AJ, 27, FALSE) | Z52: =VLOOKUP($A52, RawData!$A:$AJ, 28, FALSE) -> 1.9889679 | AA52: =VLOOKUP($A52, RawData!$A:$AJ, 31, FALSE) -> 94.38534 | AB52: =VLOOKUP($A52, RawData!$A:$AJ,32, FALSE) | AC52: =VLOOKUP($A52, RawData!$A:$AJ, 34, FALSE) -> 290.99 | AD52: =VLOOKUP($A52, RawData!$A:$AJ, 35, FALSE) -> 4.89 | AE52: =VLOOKUP($A52, RawData!$A:$AJ, 36, FALSE) -> 57.7
A53: EVLV | B53: Evolv Technologies | C53: Medium | D53: [READ PITCH](https://community.microcapclub.com/forums/topic/4271-evolv-technologies-evlv/#comment-87682) | E53: =IFERROR(__xludf.DUMMYFUNCTION("IFERROR(HYPERLINK(REGEXEXTRACT(D53,""\(([^)]*)\)""),REGEXEXTRACT(D53,""\[([^\]]+)\]"")),"""") "),"READ PITCH") -> READ PITCH | F53: =VLOOKUP($A53, RawData!$A:$AJ, 33, FALSE) -> 1258.9929 | G53: =VLOOKUP($A53, RawData!$A:$AJ, 2, FALSE) | H53: =VLOOKUP($A53, RawData!$A:$AJ, 3, FALSE) -> 0.4161 | I53: =VLOOKUP($A53, RawData!$A:$AJ, 4, FALSE) -> 0.77653176 | J53: =VLOOKUP($A53, RawData!$A:$AM, 37, FALSE) -> -37.982 | K53: =VLOOKUP($A53, RawData!$A:$AM, 38, FALSE) | L53: =VLOOKUP($A53, RawData!$A:$AM, 39, FALSE) -> -0.03718961 | M53: =VLOOKUP($A53, RawData!$A:$AJ, 30, FALSE) -> -24.982876 | N53: =VLOOKUP($A53, RawData!$A:$AJ, 5, FALSE) -> -0.34371778 | O53: =VLOOKUP($A53, RawData!$A:$AJ, 6, FALSE) -> 0.0890155 | P53: =VLOOKUP($A53, RawData!$A:$AJ, 7, FALSE) | Q53: =VLOOKUP($A53, RawData!$A:$AJ, 8, FALSE) -> 0.5635 | R53: =VLOOKUP($A53, RawData!$A:$AJ, 11, FALSE) | S53: =VLOOKUP($A53, RawData!$A:$AJ, 13, FALSE) -> -96.201 | T53: =VLOOKUP($A53, RawData!$A:$AJ, 14, FALSE) -> 0.38169792 | U53: =VLOOKUP($A53, RawData!$A:$AJ, 23, FALSE) -> -0.2165 | V53: =VLOOKUP($A53, RawData!$A:$AJ, 24, FALSE) | W53: =VLOOKUP($A53, RawData!$A:$AJ, 25, FALSE) | X53: =VLOOKUP($A53, RawData!$A:$AJ, 26, FALSE) | Y53: =VLOOKUP($A53, RawData!$A:$AJ, 27, FALSE) | Z53: =VLOOKUP($A53, RawData!$A:$AJ, 28, FALSE) -> 8.417518 | AA53: =VLOOKUP($A53, RawData!$A:$AJ, 31, FALSE) -> -9.863719 | AB53: =VLOOKUP($A53, RawData!$A:$AJ,32, FALSE) | AC53: =VLOOKUP($A53, RawData!$A:$AJ, 34, FALSE) -> 948.8996 | AD53: =VLOOKUP($A53, RawData!$A:$AJ, 35, FALSE) -> 6.58 | AE53: =VLOOKUP($A53, RawData!$A:$AJ, 36, FALSE) -> 174.62
A54: SBET | B54: SharpLink Gaming | C54: Low (old) | D54: [READ PITCH](https://community.microcapclub.com/forums/topic/450-sharplink-gaming-sbet/#comment-6310) | E54: =IFERROR(__xludf.DUMMYFUNCTION("IFERROR(HYPERLINK(REGEXEXTRACT(D54,""\(([^)]*)\)""),REGEXEXTRACT(D54,""\[([^\]]+)\]"")),"""") "),"READ PITCH") -> READ PITCH | F54: =VLOOKUP($A54, RawData!$A:$AJ, 33, FALSE) -> 1967.1678 | G54: =VLOOKUP($A54, RawData!$A:$AJ, 2, FALSE) | H54: =VLOOKUP($A54, RawData!$A:$AJ, 3, FALSE) -> 0.6821 | I54: =VLOOKUP($A54, RawData!$A:$AJ, 4, FALSE) -> 0.22400485 | J54: =VLOOKUP($A54, RawData!$A:$AM, 37, FALSE) -> -117.03569 | K54: =VLOOKUP($A54, RawData!$A:$AM, 38, FALSE) | L54: =VLOOKUP($A54, RawData!$A:$AM, 39, FALSE) -> 4.517231 | M54: =VLOOKUP($A54, RawData!$A:$AJ, 30, FALSE) -> -18.18978 | N54: =VLOOKUP($A54, RawData!$A:$AJ, 5, FALSE) -> -0.005237023 | O54: =VLOOKUP($A54, RawData!$A:$AJ, 6, FALSE) -> -0.6823536 | P54: =VLOOKUP($A54, RawData!$A:$AJ, 7, FALSE) | Q54: =VLOOKUP($A54, RawData!$A:$AJ, 8, FALSE) -> 0.8332 | R54: =VLOOKUP($A54, RawData!$A:$AJ, 11, FALSE) | S54: =VLOOKUP($A54, RawData!$A:$AJ, 13, FALSE) -> 13.58128 | T54: =VLOOKUP($A54, RawData!$A:$AJ, 14, FALSE) -> -0.4818018 | U54: =VLOOKUP($A54, RawData!$A:$AJ, 23, FALSE) -> -0.0012 | V54: =VLOOKUP($A54, RawData!$A:$AJ, 24, FALSE) | W54: =VLOOKUP($A54, RawData!$A:$AJ, 25, FALSE) | X54: =VLOOKUP($A54, RawData!$A:$AJ, 26, FALSE) | Y54: =VLOOKUP($A54, RawData!$A:$AJ, 27, FALSE) -> No data | Z54: =VLOOKUP($A54, RawData!$A:$AJ, 28, FALSE) -> 163.28302 | AA54: =VLOOKUP($A54, RawData!$A:$AJ, 31, FALSE) -> 156.74928 | AB54: =VLOOKUP($A54, RawData!$A:$AJ,32, FALSE) | AC54: =VLOOKUP($A54, RawData!$A:$AJ, 34, FALSE) -> 2128.859 | AD54: =VLOOKUP($A54, RawData!$A:$AJ, 35, FALSE) -> 10.88 | AE54: =VLOOKUP($A54, RawData!$A:$AJ, 36, FALSE) -> 196.69
A55: TACT | B55: Transact Technologies | C55: Low Medium | D55: [READ PITCH](https://community.microcapclub.com/forums/topic/1897-transact-technologies-tact/#comment-43387) | E55: =IFERROR(__xludf.DUMMYFUNCTION("IFERROR(HYPERLINK(REGEXEXTRACT(D55,""\(([^)]*)\)""),REGEXEXTRACT(D55,""\[([^\]]+)\]"")),"""") "),"READ PITCH") -> READ PITCH | F55: =VLOOKUP($A55, RawData!$A:$AJ, 33, FALSE) -> 41.461597 | G55: =VLOOKUP($A55, RawData!$A:$AJ, 2, FALSE) | H55: =VLOOKUP($A55, RawData!$A:$AJ, 3, FALSE) -> 0.0827 | I55: =VLOOKUP($A55, RawData!$A:$AJ, 4, FALSE) -> 0.08129764 | J55: =VLOOKUP($A55, RawData!$A:$AM, 37, FALSE) -> -0.598 | K55: =VLOOKUP($A55, RawData!$A:$AM, 38, FALSE) | L55: =VLOOKUP($A55, RawData!$A:$AM, 39, FALSE) -> -0.34812024 | M55: =VLOOKUP($A55, RawData!$A:$AJ, 30, FALSE) -> -43.017223 | N55: =VLOOKUP($A55, RawData!$A:$AJ, 5, FALSE) -> -0.79782397 | O55: =VLOOKUP($A55, RawData!$A:$AJ, 6, FALSE) -> 3.0985773 | P55: =VLOOKUP($A55, RawData!$A:$AJ, 7, FALSE) | Q55: =VLOOKUP($A55, RawData!$A:$AJ, 8, FALSE) -> 0.4793 | R55: =VLOOKUP($A55, RawData!$A:$AJ, 11, FALSE) | S55: =VLOOKUP($A55, RawData!$A:$AJ, 13, FALSE) -> 8 | T55: =VLOOKUP($A55, RawData!$A:$AJ, 14, FALSE) -> -250 | U55: =VLOOKUP($A55, RawData!$A:$AJ, 23, FALSE) -> -0.1815 | V55: =VLOOKUP($A55, RawData!$A:$AJ, 24, FALSE) | W55: =VLOOKUP($A55, RawData!$A:$AJ, 25, FALSE) | X55: =VLOOKUP($A55, RawData!$A:$AJ, 26, FALSE) | Y55: =VLOOKUP($A55, RawData!$A:$AJ, 27, FALSE) | Z55: =VLOOKUP($A55, RawData!$A:$AJ, 28, FALSE) -> 0.85091525 | AA55: =VLOOKUP($A55, RawData!$A:$AJ, 31, FALSE) -> 3.2155375 | AB55: =VLOOKUP($A55, RawData!$A:$AJ,32, FALSE) | AC55: =VLOOKUP($A55, RawData!$A:$AJ, 34, FALSE) -> 25.7243 | AD55: =VLOOKUP($A55, RawData!$A:$AJ, 35, FALSE) -> 4.23 | AE55: =VLOOKUP($A55, RawData!$A:$AJ, 36, FALSE) -> 10.11
A56: GSIT | B56: GSI Technology | C56: Medium | D56: [READ PITCH](https://community.microcapclub.com/forums/topic/2206-gsi-technology-gsit/#comment-51021) | E56: =IFERROR(__xludf.DUMMYFUNCTION("IFERROR(HYPERLINK(REGEXEXTRACT(D56,""\(([^)]*)\)""),REGEXEXTRACT(D56,""\[([^\]]+)\]"")),"""") "),"READ PITCH") -> READ PITCH | F56: =VLOOKUP($A56, RawData!$A:$AJ, 33, FALSE) -> 279.1143 | G56: =VLOOKUP($A56, RawData!$A:$AJ, 2, FALSE) | H56: =VLOOKUP($A56, RawData!$A:$AJ, 3, FALSE) -> 0.22 | I56: =VLOOKUP($A56, RawData!$A:$AJ, 4, FALSE) -> -0.054954648 | J56: =VLOOKUP($A56, RawData!$A:$AM, 37, FALSE) -> -11.079 | K56: =VLOOKUP($A56, RawData!$A:$AM, 38, FALSE) | L56: =VLOOKUP($A56, RawData!$A:$AM, 39, FALSE) -> -0.09450546 | M56: =VLOOKUP($A56, RawData!$A:$AJ, 30, FALSE) -> -21.283726 | N56: =VLOOKUP($A56, RawData!$A:$AJ, 5, FALSE) -> -0.3309024 | O56: =VLOOKUP($A56, RawData!$A:$AJ, 6, FALSE) -> -0.23794276 | P56: =VLOOKUP($A56, RawData!$A:$AJ, 7, FALSE) | Q56: =VLOOKUP($A56, RawData!$A:$AJ, 8, FALSE) -> 0.558 | R56: =VLOOKUP($A56, RawData!$A:$AJ, 11, FALSE) | S56: =VLOOKUP($A56, RawData!$A:$AJ, 13, FALSE) -> -7.877 | T56: =VLOOKUP($A56, RawData!$A:$AJ, 14, FALSE) -> 0.41772285 | U56: =VLOOKUP($A56, RawData!$A:$AJ, 23, FALSE) -> -0.2456 | V56: =VLOOKUP($A56, RawData!$A:$AJ, 24, FALSE) | W56: =VLOOKUP($A56, RawData!$A:$AJ, 25, FALSE) | X56: =VLOOKUP($A56, RawData!$A:$AJ, 26, FALSE) | Y56: =VLOOKUP($A56, RawData!$A:$AJ, 27, FALSE) | Z56: =VLOOKUP($A56, RawData!$A:$AJ, 28, FALSE) -> 10.86948 | AA56: =VLOOKUP($A56, RawData!$A:$AJ, 31, FALSE) -> -29.935558 | AB56: =VLOOKUP($A56, RawData!$A:$AJ,32, FALSE) | AC56: =VLOOKUP($A56, RawData!$A:$AJ, 34, FALSE) -> 235.8024 | AD56: =VLOOKUP($A56, RawData!$A:$AJ, 35, FALSE) -> 7.41 | AE56: =VLOOKUP($A56, RawData!$A:$AJ, 36, FALSE) -> 35.24
A57: SOBR | B57: Sobr Safe | C57: Lowest | D57: [READ PITCH](https://community.microcapclub.com/forums/topic/3682-sobr-safe-sobr/#comment-80582) | E57: =IFERROR(__xludf.DUMMYFUNCTION("IFERROR(HYPERLINK(REGEXEXTRACT(D57,""\(([^)]*)\)""),REGEXEXTRACT(D57,""\[([^\]]+)\]"")),"""") "),"READ PITCH") -> READ PITCH | F57: =VLOOKUP($A57, RawData!$A:$AJ, 33, FALSE) -> 2.6534462 | G57: =VLOOKUP($A57, RawData!$A:$AJ, 2, FALSE) | H57: =VLOOKUP($A57, RawData!$A:$AJ, 3, FALSE) -> 0.9807 | I57: =VLOOKUP($A57, RawData!$A:$AJ, 4, FALSE) -> No data | J57: =VLOOKUP($A57, RawData!$A:$AM, 37, FALSE) -> -7.93412 | K57: =VLOOKUP($A57, RawData!$A:$AM, 38, FALSE) | L57: =VLOOKUP($A57, RawData!$A:$AM, 39, FALSE) -> -0.23108828 | M57: =VLOOKUP($A57, RawData!$A:$AJ, 30, FALSE) -> 0.21713687 | N57: =VLOOKUP($A57, RawData!$A:$AJ, 5, FALSE) -> -5.4248686 | O57: =VLOOKUP($A57, RawData!$A:$AJ, 6, FALSE) -> -0.08034516 | P57: =VLOOKUP($A57, RawData!$A:$AJ, 7, FALSE) | Q57: =VLOOKUP($A57, RawData!$A:$AJ, 8, FALSE) -> 0.2787 | R57: =VLOOKUP($A57, RawData!$A:$AJ, 11, FALSE) | S57: =VLOOKUP($A57, RawData!$A:$AJ, 13, FALSE) -> -6.97925 | T57: =VLOOKUP($A57, RawData!$A:$AJ, 14, FALSE) -> 1.1387053 | U57: =VLOOKUP($A57, RawData!$A:$AJ, 23, FALSE) -> -0.7871 | V57: =VLOOKUP($A57, RawData!$A:$AJ, 24, FALSE) | W57: =VLOOKUP($A57, RawData!$A:$AJ, 25, FALSE) | X57: =VLOOKUP($A57, RawData!$A:$AJ, 26, FALSE) | Y57: =VLOOKUP($A57, RawData!$A:$AJ, 27, FALSE) | Z57: =VLOOKUP($A57, RawData!$A:$AJ, 28, FALSE) -> 7.596452 | AA57: =VLOOKUP($A57, RawData!$A:$AJ, 31, FALSE) -> 0.24684457 | AB57: =VLOOKUP($A57, RawData!$A:$AJ,32, FALSE) | AC57: =VLOOKUP($A57, RawData!$A:$AJ, 34, FALSE) -> -1.72279 | AD57: =VLOOKUP($A57, RawData!$A:$AJ, 35, FALSE) -> 1.82 | AE57: =VLOOKUP($A57, RawData!$A:$AJ, 36, FALSE) -> 1.52
A58: INVE | B58: Identiv | C58: Low | D58: [READ PITCH](https://community.microcapclub.com/forums/topic/2936-identiv-inve/#comment-67469) | E58: =IFERROR(__xludf.DUMMYFUNCTION("IFERROR(HYPERLINK(REGEXEXTRACT(D58,""\(([^)]*)\)""),REGEXEXTRACT(D58,""\[([^\]]+)\]"")),"""") "),"READ PITCH") -> READ PITCH | F58: =VLOOKUP($A58, RawData!$A:$AJ, 33, FALSE) -> 83.28526 | G58: =VLOOKUP($A58, RawData!$A:$AJ, 2, FALSE) | H58: =VLOOKUP($A58, RawData!$A:$AJ, 3, FALSE) -> -0.66 | I58: =VLOOKUP($A58, RawData!$A:$AJ, 4, FALSE) -> -0.22948265 | J58: =VLOOKUP($A58, RawData!$A:$AM, 37, FALSE) -> -21.856 | K58: =VLOOKUP($A58, RawData!$A:$AM, 38, FALSE) | L58: =VLOOKUP($A58, RawData!$A:$AM, 39, FALSE) -> 0.7088183 | M58: =VLOOKUP($A58, RawData!$A:$AJ, 30, FALSE) -> 2.0064743 | N58: =VLOOKUP($A58, RawData!$A:$AJ, 5, FALSE) -> -0.61629474 | O58: =VLOOKUP($A58, RawData!$A:$AJ, 6, FALSE) -> -1.1989506 | P58: =VLOOKUP($A58, RawData!$A:$AJ, 7, FALSE) | Q58: =VLOOKUP($A58, RawData!$A:$AJ, 8, FALSE) -> -0.0365 | R58: =VLOOKUP($A58, RawData!$A:$AJ, 11, FALSE) | S58: =VLOOKUP($A58, RawData!$A:$AJ, 13, FALSE) -> -17.177 | T58: =VLOOKUP($A58, RawData!$A:$AJ, 14, FALSE) -> 2.5409763 | U58: =VLOOKUP($A58, RawData!$A:$AJ, 23, FALSE) -> -0.0934 | V58: =VLOOKUP($A58, RawData!$A:$AJ, 24, FALSE) | W58: =VLOOKUP($A58, RawData!$A:$AJ, 25, FALSE) | X58: =VLOOKUP($A58, RawData!$A:$AJ, 26, FALSE) | Y58: =VLOOKUP($A58, RawData!$A:$AJ, 27, FALSE) | Z58: =VLOOKUP($A58, RawData!$A:$AJ, 28, FALSE) -> 3.7434704 | AA58: =VLOOKUP($A58, RawData!$A:$AJ, 31, FALSE) -> 2.553036 | AB58: =VLOOKUP($A58, RawData!$A:$AJ,32, FALSE) | AC58: =VLOOKUP($A58, RawData!$A:$AJ, 34, FALSE) -> -43.8535 | AD58: =VLOOKUP($A58, RawData!$A:$AJ, 35, FALSE) -> 3.47 | AE58: =VLOOKUP($A58, RawData!$A:$AJ, 36, FALSE) -> 23.75
A59: CURI | B59: CuriosityStream Inc. | C59: Lowest | D59: [READ PITCH](https://community.microcapclub.com/forums/topic/4834-curiositystream-inc-curi/#comment-95568) | E59: =IFERROR(__xludf.DUMMYFUNCTION("IFERROR(HYPERLINK(REGEXEXTRACT(D59,""\(([^)]*)\)""),REGEXEXTRACT(D59,""\[([^\]]+)\]"")),"""") "),"READ PITCH") -> READ PITCH | F59: =VLOOKUP($A59, RawData!$A:$AJ, 33, FALSE) -> 210.16612 | G59: =VLOOKUP($A59, RawData!$A:$AJ, 2, FALSE) | H59: =VLOOKUP($A59, RawData!$A:$AJ, 3, FALSE) -> 0.2862 | I59: =VLOOKUP($A59, RawData!$A:$AJ, 4, FALSE) -> No data | J59: =VLOOKUP($A59, RawData!$A:$AM, 37, FALSE) -> 23.188 | K59: =VLOOKUP($A59, RawData!$A:$AM, 38, FALSE) | L59: =VLOOKUP($A59, RawData!$A:$AM, 39, FALSE) -> 1.8478525 | M59: =VLOOKUP($A59, RawData!$A:$AJ, 30, FALSE) -> 8.618812 | N59: =VLOOKUP($A59, RawData!$A:$AJ, 5, FALSE) -> -0.0935506 | O59: =VLOOKUP($A59, RawData!$A:$AJ, 6, FALSE) -> -0.6311625 | P59: =VLOOKUP($A59, RawData!$A:$AJ, 7, FALSE) | Q59: =VLOOKUP($A59, RawData!$A:$AJ, 8, FALSE) -> 0.545 | R59: =VLOOKUP($A59, RawData!$A:$AJ, 11, FALSE) | S59: =VLOOKUP($A59, RawData!$A:$AJ, 13, FALSE) -> 12.046 | T59: =VLOOKUP($A59, RawData!$A:$AJ, 14, FALSE) -> 4.688984 | U59: =VLOOKUP($A59, RawData!$A:$AJ, 23, FALSE) -> -0.0672 | V59: =VLOOKUP($A59, RawData!$A:$AJ, 24, FALSE) | W59: =VLOOKUP($A59, RawData!$A:$AJ, 25, FALSE) | X59: =VLOOKUP($A59, RawData!$A:$AJ, 26, FALSE) | Y59: =VLOOKUP($A59, RawData!$A:$AJ, 27, FALSE) | Z59: =VLOOKUP($A59, RawData!$A:$AJ, 28, FALSE) -> 3.212869 | AA59: =VLOOKUP($A59, RawData!$A:$AJ, 31, FALSE) -> 16.590818 | AB59: =VLOOKUP($A59, RawData!$A:$AJ,32, FALSE) | AC59: =VLOOKUP($A59, RawData!$A:$AJ, 34, FALSE) -> 199.853 | AD59: =VLOOKUP($A59, RawData!$A:$AJ, 35, FALSE) -> 3.67 | AE59: =VLOOKUP($A59, RawData!$A:$AJ, 36, FALSE) -> 58.3
A60: APPS | B60: Digital Turbine | C60: High (old) | D60: [READ PITCH](https://community.microcapclub.com/forums/topic/779-digital-turbine-apps/#comment-14417) | E60: =IFERROR(__xludf.DUMMYFUNCTION("IFERROR(HYPERLINK(REGEXEXTRACT(D60,""\(([^)]*)\)""),REGEXEXTRACT(D60,""\[([^\]]+)\]"")),"""") "),"READ PITCH") -> READ PITCH | F60: =VLOOKUP($A60, RawData!$A:$AJ, 33, FALSE) -> 547.2866 | G60: =VLOOKUP($A60, RawData!$A:$AJ, 2, FALSE) | H60: =VLOOKUP($A60, RawData!$A:$AJ, 3, FALSE) -> 0.0682 | I60: =VLOOKUP($A60, RawData!$A:$AJ, 4, FALSE) -> 0.20661658 | J60: =VLOOKUP($A60, RawData!$A:$AM, 37, FALSE) -> 46.189 | K60: =VLOOKUP($A60, RawData!$A:$AM, 38, FALSE) | L60: =VLOOKUP($A60, RawData!$A:$AM, 39, FALSE) -> 0.14666492 | M60: =VLOOKUP($A60, RawData!$A:$AJ, 30, FALSE) -> 20.446037 | N60: =VLOOKUP($A60, RawData!$A:$AJ, 5, FALSE) -> -0.6865805 | O60: =VLOOKUP($A60, RawData!$A:$AJ, 6, FALSE) -> -0.7439504 | P60: =VLOOKUP($A60, RawData!$A:$AJ, 7, FALSE) | Q60: =VLOOKUP($A60, RawData!$A:$AJ, 8, FALSE) -> 0.4577 | R60: =VLOOKUP($A60, RawData!$A:$AJ, 11, FALSE) | S60: =VLOOKUP($A60, RawData!$A:$AJ, 13, FALSE) -> 16 | T60: =VLOOKUP($A60, RawData!$A:$AJ, 14, FALSE) -> -0.48335448 | U60: =VLOOKUP($A60, RawData!$A:$AJ, 23, FALSE) -> -0.0936 | V60: =VLOOKUP($A60, RawData!$A:$AJ, 24, FALSE) | W60: =VLOOKUP($A60, RawData!$A:$AJ, 25, FALSE) | X60: =VLOOKUP($A60, RawData!$A:$AJ, 26, FALSE) | Y60: =VLOOKUP($A60, RawData!$A:$AJ, 27, FALSE) -> 16.05392 | Z60: =VLOOKUP($A60, RawData!$A:$AJ, 28, FALSE) -> 1.1191677 | AA60: =VLOOKUP($A60, RawData!$A:$AJ, 31, FALSE) -> 59.023876 | AB60: =VLOOKUP($A60, RawData!$A:$AJ,32, FALSE) | AC60: =VLOOKUP($A60, RawData!$A:$AJ, 34, FALSE) -> 944.382 | AD60: =VLOOKUP($A60, RawData!$A:$AJ, 35, FALSE) -> 5.24 | AE60: =VLOOKUP($A60, RawData!$A:$AJ, 36, FALSE) -> 112.15
A61: CMPD | B61: Compumed | C61: Medium | D61: [READ PITCH](https://community.microcapclub.com/forums/topic/2551-compumed-inc-cmpd/#comment-58840) | E61: =IFERROR(__xludf.DUMMYFUNCTION("IFERROR(HYPERLINK(REGEXEXTRACT(D61,""\(([^)]*)\)""),REGEXEXTRACT(D61,""\[([^\]]+)\]"")),"""") "),"READ PITCH") -> READ PITCH | F61: =VLOOKUP($A61, RawData!$A:$AJ, 33, FALSE) -> 5.50877 | G61: =VLOOKUP($A61, RawData!$A:$AJ, 2, FALSE) | H61: =VLOOKUP($A61, RawData!$A:$AJ, 3, FALSE) -> 0.2957 | I61: =VLOOKUP($A61, RawData!$A:$AJ, 4, FALSE) -> 0.0037851895 | J61: =VLOOKUP($A61, RawData!$A:$AM, 37, FALSE) -> -0.099 | K61: =VLOOKUP($A61, RawData!$A:$AM, 38, FALSE) | L61: =VLOOKUP($A61, RawData!$A:$AM, 39, FALSE) -> -0.4461702 | M61: =VLOOKUP($A61, RawData!$A:$AJ, 30, FALSE) -> -61.47677 | N61: =VLOOKUP($A61, RawData!$A:$AJ, 5, FALSE) -> -0.18181819 | O61: =VLOOKUP($A61, RawData!$A:$AJ, 6, FALSE) -> 3.2105262 | P61: =VLOOKUP($A61, RawData!$A:$AJ, 7, FALSE) | Q61: =VLOOKUP($A61, RawData!$A:$AJ, 8, FALSE) -> 0.5062 | R61: =VLOOKUP($A61, RawData!$A:$AJ, 11, FALSE) | S61: =VLOOKUP($A61, RawData!$A:$AJ, 13, FALSE) -> -0.014 | T61: =VLOOKUP($A61, RawData!$A:$AJ, 14, FALSE) -> -0.1627907 | U61: =VLOOKUP($A61, RawData!$A:$AJ, 23, FALSE) -> -0.3032 | V61: =VLOOKUP($A61, RawData!$A:$AJ, 24, FALSE) | W61: =VLOOKUP($A61, RawData!$A:$AJ, 25, FALSE) | X61: =VLOOKUP($A61, RawData!$A:$AJ, 26, FALSE) | Y61: =VLOOKUP($A61, RawData!$A:$AJ, 27, FALSE) | Z61: =VLOOKUP($A61, RawData!$A:$AJ, 28, FALSE) -> 2.6267457 | AA61: =VLOOKUP($A61, RawData!$A:$AJ, 31, FALSE) -> -434.72858 | AB61: =VLOOKUP($A61, RawData!$A:$AJ,32, FALSE) | AC61: =VLOOKUP($A61, RawData!$A:$AJ, 34, FALSE) -> 6.0862 | AD61: =VLOOKUP($A61, RawData!$A:$AJ, 35, FALSE) -> 4.07 | AE61: =VLOOKUP($A61, RawData!$A:$AJ, 36, FALSE) -> 1.32
A62: SOPH | B62: SOPHiA GENETICS SA | C62: Low Medium | D62: [READ PITCH](https://community.microcapclub.com/forums/topic/4838-sophia-genetics-sa-soph/#comment-95646) | E62: =IFERROR(__xludf.DUMMYFUNCTION("IFERROR(HYPERLINK(REGEXEXTRACT(D62,""\(([^)]*)\)""),REGEXEXTRACT(D62,""\[([^\]]+)\]"")),"""") "),"READ PITCH") -> READ PITCH | F62: =VLOOKUP($A62, RawData!$A:$AJ, 33, FALSE) -> 354.16162 | G62: =VLOOKUP($A62, RawData!$A:$AJ, 2, FALSE) | H62: =VLOOKUP($A62, RawData!$A:$AJ, 3, FALSE) -> 0.1366 | I62: =VLOOKUP($A62, RawData!$A:$AJ, 4, FALSE) -> 0.18350428 | J62: =VLOOKUP($A62, RawData!$A:$AM, 37, FALSE) -> -55.646 | K62: =VLOOKUP($A62, RawData!$A:$AM, 38, FALSE) | L62: =VLOOKUP($A62, RawData!$A:$AM, 39, FALSE) -> -0.009278263 | M62: =VLOOKUP($A62, RawData!$A:$AJ, 30, FALSE) -> -6.279472 | N62: =VLOOKUP($A62, RawData!$A:$AJ, 5, FALSE) -> -1.1050552 | O62: =VLOOKUP($A62, RawData!$A:$AJ, 6, FALSE) -> 0.050170876 | P62: =VLOOKUP($A62, RawData!$A:$AJ, 7, FALSE) | Q62: =VLOOKUP($A62, RawData!$A:$AJ, 8, FALSE) -> 0.6752 | R62: =VLOOKUP($A62, RawData!$A:$AJ, 11, FALSE) | S62: =VLOOKUP($A62, RawData!$A:$AJ, 13, FALSE) -> -46.454 | T62: =VLOOKUP($A62, RawData!$A:$AJ, 14, FALSE) -> 0.8933805 | U62: =VLOOKUP($A62, RawData!$A:$AJ, 23, FALSE) -> -0.4006 | V62: =VLOOKUP($A62, RawData!$A:$AJ, 24, FALSE) | W62: =VLOOKUP($A62, RawData!$A:$AJ, 25, FALSE) | X62: =VLOOKUP($A62, RawData!$A:$AJ, 26, FALSE) | Y62: =VLOOKUP($A62, RawData!$A:$AJ, 27, FALSE) | Z62: =VLOOKUP($A62, RawData!$A:$AJ, 28, FALSE) -> 4.7672825 | AA62: =VLOOKUP($A62, RawData!$A:$AJ, 31, FALSE) -> -7.522011 | AB62: =VLOOKUP($A62, RawData!$A:$AJ,32, FALSE) | AC62: =VLOOKUP($A62, RawData!$A:$AJ, 34, FALSE) -> 349.4275 | AD62: =VLOOKUP($A62, RawData!$A:$AJ, 35, FALSE) -> 5.15 | AE62: =VLOOKUP($A62, RawData!$A:$AJ, 36, FALSE) -> 67.85
A63: RSSS | B63: Research Solutions | C63: Medium High | D63: [READ PITCH](https://community.microcapclub.com/forums/topic/1434-research-solutions-rsss/) | E63: =IFERROR(__xludf.DUMMYFUNCTION("IFERROR(HYPERLINK(REGEXEXTRACT(D63,""\(([^)]*)\)""),REGEXEXTRACT(D63,""\[([^\]]+)\]"")),"""") "),"READ PITCH") -> READ PITCH | F63: =VLOOKUP($A63, RawData!$A:$AJ, 33, FALSE) -> 95.23599 | G63: =VLOOKUP($A63, RawData!$A:$AJ, 2, FALSE) | H63: =VLOOKUP($A63, RawData!$A:$AJ, 3, FALSE) -> 0.0583 | I63: =VLOOKUP($A63, RawData!$A:$AJ, 4, FALSE) -> 0.09579182 | J63: =VLOOKUP($A63, RawData!$A:$AM, 37, FALSE) -> 2.53755 | K63: =VLOOKUP($A63, RawData!$A:$AM, 38, FALSE) | L63: =VLOOKUP($A63, RawData!$A:$AM, 39, FALSE) -> 0.24963982 | M63: =VLOOKUP($A63, RawData!$A:$AJ, 30, FALSE) -> 32.20575 | N63: =VLOOKUP($A63, RawData!$A:$AJ, 5, FALSE) -> 0.04094737 | O63: =VLOOKUP($A63, RawData!$A:$AJ, 6, FALSE) -> -1.6320273 | P63: =VLOOKUP($A63, RawData!$A:$AJ, 7, FALSE) | Q63: =VLOOKUP($A63, RawData!$A:$AJ, 8, FALSE) -> 0.4998 | R63: =VLOOKUP($A63, RawData!$A:$AJ, 11, FALSE) | S63: =VLOOKUP($A63, RawData!$A:$AJ, 13, FALSE) -> 7.25037 | T63: =VLOOKUP($A63, RawData!$A:$AJ, 14, FALSE) -> 1.4079373 | U63: =VLOOKUP($A63, RawData!$A:$AJ, 23, FALSE) -> 0.03 | V63: =VLOOKUP($A63, RawData!$A:$AJ, 24, FALSE) | W63: =VLOOKUP($A63, RawData!$A:$AJ, 25, FALSE) | X63: =VLOOKUP($A63, RawData!$A:$AJ, 26, FALSE) -> 69.60154 | Y63: =VLOOKUP($A63, RawData!$A:$AJ, 27, FALSE) -> 20.155586 | Z63: =VLOOKUP($A63, RawData!$A:$AJ, 28, FALSE) -> 1.8992027 | AA63: =VLOOKUP($A63, RawData!$A:$AJ, 31, FALSE) -> 11.271659 | AB63: =VLOOKUP($A63, RawData!$A:$AJ,32, FALSE) | AC63: =VLOOKUP($A63, RawData!$A:$AJ, 34, FALSE) -> 81.7237 | AD63: =VLOOKUP($A63, RawData!$A:$AJ, 35, FALSE) -> 2.85 | AE63: =VLOOKUP($A63, RawData!$A:$AJ, 36, FALSE) -> 32.87
A64: ELVA | B64: Electrovaya | C64: Lowest | D64: [READ PITCH](https://community.microcapclub.com/forums/topic/3916-electrovaya-elva/#comment-83253) | E64: =IFERROR(__xludf.DUMMYFUNCTION("IFERROR(HYPERLINK(REGEXEXTRACT(D64,""\(([^)]*)\)""),REGEXEXTRACT(D64,""\[([^\]]+)\]"")),"""") "),"READ PITCH") -> READ PITCH | F64: =VLOOKUP($A64, RawData!$A:$AJ, 33, FALSE) -> 571.59247 | G64: =VLOOKUP($A64, RawData!$A:$AJ, 2, FALSE) | H64: =VLOOKUP($A64, RawData!$A:$AJ, 3, FALSE) -> 0.4306 | I64: =VLOOKUP($A64, RawData!$A:$AJ, 4, FALSE) -> 0.34445542 | J64: =VLOOKUP($A64, RawData!$A:$AM, 37, FALSE) -> 6.994 | K64: =VLOOKUP($A64, RawData!$A:$AM, 38, FALSE) | L64: =VLOOKUP($A64, RawData!$A:$AM, 39, FALSE) -> 0.087883994 | M64: =VLOOKUP($A64, RawData!$A:$AJ, 30, FALSE) -> 57.66289 | N64: =VLOOKUP($A64, RawData!$A:$AJ, 5, FALSE) -> 0.07389585 | O64: =VLOOKUP($A64, RawData!$A:$AJ, 6, FALSE) -> -3.2769127 | P64: =VLOOKUP($A64, RawData!$A:$AJ, 7, FALSE) | Q64: =VLOOKUP($A64, RawData!$A:$AJ, 8, FALSE) -> 0.309 | R64: =VLOOKUP($A64, RawData!$A:$AJ, 11, FALSE) | S64: =VLOOKUP($A64, RawData!$A:$AJ, 13, FALSE) -> -2.894 | T64: =VLOOKUP($A64, RawData!$A:$AJ, 14, FALSE) -> -3.18022 | U64: =VLOOKUP($A64, RawData!$A:$AJ, 23, FALSE) -> 0.0646 | V64: =VLOOKUP($A64, RawData!$A:$AJ, 24, FALSE) | W64: =VLOOKUP($A64, RawData!$A:$AJ, 25, FALSE) | X64: =VLOOKUP($A64, RawData!$A:$AJ, 26, FALSE) -> 115.00483 | Y64: =VLOOKUP($A64, RawData!$A:$AJ, 27, FALSE) -> 48.428684 | Z64: =VLOOKUP($A64, RawData!$A:$AJ, 28, FALSE) -> 6.059619 | AA64: =VLOOKUP($A64, RawData!$A:$AJ, 31, FALSE) -> -139.3553 | AB64: =VLOOKUP($A64, RawData!$A:$AJ,32, FALSE) | AC64: =VLOOKUP($A64, RawData!$A:$AJ, 34, FALSE) -> 559.97406 | AD64: =VLOOKUP($A64, RawData!$A:$AJ, 35, FALSE) -> 8.69 | AE64: =VLOOKUP($A64, RawData!$A:$AJ, 36, FALSE) -> No data
A65: OSS | B65: One Stop Systems | C65: Medium | D65: [READ PITCH](https://community.microcapclub.com/forums/topic/2643-one-stop-systems-inc-oss/#comment-61784) | E65: =IFERROR(__xludf.DUMMYFUNCTION("IFERROR(HYPERLINK(REGEXEXTRACT(D65,""\(([^)]*)\)""),REGEXEXTRACT(D65,""\[([^\]]+)\]"")),"""") "),"READ PITCH") -> READ PITCH | F65: =VLOOKUP($A65, RawData!$A:$AJ, 33, FALSE) -> 200.3798 | G65: =VLOOKUP($A65, RawData!$A:$AJ, 2, FALSE) | H65: =VLOOKUP($A65, RawData!$A:$AJ, 3, FALSE) -> 0.1433 | I65: =VLOOKUP($A65, RawData!$A:$AJ, 4, FALSE) -> 0.013377401 | J65: =VLOOKUP($A65, RawData!$A:$AM, 37, FALSE) -> -5.24694 | K65: =VLOOKUP($A65, RawData!$A:$AM, 38, FALSE) | L65: =VLOOKUP($A65, RawData!$A:$AM, 39, FALSE) -> 0.41211525 | M65: =VLOOKUP($A65, RawData!$A:$AJ, 30, FALSE) -> -37.363663 | N65: =VLOOKUP($A65, RawData!$A:$AJ, 5, FALSE) -> -0.28160155 | O65: =VLOOKUP($A65, RawData!$A:$AJ, 6, FALSE) -> -0.35932902 | P65: =VLOOKUP($A65, RawData!$A:$AJ, 7, FALSE) | Q65: =VLOOKUP($A65, RawData!$A:$AJ, 8, FALSE) -> 0.2901 | R65: =VLOOKUP($A65, RawData!$A:$AJ, 11, FALSE) | S65: =VLOOKUP($A65, RawData!$A:$AJ, 13, FALSE) -> -7.7035 | T65: =VLOOKUP($A65, RawData!$A:$AJ, 14, FALSE) -> -10.720598 | U65: =VLOOKUP($A65, RawData!$A:$AJ, 23, FALSE) -> -0.1764 | V65: =VLOOKUP($A65, RawData!$A:$AJ, 24, FALSE) | W65: =VLOOKUP($A65, RawData!$A:$AJ, 25, FALSE) | X65: =VLOOKUP($A65, RawData!$A:$AJ, 26, FALSE) | Y65: =VLOOKUP($A65, RawData!$A:$AJ, 27, FALSE) | Z65: =VLOOKUP($A65, RawData!$A:$AJ, 28, FALSE) -> 3.3250332 | AA65: =VLOOKUP($A65, RawData!$A:$AJ, 31, FALSE) -> -25.448809 | AB65: =VLOOKUP($A65, RawData!$A:$AJ,32, FALSE) | AC65: =VLOOKUP($A65, RawData!$A:$AJ, 34, FALSE) -> 196.0449 | AD65: =VLOOKUP($A65, RawData!$A:$AJ, 35, FALSE) -> 11.69 | AE65: =VLOOKUP($A65, RawData!$A:$AJ, 36, FALSE) -> 24.52
A66: IDN | B66: Intellicheck | C66: High | D66: [READ PITCH](https://community.microcapclub.com/forums/topic/2035-intellicheck-idn/#comment-46279) | E66: =IFERROR(__xludf.DUMMYFUNCTION("IFERROR(HYPERLINK(REGEXEXTRACT(D66,""\(([^)]*)\)""),REGEXEXTRACT(D66,""\[([^\]]+)\]"")),"""") "),"READ PITCH") -> READ PITCH | F66: =VLOOKUP($A66, RawData!$A:$AJ, 33, FALSE) -> 129.7155 | G66: =VLOOKUP($A66, RawData!$A:$AJ, 2, FALSE) | H66: =VLOOKUP($A66, RawData!$A:$AJ, 3, FALSE) -> 0.142 | I66: =VLOOKUP($A66, RawData!$A:$AJ, 4, FALSE) -> 0.15777807 | J66: =VLOOKUP($A66, RawData!$A:$AM, 37, FALSE) -> 0.732 | K66: =VLOOKUP($A66, RawData!$A:$AM, 38, FALSE) | L66: =VLOOKUP($A66, RawData!$A:$AM, 39, FALSE) -> -0.14377438 | M66: =VLOOKUP($A66, RawData!$A:$AJ, 30, FALSE) -> 156.53415 | N66: =VLOOKUP($A66, RawData!$A:$AJ, 5, FALSE) -> 0.010346535 | O66: =VLOOKUP($A66, RawData!$A:$AJ, 6, FALSE) -> -1.3220339 | P66: =VLOOKUP($A66, RawData!$A:$AJ, 7, FALSE) | Q66: =VLOOKUP($A66, RawData!$A:$AJ, 8, FALSE) -> 0.9033 | R66: =VLOOKUP($A66, RawData!$A:$AJ, 11, FALSE) | S66: =VLOOKUP($A66, RawData!$A:$AJ, 13, FALSE) -> 0.347 | T66: =VLOOKUP($A66, RawData!$A:$AJ, 14, FALSE) -> -0.10776398 | U66: =VLOOKUP($A66, RawData!$A:$AJ, 23, FALSE) -> 0.0089 | V66: =VLOOKUP($A66, RawData!$A:$AJ, 24, FALSE) | W66: =VLOOKUP($A66, RawData!$A:$AJ, 25, FALSE) | X66: =VLOOKUP($A66, RawData!$A:$AJ, 26, FALSE) -> 582.80383 | Y66: =VLOOKUP($A66, RawData!$A:$AJ, 27, FALSE) -> 895.097 | Z66: =VLOOKUP($A66, RawData!$A:$AJ, 28, FALSE) -> 5.5447016 | AA66: =VLOOKUP($A66, RawData!$A:$AJ, 31, FALSE) -> 330.2104 | AB66: =VLOOKUP($A66, RawData!$A:$AJ,32, FALSE) | AC66: =VLOOKUP($A66, RawData!$A:$AJ, 34, FALSE) -> 114.583 | AD66: =VLOOKUP($A66, RawData!$A:$AJ, 35, FALSE) -> 6.03 | AE66: =VLOOKUP($A66, RawData!$A:$AJ, 36, FALSE) -> 20.2
A67: RDNW | B67: RideNow | C67: Medium | D67: [READ PITCH](https://community.microcapclub.com/forums/topic/2131-rumbleon-inc-rmbl/#comment-49046) | E67: =IFERROR(__xludf.DUMMYFUNCTION("IFERROR(HYPERLINK(REGEXEXTRACT(D67,""\(([^)]*)\)""),REGEXEXTRACT(D67,""\[([^\]]+)\]"")),"""") "),"READ PITCH") -> READ PITCH | F67: =VLOOKUP($A67, RawData!$A:$AJ, 33, FALSE) -> 224.2176 | G67: =VLOOKUP($A67, RawData!$A:$AJ, 2, FALSE) | H67: =VLOOKUP($A67, RawData!$A:$AJ, 3, FALSE) -> -0.1244 | I67: =VLOOKUP($A67, RawData!$A:$AJ, 4, FALSE) -> 0.18299134 | J67: =VLOOKUP($A67, RawData!$A:$AM, 37, FALSE) -> -35.1 | K67: =VLOOKUP($A67, RawData!$A:$AM, 38, FALSE) | L67: =VLOOKUP($A67, RawData!$A:$AM, 39, FALSE) -> 0.06251342 | M67: =VLOOKUP($A67, RawData!$A:$AJ, 30, FALSE) -> -18.016914 | N67: =VLOOKUP($A67, RawData!$A:$AJ, 5, FALSE) -> -2.679275 | O67: =VLOOKUP($A67, RawData!$A:$AJ, 6, FALSE) -> -0.46464 | P67: =VLOOKUP($A67, RawData!$A:$AJ, 7, FALSE) | Q67: =VLOOKUP($A67, RawData!$A:$AJ, 8, FALSE) -> 0.269 | R67: =VLOOKUP($A67, RawData!$A:$AJ, 11, FALSE) | S67: =VLOOKUP($A67, RawData!$A:$AJ, 13, FALSE) -> 40 | T67: =VLOOKUP($A67, RawData!$A:$AJ, 14, FALSE) -> 0.97205347 | U67: =VLOOKUP($A67, RawData!$A:$AJ, 23, FALSE) -> -0.1404 | V67: =VLOOKUP($A67, RawData!$A:$AJ, 24, FALSE) | W67: =VLOOKUP($A67, RawData!$A:$AJ, 25, FALSE) | X67: =VLOOKUP($A67, RawData!$A:$AJ, 26, FALSE) | Y67: =VLOOKUP($A67, RawData!$A:$AJ, 27, FALSE) | Z67: =VLOOKUP($A67, RawData!$A:$AJ, 28, FALSE) -> 0.20543617 | AA67: =VLOOKUP($A67, RawData!$A:$AJ, 31, FALSE) -> 15.809842 | AB67: =VLOOKUP($A67, RawData!$A:$AJ,32, FALSE) | AC67: =VLOOKUP($A67, RawData!$A:$AJ, 34, FALSE) -> 632.3937 | AD67: =VLOOKUP($A67, RawData!$A:$AJ, 35, FALSE) -> 5.91 | AE67: =VLOOKUP($A67, RawData!$A:$AJ, 36, FALSE) -> 38.07
A68: ZDGE | B68: Zedge | C68: Medium | D68: [READ PITCH](https://community.microcapclub.com/forums/topic/1531-zedge-zdge/) | E68: =IFERROR(__xludf.DUMMYFUNCTION("IFERROR(HYPERLINK(REGEXEXTRACT(D68,""\(([^)]*)\)""),REGEXEXTRACT(D68,""\[([^\]]+)\]"")),"""") "),"READ PITCH") -> READ PITCH | F68: =VLOOKUP($A68, RawData!$A:$AJ, 33, FALSE) -> 48.78874 | G68: =VLOOKUP($A68, RawData!$A:$AJ, 2, FALSE) | H68: =VLOOKUP($A68, RawData!$A:$AJ, 3, FALSE) -> -0.0129 | I68: =VLOOKUP($A68, RawData!$A:$AJ, 4, FALSE) -> 0.21632099 | J68: =VLOOKUP($A68, RawData!$A:$AM, 37, FALSE) -> -0.429 | K68: =VLOOKUP($A68, RawData!$A:$AM, 38, FALSE) | L68: =VLOOKUP($A68, RawData!$A:$AM, 39, FALSE) -> 0.5115977 | M68: =VLOOKUP($A68, RawData!$A:$AJ, 30, FALSE) -> -73.552444 | N68: =VLOOKUP($A68, RawData!$A:$AJ, 5, FALSE) -> -0.09730769 | O68: =VLOOKUP($A68, RawData!$A:$AJ, 6, FALSE) -> -0.866772 | P68: =VLOOKUP($A68, RawData!$A:$AJ, 7, FALSE) | Q68: =VLOOKUP($A68, RawData!$A:$AJ, 8, FALSE) -> 0.9351 | R68: =VLOOKUP($A68, RawData!$A:$AJ, 11, FALSE) | S68: =VLOOKUP($A68, RawData!$A:$AJ, 13, FALSE) -> 2.5 | T68: =VLOOKUP($A68, RawData!$A:$AJ, 14, FALSE) -> 0.51503915 | U68: =VLOOKUP($A68, RawData!$A:$AJ, 23, FALSE) -> -0.0345 | V68: =VLOOKUP($A68, RawData!$A:$AJ, 24, FALSE) | W68: =VLOOKUP($A68, RawData!$A:$AJ, 25, FALSE) | X68: =VLOOKUP($A68, RawData!$A:$AJ, 26, FALSE) | Y68: =VLOOKUP($A68, RawData!$A:$AJ, 27, FALSE) -> 34.653465 | Z68: =VLOOKUP($A68, RawData!$A:$AJ, 28, FALSE) -> 1.6787416 | AA68: =VLOOKUP($A68, RawData!$A:$AJ, 31, FALSE) -> 12.6216 | AB68: =VLOOKUP($A68, RawData!$A:$AJ,32, FALSE) | AC68: =VLOOKUP($A68, RawData!$A:$AJ, 34, FALSE) -> 31.554 | AD68: =VLOOKUP($A68, RawData!$A:$AJ, 35, FALSE) -> 3.85 | AE68: =VLOOKUP($A68, RawData!$A:$AJ, 36, FALSE) -> 13
A69: PAYS | B69: Paysign | C69: Medium High | D69: [READ PITCH](https://community.microcapclub.com/forums/topic/2116-paysign-inc-pays/#comment-48669) | E69: =IFERROR(__xludf.DUMMYFUNCTION("IFERROR(HYPERLINK(REGEXEXTRACT(D69,""\(([^)]*)\)""),REGEXEXTRACT(D69,""\[([^\]]+)\]"")),"""") "),"READ PITCH") -> READ PITCH | F69: =VLOOKUP($A69, RawData!$A:$AJ, 33, FALSE) -> 270.811 | G69: =VLOOKUP($A69, RawData!$A:$AJ, 2, FALSE) | H69: =VLOOKUP($A69, RawData!$A:$AJ, 3, FALSE) -> 0.3261 | I69: =VLOOKUP($A69, RawData!$A:$AJ, 4, FALSE) -> 0.22969745 | J69: =VLOOKUP($A69, RawData!$A:$AM, 37, FALSE) -> 2.92351 | K69: =VLOOKUP($A69, RawData!$A:$AM, 38, FALSE) | L69: =VLOOKUP($A69, RawData!$A:$AM, 39, FALSE) -> 0.019071344 | M69: =VLOOKUP($A69, RawData!$A:$AJ, 30, FALSE) -> 88.3841 | N69: =VLOOKUP($A69, RawData!$A:$AJ, 5, FALSE) -> 0.13738863 | O69: =VLOOKUP($A69, RawData!$A:$AJ, 6, FALSE) -> -0.06324505 | P69: =VLOOKUP($A69, RawData!$A:$AJ, 7, FALSE) | Q69: =VLOOKUP($A69, RawData!$A:$AJ, 8, FALSE) -> 0.5982 | R69: =VLOOKUP($A69, RawData!$A:$AJ, 11, FALSE) | S69: =VLOOKUP($A69, RawData!$A:$AJ, 13, FALSE) -> 9.84225 | T69: =VLOOKUP($A69, RawData!$A:$AJ, 14, FALSE) -> 0.42919394 | U69: =VLOOKUP($A69, RawData!$A:$AJ, 23, FALSE) -> 0.0384 | V69: =VLOOKUP($A69, RawData!$A:$AJ, 24, FALSE) | W69: =VLOOKUP($A69, RawData!$A:$AJ, 25, FALSE) | X69: =VLOOKUP($A69, RawData!$A:$AJ, 26, FALSE) -> 34.93739 | Y69: =VLOOKUP($A69, RawData!$A:$AJ, 27, FALSE) -> 37.274315 | Z69: =VLOOKUP($A69, RawData!$A:$AJ, 28, FALSE) -> 3.5282333 | AA69: =VLOOKUP($A69, RawData!$A:$AJ, 31, FALSE) -> 26.253326 | AB69: =VLOOKUP($A69, RawData!$A:$AJ,32, FALSE) | AC69: =VLOOKUP($A69, RawData!$A:$AJ, 34, FALSE) -> 258.3918 | AD69: =VLOOKUP($A69, RawData!$A:$AJ, 35, FALSE) -> 4.8 | AE69: =VLOOKUP($A69, RawData!$A:$AJ, 36, FALSE) -> 55.04
A70: NTWK | B70: NetSol Technologies | C70: Medium (old) | D70: [READ PITCH](https://community.microcapclub.com/forums/topic/1080-netsol-technologies-ntwk/#comment-23493) | E70: =IFERROR(__xludf.DUMMYFUNCTION("IFERROR(HYPERLINK(REGEXEXTRACT(D70,""\(([^)]*)\)""),REGEXEXTRACT(D70,""\[([^\]]+)\]"")),"""") "),"READ PITCH") -> READ PITCH | F70: =VLOOKUP($A70, RawData!$A:$AJ, 33, FALSE) -> 37.39578 | G70: =VLOOKUP($A70, RawData!$A:$AJ, 2, FALSE) | H70: =VLOOKUP($A70, RawData!$A:$AJ, 3, FALSE) -> 0.077 | I70: =VLOOKUP($A70, RawData!$A:$AJ, 4, FALSE) -> 0.03701771 | J70: =VLOOKUP($A70, RawData!$A:$AM, 37, FALSE) -> 3.95398 | K70: =VLOOKUP($A70, RawData!$A:$AM, 38, FALSE) | L70: =VLOOKUP($A70, RawData!$A:$AM, 39, FALSE) -> -0.09657143 | M70: =VLOOKUP($A70, RawData!$A:$AJ, 30, FALSE) -> 5.764268 | N70: =VLOOKUP($A70, RawData!$A:$AJ, 5, FALSE) -> 0.041961864 | O70: =VLOOKUP($A70, RawData!$A:$AJ, 6, FALSE) -> -0.31589273 | P70: =VLOOKUP($A70, RawData!$A:$AJ, 7, FALSE) | Q70: =VLOOKUP($A70, RawData!$A:$AJ, 8, FALSE) -> 0.48 | R70: =VLOOKUP($A70, RawData!$A:$AJ, 11, FALSE) | S70: =VLOOKUP($A70, RawData!$A:$AJ, 13, FALSE) -> -1.53423 | T70: =VLOOKUP($A70, RawData!$A:$AJ, 14, FALSE) -> -0.23527527 | U70: =VLOOKUP($A70, RawData!$A:$AJ, 23, FALSE) -> 0.0082 | V70: =VLOOKUP($A70, RawData!$A:$AJ, 24, FALSE) | W70: =VLOOKUP($A70, RawData!$A:$AJ, 25, FALSE) | X70: =VLOOKUP($A70, RawData!$A:$AJ, 26, FALSE) -> 74.59154 | Y70: =VLOOKUP($A70, RawData!$A:$AJ, 27, FALSE) | Z70: =VLOOKUP($A70, RawData!$A:$AJ, 28, FALSE) -> 0.5553851 | AA70: =VLOOKUP($A70, RawData!$A:$AJ, 31, FALSE) -> -14.85553 | AB70: =VLOOKUP($A70, RawData!$A:$AJ,32, FALSE) | AC70: =VLOOKUP($A70, RawData!$A:$AJ, 34, FALSE) -> 22.7918 | AD70: =VLOOKUP($A70, RawData!$A:$AJ, 35, FALSE) -> 3.13 | AE70: =VLOOKUP($A70, RawData!$A:$AJ, 36, FALSE) -> 11.8
A71: DAIO | B71: Data I/O | C71: Medium High | D71: [READ PITCH](https://community.microcapclub.com/forums/topic/1696-data-io-corporation-daio/#comment-38382) | E71: =IFERROR(__xludf.DUMMYFUNCTION("IFERROR(HYPERLINK(REGEXEXTRACT(D71,""\(([^)]*)\)""),REGEXEXTRACT(D71,""\[([^\]]+)\]"")),"""") "),"READ PITCH") -> READ PITCH | F71: =VLOOKUP($A71, RawData!$A:$AJ, 33, FALSE) -> 29.565647 | G71: =VLOOKUP($A71, RawData!$A:$AJ, 2, FALSE) | H71: =VLOOKUP($A71, RawData!$A:$AJ, 3, FALSE) -> -0.2858 | I71: =VLOOKUP($A71, RawData!$A:$AJ, 4, FALSE) -> -0.04661085 | J71: =VLOOKUP($A71, RawData!$A:$AM, 37, FALSE) -> -3.418 | K71: =VLOOKUP($A71, RawData!$A:$AM, 38, FALSE) | L71: =VLOOKUP($A71, RawData!$A:$AM, 39, FALSE) -> 0.25224647 | M71: =VLOOKUP($A71, RawData!$A:$AJ, 30, FALSE) -> -5.9637213 | N71: =VLOOKUP($A71, RawData!$A:$AJ, 5, FALSE) -> -0.39062834 | O71: =VLOOKUP($A71, RawData!$A:$AJ, 6, FALSE) -> 1.06881 | P71: =VLOOKUP($A71, RawData!$A:$AJ, 7, FALSE) | Q71: =VLOOKUP($A71, RawData!$A:$AJ, 8, FALSE) -> 0.515 | R71: =VLOOKUP($A71, RawData!$A:$AJ, 11, FALSE) | S71: =VLOOKUP($A71, RawData!$A:$AJ, 13, FALSE) -> -2.67 | T71: =VLOOKUP($A71, RawData!$A:$AJ, 14, FALSE) -> -4.917127 | U71: =VLOOKUP($A71, RawData!$A:$AJ, 23, FALSE) -> -0.1524 | V71: =VLOOKUP($A71, RawData!$A:$AJ, 24, FALSE) | W71: =VLOOKUP($A71, RawData!$A:$AJ, 25, FALSE) | X71: =VLOOKUP($A71, RawData!$A:$AJ, 26, FALSE) | Y71: =VLOOKUP($A71, RawData!$A:$AJ, 27, FALSE) | Z71: =VLOOKUP($A71, RawData!$A:$AJ, 28, FALSE) -> 1.7934822 | AA71: =VLOOKUP($A71, RawData!$A:$AJ, 31, FALSE) -> -7.634457 | AB71: =VLOOKUP($A71, RawData!$A:$AJ,32, FALSE) | AC71: =VLOOKUP($A71, RawData!$A:$AJ, 34, FALSE) -> 20.384 | AD71: =VLOOKUP($A71, RawData!$A:$AJ, 35, FALSE) -> 3.2 | AE71: =VLOOKUP($A71, RawData!$A:$AJ, 36, FALSE) -> 9.39
A72: SPRS | B72: Surge Components | C72: Lowest | D72: [READ PITCH](https://community.microcapclub.com/forums/topic/3749-surge-components-sprs/#comment-81511) | E72: =IFERROR(__xludf.DUMMYFUNCTION("IFERROR(HYPERLINK(REGEXEXTRACT(D72,""\(([^)]*)\)""),REGEXEXTRACT(D72,""\[([^\]]+)\]"")),"""") "),"READ PITCH") -> READ PITCH | F72: =VLOOKUP($A72, RawData!$A:$AJ, 33, FALSE) -> 18.889282 | G72: =VLOOKUP($A72, RawData!$A:$AJ, 2, FALSE) | H72: =VLOOKUP($A72, RawData!$A:$AJ, 3, FALSE) -> 0.1601 | I72: =VLOOKUP($A72, RawData!$A:$AJ, 4, FALSE) -> 0.035382215 | J72: =VLOOKUP($A72, RawData!$A:$AM, 37, FALSE) -> 1.12799 | K72: =VLOOKUP($A72, RawData!$A:$AM, 38, FALSE) | L72: =VLOOKUP($A72, RawData!$A:$AM, 39, FALSE) -> 0.031818487 | M72: =VLOOKUP($A72, RawData!$A:$AJ, 30, FALSE) -> 13.116783 | N72: =VLOOKUP($A72, RawData!$A:$AJ, 5, FALSE) -> 0.1581296 | O72: =VLOOKUP($A72, RawData!$A:$AJ, 6, FALSE) -> 0.8438228 | P72: =VLOOKUP($A72, RawData!$A:$AJ, 7, FALSE) | Q72: =VLOOKUP($A72, RawData!$A:$AJ, 8, FALSE) -> 0.2822 | R72: =VLOOKUP($A72, RawData!$A:$AJ, 11, FALSE) | S72: =VLOOKUP($A72, RawData!$A:$AJ, 13, FALSE) -> 0.93553 | T72: =VLOOKUP($A72, RawData!$A:$AJ, 14, FALSE) -> 0.5041196 | U72: =VLOOKUP($A72, RawData!$A:$AJ, 23, FALSE) -> 0.0347 | V72: =VLOOKUP($A72, RawData!$A:$AJ, 24, FALSE) | W72: =VLOOKUP($A72, RawData!$A:$AJ, 25, FALSE) | X72: =VLOOKUP($A72, RawData!$A:$AJ, 26, FALSE) -> 21.121916 | Y72: =VLOOKUP($A72, RawData!$A:$AJ, 27, FALSE) -> No data | Z72: =VLOOKUP($A72, RawData!$A:$AJ, 28, FALSE) -> 0.5408086 | AA72: =VLOOKUP($A72, RawData!$A:$AJ, 31, FALSE) -> 15.815207 | AB72: =VLOOKUP($A72, RawData!$A:$AJ,32, FALSE) | AC72: =VLOOKUP($A72, RawData!$A:$AJ, 34, FALSE) -> 14.7956 | AD72: =VLOOKUP($A72, RawData!$A:$AJ, 35, FALSE) -> 3.35 | AE72: =VLOOKUP($A72, RawData!$A:$AJ, 36, FALSE) -> 5.71
A73: LTRX | B73: Lantronix | C73: Low Medium | D73: [READ PITCH](https://community.microcapclub.com/forums/topic/2529-lantronix-ltrx/#comment-58321) | E73: =IFERROR(__xludf.DUMMYFUNCTION("IFERROR(HYPERLINK(REGEXEXTRACT(D73,""\(([^)]*)\)""),REGEXEXTRACT(D73,""\[([^\]]+)\]"")),"""") "),"READ PITCH") -> READ PITCH | F73: =VLOOKUP($A73, RawData!$A:$AJ, 33, FALSE) -> 247.17206 | G73: =VLOOKUP($A73, RawData!$A:$AJ, 2, FALSE) | H73: =VLOOKUP($A73, RawData!$A:$AJ, 3, FALSE) -> -0.2685 | I73: =VLOOKUP($A73, RawData!$A:$AJ, 4, FALSE) -> 0.1297019 | J73: =VLOOKUP($A73, RawData!$A:$AM, 37, FALSE) -> -1.699 | K73: =VLOOKUP($A73, RawData!$A:$AM, 38, FALSE) | L73: =VLOOKUP($A73, RawData!$A:$AM, 39, FALSE) -> -0.0047577 | M73: =VLOOKUP($A73, RawData!$A:$AJ, 30, FALSE) -> -142.63861 | N73: =VLOOKUP($A73, RawData!$A:$AJ, 5, FALSE) -> -0.2609756 | O73: =VLOOKUP($A73, RawData!$A:$AJ, 6, FALSE) -> 1.0015589 | P73: =VLOOKUP($A73, RawData!$A:$AJ, 7, FALSE) | Q73: =VLOOKUP($A73, RawData!$A:$AJ, 8, FALSE) -> 0.4275 | R73: =VLOOKUP($A73, RawData!$A:$AJ, 11, FALSE) | S73: =VLOOKUP($A73, RawData!$A:$AJ, 13, FALSE) -> 7.805 | T73: =VLOOKUP($A73, RawData!$A:$AJ, 14, FALSE) -> 0.61748415 | U73: =VLOOKUP($A73, RawData!$A:$AJ, 23, FALSE) -> -0.0819 | V73: =VLOOKUP($A73, RawData!$A:$AJ, 24, FALSE) | W73: =VLOOKUP($A73, RawData!$A:$AJ, 25, FALSE) | X73: =VLOOKUP($A73, RawData!$A:$AJ, 26, FALSE) | Y73: =VLOOKUP($A73, RawData!$A:$AJ, 27, FALSE) -> 33.281734 | Z73: =VLOOKUP($A73, RawData!$A:$AJ, 28, FALSE) -> 2.1461105 | AA73: =VLOOKUP($A73, RawData!$A:$AJ, 31, FALSE) -> 31.049711 | AB73: =VLOOKUP($A73, RawData!$A:$AJ,32, FALSE) | AC73: =VLOOKUP($A73, RawData!$A:$AJ, 34, FALSE) -> 242.343 | AD73: =VLOOKUP($A73, RawData!$A:$AJ, 35, FALSE) -> 6.45 | AE73: =VLOOKUP($A73, RawData!$A:$AJ, 36, FALSE) -> 39.36
A74: POLA | B74: Polar Power | C74: Medium (old) | D74: [READ PITCH](https://community.microcapclub.com/forums/topic/1852-polar-power-pola/#comment-42282) | E74: =IFERROR(__xludf.DUMMYFUNCTION("IFERROR(HYPERLINK(REGEXEXTRACT(D74,""\(([^)]*)\)""),REGEXEXTRACT(D74,""\[([^\]]+)\]"")),"""") "),"READ PITCH") -> READ PITCH | F74: =VLOOKUP($A74, RawData!$A:$AJ, 33, FALSE) -> 5.2644444 | G74: =VLOOKUP($A74, RawData!$A:$AJ, 2, FALSE) | H74: =VLOOKUP($A74, RawData!$A:$AJ, 3, FALSE) -> -0.4432 | I74: =VLOOKUP($A74, RawData!$A:$AJ, 4, FALSE) -> 0.024693035 | J74: =VLOOKUP($A74, RawData!$A:$AM, 37, FALSE) -> -8.123 | K74: =VLOOKUP($A74, RawData!$A:$AM, 38, FALSE) | L74: =VLOOKUP($A74, RawData!$A:$AM, 39, FALSE) -> -0.094450645 | M74: =VLOOKUP($A74, RawData!$A:$AJ, 30, FALSE) -> -1.2827089 | N74: =VLOOKUP($A74, RawData!$A:$AJ, 5, FALSE) -> -3.2593985 | O74: =VLOOKUP($A74, RawData!$A:$AJ, 6, FALSE) -> 0.8126699 | P74: =VLOOKUP($A74, RawData!$A:$AJ, 7, FALSE) | Q74: =VLOOKUP($A74, RawData!$A:$AJ, 8, FALSE) -> -0.3063 | R74: =VLOOKUP($A74, RawData!$A:$AJ, 11, FALSE) | S74: =VLOOKUP($A74, RawData!$A:$AJ, 13, FALSE) -> -0.726 | T74: =VLOOKUP($A74, RawData!$A:$AJ, 14, FALSE) -> 0.9404145 | U74: =VLOOKUP($A74, RawData!$A:$AJ, 23, FALSE) -> -0.5502 | V74: =VLOOKUP($A74, RawData!$A:$AJ, 24, FALSE) | W74: =VLOOKUP($A74, RawData!$A:$AJ, 25, FALSE) | X74: =VLOOKUP($A74, RawData!$A:$AJ, 26, FALSE) | Y74: =VLOOKUP($A74, RawData!$A:$AJ, 27, FALSE) | Z74: =VLOOKUP($A74, RawData!$A:$AJ, 28, FALSE) -> 0.63228977 | AA74: =VLOOKUP($A74, RawData!$A:$AJ, 31, FALSE) -> -14.351851 | AB74: =VLOOKUP($A74, RawData!$A:$AJ,32, FALSE) | AC74: =VLOOKUP($A74, RawData!$A:$AJ, 34, FALSE) -> 10.419444 | AD74: =VLOOKUP($A74, RawData!$A:$AJ, 35, FALSE) -> 1.49 | AE74: =VLOOKUP($A74, RawData!$A:$AJ, 36, FALSE) -> 2.66
A75: BLIN | B75: Bridgeline Digital | C75: Medium (old) | D75: [READ PITCH](https://community.microcapclub.com/forums/topic/419-bridgeline-digital-blin/) | E75: =IFERROR(__xludf.DUMMYFUNCTION("IFERROR(HYPERLINK(REGEXEXTRACT(D75,""\(([^)]*)\)""),REGEXEXTRACT(D75,""\[([^\]]+)\]"")),"""") "),"READ PITCH") -> READ PITCH | F75: =VLOOKUP($A75, RawData!$A:$AJ, 33, FALSE) -> 9.77952 | G75: =VLOOKUP($A75, RawData!$A:$AJ, 2, FALSE) | H75: =VLOOKUP($A75, RawData!$A:$AJ, 3, FALSE) -> 0.0016 | I75: =VLOOKUP($A75, RawData!$A:$AJ, 4, FALSE) -> 0.07141433 | J75: =VLOOKUP($A75, RawData!$A:$AM, 37, FALSE) -> -0.946 | K75: =VLOOKUP($A75, RawData!$A:$AM, 38, FALSE) | L75: =VLOOKUP($A75, RawData!$A:$AM, 39, FALSE) -> -0.41584945 | M75: =VLOOKUP($A75, RawData!$A:$AJ, 30, FALSE) -> -9.051501 | N75: =VLOOKUP($A75, RawData!$A:$AJ, 5, FALSE) -> -0.21345995 | O75: =VLOOKUP($A75, RawData!$A:$AJ, 6, FALSE) -> -0.7305046 | P75: =VLOOKUP($A75, RawData!$A:$AJ, 7, FALSE) | Q75: =VLOOKUP($A75, RawData!$A:$AJ, 8, FALSE) -> 0.6657 | R75: =VLOOKUP($A75, RawData!$A:$AJ, 11, FALSE) | S75: =VLOOKUP($A75, RawData!$A:$AJ, 13, FALSE) -> -0.559 | T75: =VLOOKUP($A75, RawData!$A:$AJ, 14, FALSE) -> 0.51568264 | U75: =VLOOKUP($A75, RawData!$A:$AJ, 23, FALSE) -> -0.1573 | V75: =VLOOKUP($A75, RawData!$A:$AJ, 24, FALSE) | W75: =VLOOKUP($A75, RawData!$A:$AJ, 25, FALSE) | X75: =VLOOKUP($A75, RawData!$A:$AJ, 26, FALSE) | Y75: =VLOOKUP($A75, RawData!$A:$AJ, 27, FALSE) | Z75: =VLOOKUP($A75, RawData!$A:$AJ, 28, FALSE) -> 0.67107123 | AA75: =VLOOKUP($A75, RawData!$A:$AJ, 31, FALSE) -> -15.317925 | AB75: =VLOOKUP($A75, RawData!$A:$AJ,32, FALSE) | AC75: =VLOOKUP($A75, RawData!$A:$AJ, 34, FALSE) -> 8.56272 | AD75: =VLOOKUP($A75, RawData!$A:$AJ, 35, FALSE) -> 0.852 | AE75: =VLOOKUP($A75, RawData!$A:$AJ, 36, FALSE) -> 12.11
A76: AMPG | B76: AmpliTech Group | C76: Medium (old) | D76: [READ PITCH](https://community.microcapclub.com/forums/topic/1795-amplitech-group-ampg/#comment-40429) | E76: =IFERROR(__xludf.DUMMYFUNCTION("IFERROR(HYPERLINK(REGEXEXTRACT(D76,""\(([^)]*)\)""),REGEXEXTRACT(D76,""\[([^\]]+)\]"")),"""") "),"READ PITCH") -> READ PITCH | F76: =VLOOKUP($A76, RawData!$A:$AJ, 33, FALSE) -> 64.11759 | G76: =VLOOKUP($A76, RawData!$A:$AJ, 2, FALSE) | H76: =VLOOKUP($A76, RawData!$A:$AJ, 3, FALSE) -> 0.9347 | I76: =VLOOKUP($A76, RawData!$A:$AJ, 4, FALSE) -> 0.43794656 | J76: =VLOOKUP($A76, RawData!$A:$AM, 37, FALSE) -> -6.69496 | K76: =VLOOKUP($A76, RawData!$A:$AM, 38, FALSE) | L76: =VLOOKUP($A76, RawData!$A:$AM, 39, FALSE) -> 0.84518844 | M76: =VLOOKUP($A76, RawData!$A:$AJ, 30, FALSE) -> -10.314636 | N76: =VLOOKUP($A76, RawData!$A:$AJ, 5, FALSE) -> -0.36927375 | O76: =VLOOKUP($A76, RawData!$A:$AJ, 6, FALSE) -> -0.04057577 | P76: =VLOOKUP($A76, RawData!$A:$AJ, 7, FALSE) | Q76: =VLOOKUP($A76, RawData!$A:$AJ, 8, FALSE) -> 0.2307 | R76: =VLOOKUP($A76, RawData!$A:$AJ, 11, FALSE) | S76: =VLOOKUP($A76, RawData!$A:$AJ, 13, FALSE) -> -8.61305 | T76: =VLOOKUP($A76, RawData!$A:$AJ, 14, FALSE) -> 1.4593937 | U76: =VLOOKUP($A76, RawData!$A:$AJ, 23, FALSE) -> -0.1683 | V76: =VLOOKUP($A76, RawData!$A:$AJ, 24, FALSE) | W76: =VLOOKUP($A76, RawData!$A:$AJ, 25, FALSE) | X76: =VLOOKUP($A76, RawData!$A:$AJ, 26, FALSE) | Y76: =VLOOKUP($A76, RawData!$A:$AJ, 27, FALSE) | Z76: =VLOOKUP($A76, RawData!$A:$AJ, 28, FALSE) -> 3.429027 | AA76: =VLOOKUP($A76, RawData!$A:$AJ, 31, FALSE) -> -8.017611 | AB76: =VLOOKUP($A76, RawData!$A:$AJ,32, FALSE) | AC76: =VLOOKUP($A76, RawData!$A:$AJ, 34, FALSE) -> 69.05608 | AD76: =VLOOKUP($A76, RawData!$A:$AJ, 35, FALSE) -> 3.75 | AE76: =VLOOKUP($A76, RawData!$A:$AJ, 36, FALSE) -> 20.64
A77: PERF | B77: Perfect Corp | C77: Medium | D77: [READ PITCH](https://community.microcapclub.com/forums/topic/4733-perfect-corp-perf/#comment-94166) | E77: =IFERROR(__xludf.DUMMYFUNCTION("IFERROR(HYPERLINK(REGEXEXTRACT(D77,""\(([^)]*)\)""),REGEXEXTRACT(D77,""\[([^\]]+)\]"")),"""") "),"READ PITCH") -> READ PITCH | F77: =VLOOKUP($A77, RawData!$A:$AJ, 33, FALSE) -> 174.16342 | G77: =VLOOKUP($A77, RawData!$A:$AJ, 2, FALSE) | H77: =VLOOKUP($A77, RawData!$A:$AJ, 3, FALSE) -> 0.1447 | I77: =VLOOKUP($A77, RawData!$A:$AJ, 4, FALSE) -> 0.15145504 | J77: =VLOOKUP($A77, RawData!$A:$AM, 37, FALSE) -> 0.873 | K77: =VLOOKUP($A77, RawData!$A:$AM, 38, FALSE) | L77: =VLOOKUP($A77, RawData!$A:$AM, 39, FALSE) -> -0.96865416 | M77: =VLOOKUP($A77, RawData!$A:$AJ, 30, FALSE) -> 61.197594 | N77: =VLOOKUP($A77, RawData!$A:$AJ, 5, FALSE) -> 0.055719193 | O77: =VLOOKUP($A77, RawData!$A:$AJ, 6, FALSE) -> 0.0655276 | P77: =VLOOKUP($A77, RawData!$A:$AJ, 7, FALSE) | Q77: =VLOOKUP($A77, RawData!$A:$AJ, 8, FALSE) -> 0.7577 | R77: =VLOOKUP($A77, RawData!$A:$AJ, 11, FALSE) | S77: =VLOOKUP($A77, RawData!$A:$AJ, 13, FALSE) -> 13.587 | T77: =VLOOKUP($A77, RawData!$A:$AJ, 14, FALSE) -> 1.4523784 | U77: =VLOOKUP($A77, RawData!$A:$AJ, 23, FALSE) -> 0.0302 | V77: =VLOOKUP($A77, RawData!$A:$AJ, 24, FALSE) | W77: =VLOOKUP($A77, RawData!$A:$AJ, 25, FALSE) | X77: =VLOOKUP($A77, RawData!$A:$AJ, 26, FALSE) -> 31.766432 | Y77: =VLOOKUP($A77, RawData!$A:$AJ, 27, FALSE) -> 29.20792 | Z77: =VLOOKUP($A77, RawData!$A:$AJ, 28, FALSE) -> 2.694646 | AA77: =VLOOKUP($A77, RawData!$A:$AJ, 31, FALSE) -> 3.932104 | AB77: =VLOOKUP($A77, RawData!$A:$AJ,32, FALSE) | AC77: =VLOOKUP($A77, RawData!$A:$AJ, 34, FALSE) -> 53.4255 | AD77: =VLOOKUP($A77, RawData!$A:$AJ, 35, FALSE) -> 1.77 | AE77: =VLOOKUP($A77, RawData!$A:$AJ, 36, FALSE) -> 101.85
A78: CREX | B78: Creative Realities | C78: Medium | D78: [READ PITCH](https://community.microcapclub.com/forums/topic/3900-creative-realities-crex/#comment-83161) | E78: =IFERROR(__xludf.DUMMYFUNCTION("IFERROR(HYPERLINK(REGEXEXTRACT(D78,""\(([^)]*)\)""),REGEXEXTRACT(D78,""\[([^\]]+)\]"")),"""") "),"READ PITCH") -> READ PITCH | F78: =VLOOKUP($A78, RawData!$A:$AJ, 33, FALSE) -> 32.924255 | G78: =VLOOKUP($A78, RawData!$A:$AJ, 2, FALSE) | H78: =VLOOKUP($A78, RawData!$A:$AJ, 3, FALSE) -> -0.1837 | I78: =VLOOKUP($A78, RawData!$A:$AJ, 4, FALSE) -> 0.19030169 | J78: =VLOOKUP($A78, RawData!$A:$AM, 37, FALSE) -> -0.79 | K78: =VLOOKUP($A78, RawData!$A:$AM, 38, FALSE) | L78: =VLOOKUP($A78, RawData!$A:$AM, 39, FALSE) -> -0.4308674 | M78: =VLOOKUP($A78, RawData!$A:$AJ, 30, FALSE) -> -69.33747 | N78: =VLOOKUP($A78, RawData!$A:$AJ, 5, FALSE) -> -0.8696768 | O78: =VLOOKUP($A78, RawData!$A:$AJ, 6, FALSE) -> -13.214953 | P78: =VLOOKUP($A78, RawData!$A:$AJ, 7, FALSE) | Q78: =VLOOKUP($A78, RawData!$A:$AJ, 8, FALSE) -> 0.4313 | R78: =VLOOKUP($A78, RawData!$A:$AJ, 11, FALSE) | S78: =VLOOKUP($A78, RawData!$A:$AJ, 13, FALSE) -> -4.675 | T78: =VLOOKUP($A78, RawData!$A:$AJ, 14, FALSE) -> 2.9588609 | U78: =VLOOKUP($A78, RawData!$A:$AJ, 23, FALSE) -> -0.1423 | V78: =VLOOKUP($A78, RawData!$A:$AJ, 24, FALSE) | W78: =VLOOKUP($A78, RawData!$A:$AJ, 25, FALSE) | X78: =VLOOKUP($A78, RawData!$A:$AJ, 26, FALSE) | Y78: =VLOOKUP($A78, RawData!$A:$AJ, 27, FALSE) | Z78: =VLOOKUP($A78, RawData!$A:$AJ, 28, FALSE) -> 0.74290097 | AA78: =VLOOKUP($A78, RawData!$A:$AJ, 31, FALSE) -> -11.71692 | AB78: =VLOOKUP($A78, RawData!$A:$AJ,32, FALSE) | AC78: =VLOOKUP($A78, RawData!$A:$AJ, 34, FALSE) -> 54.7766 | AD78: =VLOOKUP($A78, RawData!$A:$AJ, 35, FALSE) -> 3.13 | AE78: =VLOOKUP($A78, RawData!$A:$AJ, 36, FALSE) -> 10.52
A79: ZENV | B79: Zenvia | C79: Lowest | D79: [READ PITCH](https://community.microcapclub.com/forums/topic/3273-zentek-zenv-zenyfotc/#comment-73991) | E79: =IFERROR(__xludf.DUMMYFUNCTION("IFERROR(HYPERLINK(REGEXEXTRACT(D79,""\(([^)]*)\)""),REGEXEXTRACT(D79,""\[([^\]]+)\]"")),"""") "),"READ PITCH") -> READ PITCH | F79: =VLOOKUP($A79, RawData!$A:$AJ, 33, FALSE) -> 52.567287 | G79: =VLOOKUP($A79, RawData!$A:$AJ, 2, FALSE) | H79: =VLOOKUP($A79, RawData!$A:$AJ, 3, FALSE) -> 0.248 | I79: =VLOOKUP($A79, RawData!$A:$AJ, 4, FALSE) -> 0.43559247 | J79: =VLOOKUP($A79, RawData!$A:$AM, 37, FALSE) -> -1.444 | K79: =VLOOKUP($A79, RawData!$A:$AM, 38, FALSE) | L79: =VLOOKUP($A79, RawData!$A:$AM, 39, FALSE) -> -0.06630851 | M79: =VLOOKUP($A79, RawData!$A:$AJ, 30, FALSE) -> -226.73402 | N79: =VLOOKUP($A79, RawData!$A:$AJ, 5, FALSE) -> -2.2933233 | O79: =VLOOKUP($A79, RawData!$A:$AJ, 6, FALSE) -> 0.043592673 | P79: =VLOOKUP($A79, RawData!$A:$AJ, 7, FALSE) | Q79: =VLOOKUP($A79, RawData!$A:$AJ, 8, FALSE) -> 0.2227 | R79: =VLOOKUP($A79, RawData!$A:$AJ, 11, FALSE) | S79: =VLOOKUP($A79, RawData!$A:$AJ, 13, FALSE) -> 41.702 | T79: =VLOOKUP($A79, RawData!$A:$AJ, 14, FALSE) -> -1.4890913 | U79: =VLOOKUP($A79, RawData!$A:$AJ, 23, FALSE) -> -0.0688 | V79: =VLOOKUP($A79, RawData!$A:$AJ, 24, FALSE) | W79: =VLOOKUP($A79, RawData!$A:$AJ, 25, FALSE) | X79: =VLOOKUP($A79, RawData!$A:$AJ, 26, FALSE) | Y79: =VLOOKUP($A79, RawData!$A:$AJ, 27, FALSE) | Z79: =VLOOKUP($A79, RawData!$A:$AJ, 28, FALSE) -> 0.22863969 | AA79: =VLOOKUP($A79, RawData!$A:$AJ, 31, FALSE) -> 7.8510365 | AB79: =VLOOKUP($A79, RawData!$A:$AJ,32, FALSE) | AC79: =VLOOKUP($A79, RawData!$A:$AJ, 34, FALSE) -> 60.701176 | AD79: =VLOOKUP($A79, RawData!$A:$AJ, 35, FALSE) -> 0.885 | AE79: =VLOOKUP($A79, RawData!$A:$AJ, 36, FALSE) -> 52.57
A80: EFOI | B80: Energy Focus | C80: Low Medium (old) | D80: [READ PITCH](https://community.microcapclub.com/forums/topic/2649-energy-focus-efoi/#comment-61924) | E80: =IFERROR(__xludf.DUMMYFUNCTION("IFERROR(HYPERLINK(REGEXEXTRACT(D80,""\(([^)]*)\)""),REGEXEXTRACT(D80,""\[([^\]]+)\]"")),"""") "),"READ PITCH") -> READ PITCH | F80: =VLOOKUP($A80, RawData!$A:$AJ, 33, FALSE) -> 12.569894 | G80: =VLOOKUP($A80, RawData!$A:$AJ, 2, FALSE) | H80: =VLOOKUP($A80, RawData!$A:$AJ, 3, FALSE) -> -0.3535 | I80: =VLOOKUP($A80, RawData!$A:$AJ, 4, FALSE) -> -0.2530165 | J80: =VLOOKUP($A80, RawData!$A:$AM, 37, FALSE) -> -0.927 | K80: =VLOOKUP($A80, RawData!$A:$AM, 38, FALSE) | L80: =VLOOKUP($A80, RawData!$A:$AM, 39, FALSE) -> -0.26629978 | M80: =VLOOKUP($A80, RawData!$A:$AJ, 30, FALSE) -> -13.274002 | N80: =VLOOKUP($A80, RawData!$A:$AJ, 5, FALSE) -> -0.16811846 | O80: =VLOOKUP($A80, RawData!$A:$AJ, 6, FALSE) -> -0.5484324 | P80: =VLOOKUP($A80, RawData!$A:$AJ, 7, FALSE) | Q80: =VLOOKUP($A80, RawData!$A:$AJ, 8, FALSE) -> 0.1949 | R80: =VLOOKUP($A80, RawData!$A:$AJ, 11, FALSE) | S80: =VLOOKUP($A80, RawData!$A:$AJ, 13, FALSE) -> -0.85 | T80: =VLOOKUP($A80, RawData!$A:$AJ, 14, FALSE) -> 0.72649574 | U80: =VLOOKUP($A80, RawData!$A:$AJ, 23, FALSE) -> -0.1835 | V80: =VLOOKUP($A80, RawData!$A:$AJ, 24, FALSE) | W80: =VLOOKUP($A80, RawData!$A:$AJ, 25, FALSE) | X80: =VLOOKUP($A80, RawData!$A:$AJ, 26, FALSE) | Y80: =VLOOKUP($A80, RawData!$A:$AJ, 27, FALSE) | Z80: =VLOOKUP($A80, RawData!$A:$AJ, 28, FALSE) -> 3.417551 | AA80: =VLOOKUP($A80, RawData!$A:$AJ, 31, FALSE) -> -14.476471 | AB80: =VLOOKUP($A80, RawData!$A:$AJ,32, FALSE) | AC80: =VLOOKUP($A80, RawData!$A:$AJ, 34, FALSE) -> 12.305 | AD80: =VLOOKUP($A80, RawData!$A:$AJ, 35, FALSE) -> 2.3 | AE80: =VLOOKUP($A80, RawData!$A:$AJ, 36, FALSE) -> 5.74
A81: AWRE | B81: Aware, Inc. | C81: Low | D81: [READ PITCH](https://community.microcapclub.com/forums/topic/4504-aware-inc-awre/#comment-90983) | E81: =IFERROR(__xludf.DUMMYFUNCTION("IFERROR(HYPERLINK(REGEXEXTRACT(D81,""\(([^)]*)\)""),REGEXEXTRACT(D81,""\[([^\]]+)\]"")),"""") "),"READ PITCH") -> READ PITCH | F81: =VLOOKUP($A81, RawData!$A:$AJ, 33, FALSE) -> 41.46497 | G81: =VLOOKUP($A81, RawData!$A:$AJ, 2, FALSE) | H81: =VLOOKUP($A81, RawData!$A:$AJ, 3, FALSE) -> 0.0273 | I81: =VLOOKUP($A81, RawData!$A:$AJ, 4, FALSE) -> 0.11028489 | J81: =VLOOKUP($A81, RawData!$A:$AM, 37, FALSE) -> -6.008 | K81: =VLOOKUP($A81, RawData!$A:$AM, 38, FALSE) | L81: =VLOOKUP($A81, RawData!$A:$AM, 39, FALSE) -> -0.07328069 | M81: =VLOOKUP($A81, RawData!$A:$AJ, 30, FALSE) -> -6.6514482 | N81: =VLOOKUP($A81, RawData!$A:$AJ, 5, FALSE) -> -0.26251754 | O81: =VLOOKUP($A81, RawData!$A:$AJ, 6, FALSE) -> -0.25 | P81: =VLOOKUP($A81, RawData!$A:$AJ, 7, FALSE) | Q81: =VLOOKUP($A81, RawData!$A:$AJ, 8, FALSE) -> 0.9202 | R81: =VLOOKUP($A81, RawData!$A:$AJ, 11, FALSE) | S81: =VLOOKUP($A81, RawData!$A:$AJ, 13, FALSE) -> -5.809 | T81: =VLOOKUP($A81, RawData!$A:$AJ, 14, FALSE) -> 7.0583234 | U81: =VLOOKUP($A81, RawData!$A:$AJ, 23, FALSE) -> -0.1391 | V81: =VLOOKUP($A81, RawData!$A:$AJ, 24, FALSE) | W81: =VLOOKUP($A81, RawData!$A:$AJ, 25, FALSE) | X81: =VLOOKUP($A81, RawData!$A:$AJ, 26, FALSE) | Y81: =VLOOKUP($A81, RawData!$A:$AJ, 27, FALSE) | Z81: =VLOOKUP($A81, RawData!$A:$AJ, 28, FALSE) -> 2.2928395 | AA81: =VLOOKUP($A81, RawData!$A:$AJ, 31, FALSE) -> -6.8793077 | AB81: =VLOOKUP($A81, RawData!$A:$AJ,32, FALSE) | AC81: =VLOOKUP($A81, RawData!$A:$AJ, 34, FALSE) -> 39.9619 | AD81: =VLOOKUP($A81, RawData!$A:$AJ, 35, FALSE) -> 1.87 | AE81: =VLOOKUP($A81, RawData!$A:$AJ, 36, FALSE) -> 21.37
A82: NNDM | B82: Nano Dimenstion | C82: Low | D82: [READ PITCH](https://community.microcapclub.com/forums/topic/4804-nano-dimension-ltd-nndm/#comment-95107) | E82: =IFERROR(__xludf.DUMMYFUNCTION("IFERROR(HYPERLINK(REGEXEXTRACT(D82,""\(([^)]*)\)""),REGEXEXTRACT(D82,""\[([^\]]+)\]"")),"""") "),"READ PITCH") -> READ PITCH | F82: =VLOOKUP($A82, RawData!$A:$AJ, 33, FALSE) -> 364.4488 | G82: =VLOOKUP($A82, RawData!$A:$AJ, 2, FALSE) | H82: =VLOOKUP($A82, RawData!$A:$AJ, 3, FALSE) -> 0.4168 | I82: =VLOOKUP($A82, RawData!$A:$AJ, 4, FALSE) -> 0.35547808 | J82: =VLOOKUP($A82, RawData!$A:$AM, 37, FALSE) -> -126.438 | K82: =VLOOKUP($A82, RawData!$A:$AM, 38, FALSE) | L82: =VLOOKUP($A82, RawData!$A:$AM, 39, FALSE) -> -0.19502638 | M82: =VLOOKUP($A82, RawData!$A:$AJ, 30, FALSE) -> -0.03313798 | N82: =VLOOKUP($A82, RawData!$A:$AJ, 5, FALSE) -> -1.2361499 | O82: =VLOOKUP($A82, RawData!$A:$AJ, 6, FALSE) -> 2.0424788 | P82: =VLOOKUP($A82, RawData!$A:$AJ, 7, FALSE) | Q82: =VLOOKUP($A82, RawData!$A:$AJ, 8, FALSE) -> 0.3362 | R82: =VLOOKUP($A82, RawData!$A:$AJ, 11, FALSE) | S82: =VLOOKUP($A82, RawData!$A:$AJ, 13, FALSE) -> -104.1 | T82: =VLOOKUP($A82, RawData!$A:$AJ, 14, FALSE) -> 1.3624228 | U82: =VLOOKUP($A82, RawData!$A:$AJ, 23, FALSE) -> -0.3173 | V82: =VLOOKUP($A82, RawData!$A:$AJ, 24, FALSE) | W82: =VLOOKUP($A82, RawData!$A:$AJ, 25, FALSE) | X82: =VLOOKUP($A82, RawData!$A:$AJ, 26, FALSE) | Y82: =VLOOKUP($A82, RawData!$A:$AJ, 27, FALSE) | Z82: =VLOOKUP($A82, RawData!$A:$AJ, 28, FALSE) -> 4.5940056 | AA82: =VLOOKUP($A82, RawData!$A:$AJ, 31, FALSE) -> -0.0402488 | AB82: =VLOOKUP($A82, RawData!$A:$AJ,32, FALSE) | AC82: =VLOOKUP($A82, RawData!$A:$AJ, 34, FALSE) -> 4.1899 | AD82: =VLOOKUP($A82, RawData!$A:$AJ, 35, FALSE) -> 1.73 | AE82: =VLOOKUP($A82, RawData!$A:$AJ, 36, FALSE) -> 216.93
A83: USIO | B83: Usio | C83: Lowest (old) | D83: [READ PITCH](https://community.microcapclub.com/forums/topic/3253-usio-usio/#comment-73541) | E83: =IFERROR(__xludf.DUMMYFUNCTION("IFERROR(HYPERLINK(REGEXEXTRACT(D83,""\(([^)]*)\)""),REGEXEXTRACT(D83,""\[([^\]]+)\]"")),"""") "),"READ PITCH") -> READ PITCH | F83: =VLOOKUP($A83, RawData!$A:$AJ, 33, FALSE) -> 37.357124 | G83: =VLOOKUP($A83, RawData!$A:$AJ, 2, FALSE) | H83: =VLOOKUP($A83, RawData!$A:$AJ, 3, FALSE) -> 0.0324 | I83: =VLOOKUP($A83, RawData!$A:$AJ, 4, FALSE) -> 0.22585636 | J83: =VLOOKUP($A83, RawData!$A:$AM, 37, FALSE) -> -0.9408 | K83: =VLOOKUP($A83, RawData!$A:$AM, 38, FALSE) | L83: =VLOOKUP($A83, RawData!$A:$AM, 39, FALSE) -> -0.027219826 | M83: =VLOOKUP($A83, RawData!$A:$AJ, 30, FALSE) -> -27.241072 | N83: =VLOOKUP($A83, RawData!$A:$AJ, 5, FALSE) -> -0.014199194 | O83: =VLOOKUP($A83, RawData!$A:$AJ, 6, FALSE) -> -1.1434889 | P83: =VLOOKUP($A83, RawData!$A:$AJ, 7, FALSE) | Q83: =VLOOKUP($A83, RawData!$A:$AJ, 8, FALSE) -> 0.2375 | R83: =VLOOKUP($A83, RawData!$A:$AJ, 11, FALSE) | S83: =VLOOKUP($A83, RawData!$A:$AJ, 13, FALSE) -> 10.50015 | T83: =VLOOKUP($A83, RawData!$A:$AJ, 14, FALSE) -> -0.29864204 | U83: =VLOOKUP($A83, RawData!$A:$AJ, 23, FALSE) -> -0.0037 | V83: =VLOOKUP($A83, RawData!$A:$AJ, 24, FALSE) | W83: =VLOOKUP($A83, RawData!$A:$AJ, 25, FALSE) | X83: =VLOOKUP($A83, RawData!$A:$AJ, 26, FALSE) | Y83: =VLOOKUP($A83, RawData!$A:$AJ, 27, FALSE) | Z83: =VLOOKUP($A83, RawData!$A:$AJ, 28, FALSE) -> 0.44695348 | AA83: =VLOOKUP($A83, RawData!$A:$AJ, 31, FALSE) -> 2.4407768 | AB83: =VLOOKUP($A83, RawData!$A:$AJ,32, FALSE) | AC83: =VLOOKUP($A83, RawData!$A:$AJ, 34, FALSE) -> 25.6284 | AD83: =VLOOKUP($A83, RawData!$A:$AJ, 35, FALSE) -> 1.37 | AE83: =VLOOKUP($A83, RawData!$A:$AJ, 36, FALSE) -> 27.31
A84: PXHI | B84: PhoneX Holdings | C84: Low Medium | D84: [READ PITCH](https://community.microcapclub.com/forums/topic/3174-phonex-holdings-pxhi/#comment-71870) | E84: =IFERROR(__xludf.DUMMYFUNCTION("IFERROR(HYPERLINK(REGEXEXTRACT(D84,""\(([^)]*)\)""),REGEXEXTRACT(D84,""\[([^\]]+)\]"")),"""") "),"READ PITCH") -> READ PITCH | F84: =VLOOKUP($A84, RawData!$A:$AJ, 33, FALSE) -> 66.427734 | G84: =VLOOKUP($A84, RawData!$A:$AJ, 2, FALSE) | H84: =VLOOKUP($A84, RawData!$A:$AJ, 3, FALSE) -> 0.1061 | I84: =VLOOKUP($A84, RawData!$A:$AJ, 4, FALSE) -> 0.7341018 | J84: =VLOOKUP($A84, RawData!$A:$AM, 37, FALSE) -> -10.69225 | K84: =VLOOKUP($A84, RawData!$A:$AM, 38, FALSE) | L84: =VLOOKUP($A84, RawData!$A:$AM, 39, FALSE) -> 0.18844342 | M84: =VLOOKUP($A84, RawData!$A:$AJ, 30, FALSE) -> -5.9165764 | N84: =VLOOKUP($A84, RawData!$A:$AJ, 5, FALSE) -> -0.40171218 | O84: =VLOOKUP($A84, RawData!$A:$AJ, 6, FALSE) -> 2.6766396 | P84: =VLOOKUP($A84, RawData!$A:$AJ, 7, FALSE) | Q84: =VLOOKUP($A84, RawData!$A:$AJ, 8, FALSE) -> 0.0556 | R84: =VLOOKUP($A84, RawData!$A:$AJ, 11, FALSE) | S84: =VLOOKUP($A84, RawData!$A:$AJ, 13, FALSE) -> -0.47704 | T84: =VLOOKUP($A84, RawData!$A:$AJ, 14, FALSE) -> 0.2767294 | U84: =VLOOKUP($A84, RawData!$A:$AJ, 23, FALSE) -> -1.0033 | V84: =VLOOKUP($A84, RawData!$A:$AJ, 24, FALSE) | W84: =VLOOKUP($A84, RawData!$A:$AJ, 25, FALSE) | X84: =VLOOKUP($A84, RawData!$A:$AJ, 26, FALSE) | Y84: =VLOOKUP($A84, RawData!$A:$AJ, 27, FALSE) -> No data | Z84: =VLOOKUP($A84, RawData!$A:$AJ, 28, FALSE) -> 0.7772175 | AA84: =VLOOKUP($A84, RawData!$A:$AJ, 31, FALSE) -> -132.61322 | AB84: =VLOOKUP($A84, RawData!$A:$AJ,32, FALSE) | AC84: =VLOOKUP($A84, RawData!$A:$AJ, 34, FALSE) -> 63.26181 | AD84: =VLOOKUP($A84, RawData!$A:$AJ, 35, FALSE) -> 1.7 | AE84: =VLOOKUP($A84, RawData!$A:$AJ, 36, FALSE) -> 33.91
A85: BEEM | B85: Beam Global | C85: Low | D85: [READ PITCH](https://community.microcapclub.com/forums/topic/4265-beam-global-beem/#comment-87607) | E85: =IFERROR(__xludf.DUMMYFUNCTION("IFERROR(HYPERLINK(REGEXEXTRACT(D85,""\(([^)]*)\)""),REGEXEXTRACT(D85,""\[([^\]]+)\]"")),"""") "),"READ PITCH") -> READ PITCH | F85: =VLOOKUP($A85, RawData!$A:$AJ, 33, FALSE) -> 31.683863 | G85: =VLOOKUP($A85, RawData!$A:$AJ, 2, FALSE) | H85: =VLOOKUP($A85, RawData!$A:$AJ, 3, FALSE) -> -0.5456 | I85: =VLOOKUP($A85, RawData!$A:$AJ, 4, FALSE) -> 0.43670586 | J85: =VLOOKUP($A85, RawData!$A:$AM, 37, FALSE) -> -25.925 | K85: =VLOOKUP($A85, RawData!$A:$AM, 38, FALSE) | L85: =VLOOKUP($A85, RawData!$A:$AM, 39, FALSE) -> 0.437743 | M85: =VLOOKUP($A85, RawData!$A:$AJ, 30, FALSE) -> -1.1962662 | N85: =VLOOKUP($A85, RawData!$A:$AJ, 5, FALSE) -> -1.6044359 | O85: =VLOOKUP($A85, RawData!$A:$AJ, 6, FALSE) -> 1.498465 | P85: =VLOOKUP($A85, RawData!$A:$AJ, 7, FALSE) | Q85: =VLOOKUP($A85, RawData!$A:$AJ, 8, FALSE) -> 0.1495 | R85: =VLOOKUP($A85, RawData!$A:$AJ, 11, FALSE) | S85: =VLOOKUP($A85, RawData!$A:$AJ, 13, FALSE) -> -6.654 | T85: =VLOOKUP($A85, RawData!$A:$AJ, 14, FALSE) -> 2.0819774 | U85: =VLOOKUP($A85, RawData!$A:$AJ, 23, FALSE) -> -0.5872 | V85: =VLOOKUP($A85, RawData!$A:$AJ, 24, FALSE) | W85: =VLOOKUP($A85, RawData!$A:$AJ, 25, FALSE) | X85: =VLOOKUP($A85, RawData!$A:$AJ, 26, FALSE) | Y85: =VLOOKUP($A85, RawData!$A:$AJ, 27, FALSE) | Z85: =VLOOKUP($A85, RawData!$A:$AJ, 28, FALSE) -> 1.2341405 | AA85: =VLOOKUP($A85, RawData!$A:$AJ, 31, FALSE) -> -4.6608357 | AB85: =VLOOKUP($A85, RawData!$A:$AJ,32, FALSE) | AC85: =VLOOKUP($A85, RawData!$A:$AJ, 34, FALSE) -> 31.0132 | AD85: =VLOOKUP($A85, RawData!$A:$AJ, 35, FALSE) -> 1.87 | AE85: =VLOOKUP($A85, RawData!$A:$AJ, 36, FALSE) -> 18.26
